Workbook

Sheet README
A1: Deliverable 2 — Household Aggregation Workbook (Read-Only Aggregation Layer)
A3: Purpose
A4: This workbook aggregates FINAL, accepted account-level outputs produced by Deliverable 1. It does NOT ingest raw transactions and does NOT perform ACB/FX/tax recomputation.
A6: How to use (3 steps)
A7: 1) Fill in households + accounts on the 'CONFIG' sheet.
A8: 2) Paste or link account-level outputs into 'INPUT_ACCOUNT_SUMMARY' and (optionally) 'INPUT_SECURITY_DETAIL'.
A9: 3) Review household rollups on 'HH_SUMMARY' and drill-down via filters on 'ACCOUNT_ROLLUP' / 'INPUT_SECURITY_DETAIL'.
A11: Reconciliation
A12: See 'CHECKS' for pass/fail comparisons between household totals and summed account totals.

Sheet CONFIG
A1: Configuration
A3: Base Currency | B3: CAD
A4: Period Start | B4: 2025-01-01
A5: Period End | B5: 2025-12-31
A7: Households (enter at least one)
A8: Household_ID | B8: Household_Name | C8: Notes
A31: Accounts (enter each account to be aggregated)
A32: Include | B32: Account_ID | C32: Account_Name | D32: Owner | E32: Household_ID | F32: Base_Currency | G32: Notes
A33: TRUE
A34: TRUE
A35: TRUE
A36: TRUE
A37: TRUE
A38: TRUE
A39: TRUE
A40: TRUE
A41: TRUE
A42: TRUE
A43: TRUE
A44: TRUE
... A232: TRUE

Sheet INPUT_ACCOUNT_SUMMARY
A1: Input: Account-level period outputs (paste from Deliverable 1)
A3: Account_ID | B3: Period_Start | C3: Period_End | D3: Begin_Balance_Base | E3: End_Balance_Base | F3: Net_Contrib_Base | G3: Income_Interest_Base | H3: Income_Dividends_Base | I3: Income_Other_Base | J3: Realized_GL_Base | K3: Fees_Base | L3: Taxes_Base | M3: Return_Period

Sheet INPUT_SECURITY_DETAIL
A1: Optional input: Security-level outputs (for security→account→household drill-down)
A3: Account_ID | B3: AsOfDate | C3: Security_ID | D3: Security_Name | E3: Asset_Class | F3: Currency | G3: Market_Value_Base | H3: Income_Interest_Base | I3: Income_Dividends_Base | J3: Income_Other_Base | K3: Realized_GL_Base | L3: Notes

Sheet ACCOUNT_ROLLUP
A1: Account Rollup (from INPUT_ACCOUNT_SUMMARY)
A3: Account_ID | B3: Account_Name | C3: Household_ID | D3: Begin_Balance_Base | E3: End_Balance_Base | F3: Net_Contrib_Base | G3: Income_Interest_Base | H3: Income_Dividends_Base | I3: Income_Other_Base | J3: Income_Total_Base | K3: Realized_GL_Base | L3: Fees_Base | M3: Taxes_Base | N3: Return_Period
A4: =IFERROR(INDEX(tblAccounts[Account_ID],1),"") | B4: =IF(A4="","",IFERROR(XLOOKUP(A4,tblAccounts[Account_ID],tblAccounts[Account_Name],""),"")) | C4: =IF(A4="","",IFERROR(XLOOKUP(A4,tblAccounts[Account_ID],tblAccounts[Household_ID],""),"")) | D4: =IF(A4="","",IF(IFERROR(XLOOKUP(A4,tblAccounts[Account_ID],tblAccounts[Include],FALSE),FALSE),SUMIFS(tblAcctSummary[Begin_Balance_Base],tblAcctSummary[Account_ID],A4),0)) | E4: =IF(A4="","",IF(IFERROR(XLOOKUP(A4,tblAccounts[Account_ID],tblAccounts[Include],FALSE),FALSE),SUMIFS(tblAcctSummary[End_Balance_Base],tblAcctSummary[Account_ID],A4),0)) | F4: =IF(A4="","",IF(IFERROR(XLOOKUP(A4,tblAccounts[Account_ID],tblAccounts[Include],FALSE),FALSE),SUMIFS(tblAcctSummary[Net_Contrib_Base],tblAcctSummary[Account_ID],A4),0)) | G4: =IF(A4="","",IF(IFERROR(XLOOKUP(A4,tblAccounts[Account_ID],tblAccounts[Include],FALSE),FALSE),SUMIFS(tblAcctSummary[Income_Interest_Base],tblAcctSummary[Account_ID],A4),0)) | H4: =IF(A4="","",IF(IFERROR(XLOOKUP(A4,tblAccounts[Account_ID],tblAccounts[Include],FALSE),FALSE),SUMIFS(tblAcctSummary[Income_Dividends_Base],tblAcctSummary[Account_ID],A4),0)) | I4: =IF(A4="","",IF(IFERROR(XLOOKUP(A4,tblAccounts[Account_ID],tblAccounts[Include],FALSE),FALSE),SUMIFS(tblAcctSummary[Income_Other_Base],tblAcctSummary[Account_ID],A4),0)) | J4: =IF(A4="","",SUM(G4:I4)) | K4: =IF(A4="","",IF(IFERROR(XLOOKUP(A4,tblAccounts[Account_ID],tblAccounts[Include],FALSE),FALSE),SUMIFS(tblAcctSummary[Realized_GL_Base],tblAcctSummary[Account_ID],A4),0)) | L4: =IF(A4="","",IF(IFERROR(XLOOKUP(A4,tblAccounts[Account_ID],tblAccounts[Include],FALSE),FALSE),SUMIFS(tblAcctSummary[Fees_Base],tblAcctSummary[Account_ID],A4),0)) | M4: =IF(A4="","",IF(IFERROR(XLOOKUP(A4,tblAccounts[Account_ID],tblAccounts[Include],FALSE),FALSE),SUMIFS(tblAcctSummary[Taxes_Base],tblAcctSummary[Account_ID],A4),0)) | N4: =IF(A4="","",IF(IFERROR(XLOOKUP(A4,tblAccounts[Account_ID],tblAccounts[Include],FALSE),FALSE),IFERROR(SUMPRODUCT(tblAcctSummary[Return_Period],tblAcctSummary[Begin_Balance_Base],--(tblAcctSummary[Account_ID]=A4))/IF(SUMIFS(tblAcctSummary[Begin_Balance_Base],tblAcctSummary[Account_ID],A4)=0,NA(),SUMIFS(tblAcctSummary[Begin_Balance_Base],tblAcctSummary[Account_ID],A4)),0),0))
A5: =IFERROR(INDEX(tblAccounts[Account_ID],2),"") | B5: =IF(A5="","",IFERROR(XLOOKUP(A5,tblAccounts[Account_ID],tblAccounts[Account_Name],""),"")) | C5: =IF(A5="","",IFERROR(XLOOKUP(A5,tblAccounts[Account_ID],tblAccounts[Household_ID],""),"")) | D5: =IF(A5="","",IF(IFERROR(XLOOKUP(A5,tblAccounts[Account_ID],tblAccounts[Include],FALSE),FALSE),SUMIFS(tblAcctSummary[Begin_Balance_Base],tblAcctSummary[Account_ID],A5),0)) | E5: =IF(A5="","",IF(IFERROR(XLOOKUP(A5,tblAccounts[Account_ID],tblAccounts[Include],FALSE),FALSE),SUMIFS(tblAcctSummary[End_Balance_Base],tblAcctSummary[Account_ID],A5),0)) | F5: =IF(A5="","",IF(IFERROR(XLOOKUP(A5,tblAccounts[Account_ID],tblAccounts[Include],FALSE),FALSE),SUMIFS(tblAcctSummary[Net_Contrib_Base],tblAcctSummary[Account_ID],A5),0)) | G5: =IF(A5="","",IF(IFERROR(XLOOKUP(A5,tblAccounts[Account_ID],tblAccounts[Include],FALSE),FALSE),SUMIFS(tblAcctSummary[Income_Interest_Base],tblAcctSummary[Account_ID],A5),0)) | H5: =IF(A5="","",IF(IFERROR(XLOOKUP(A5,tblAccounts[Account_ID],tblAccounts[Include],FALSE),FALSE),SUMIFS(tblAcctSummary[Income_Dividends_Base],tblAcctSummary[Account_ID],A5),0)) | I5: =IF(A5="","",IF(IFERROR(XLOOKUP(A5,tblAccounts[Account_ID],tblAccounts[Include],FALSE),FALSE),SUMIFS(tblAcctSummary[Income_Other_Base],tblAcctSummary[Account_ID],A5),0)) | J5: =IF(A5="","",SUM(G5:I5)) | K5: =IF(A5="","",IF(IFERROR(XLOOKUP(A5,tblAccounts[Account_ID],tblAccounts[Include],FALSE),FALSE),SUMIFS(tblAcctSummary[Realized_GL_Base],tblAcctSummary[Account_ID],A5),0)) | L5: =IF(A5="","",IF(IFERROR(XLOOKUP(A5,tblAccounts[Account_ID],tblAccounts[Include],FALSE),FALSE),SUMIFS(tblAcctSummary[Fees_Base],tblAcctSummary[Account_ID],A5),0)) | M5: =IF(A5="","",IF(IFERROR(XLOOKUP(A5,tblAccounts[Account_ID],tblAccounts[Include],FALSE),FALSE),SUMIFS(tblAcctSummary[Taxes_Base],tblAcctSummary[Account_ID],A5),0)) | N5: =IF(A5="","",IF(IFERROR(XLOOKUP(A5,tblAccounts[Account_ID],tblAccounts[Include],FALSE),FALSE),IFERROR(SUMPRODUCT(tblAcctSummary[Return_Period],tblAcctSummary[Begin_Balance_Base],--(tblAcctSummary[Account_ID]=A5))/IF(SUMIFS(tblAcctSummary[Begin_Balance_Base],tblAcctSummary[Account_ID],A5)=0,NA(),SUMIFS(tblAcctSummary[Begin_Balance_Base],tblAcctSummary[Account_ID],A5)),0),0))
A6: =IFERROR(INDEX(tblAccounts[Account_ID],3),"") | B6: =IF(A6="","",IFERROR(XLOOKUP(A6,tblAccounts[Account_ID],tblAccounts[Account_Name],""),"")) | C6: =IF(A6="","",IFERROR(XLOOKUP(A6,tblAccounts[Account_ID],tblAccounts[Household_ID],""),"")) | D6: =IF(A6="","",IF(IFERROR(XLOOKUP(A6,tblAccounts[Account_ID],tblAccounts[Include],FALSE),FALSE),SUMIFS(tblAcctSummary[Begin_Balance_Base],tblAcctSummary[Account_ID],A6),0)) | E6: =IF(A6="","",IF(IFERROR(XLOOKUP(A6,tblAccounts[Account_ID],tblAccounts[Include],FALSE),FALSE),SUMIFS(tblAcctSummary[End_Balance_Base],tblAcctSummary[Account_ID],A6),0)) | F6: =IF(A6="","",IF(IFERROR(XLOOKUP(A6,tblAccounts[Account_ID],tblAccounts[Include],FALSE),FALSE),SUMIFS(tblAcctSummary[Net_Contrib_Base],tblAcctSummary[Account_ID],A6),0)) | G6: =IF(A6="","",IF(IFERROR(XLOOKUP(A6,tblAccounts[Account_ID],tblAccounts[Include],FALSE),FALSE),SUMIFS(tblAcctSummary[Income_Interest_Base],tblAcctSummary[Account_ID],A6),0)) | H6: =IF(A6="","",IF(IFERROR(XLOOKUP(A6,tblAccounts[Account_ID],tblAccounts[Include],FALSE),FALSE),SUMIFS(tblAcctSummary[Income_Dividends_Base],tblAcctSummary[Account_ID],A6),0)) | I6: =IF(A6="","",IF(IFERROR(XLOOKUP(A6,tblAccounts[Account_ID],tblAccounts[Include],FALSE),FALSE),SUMIFS(tblAcctSummary[Income_Other_Base],tblAcctSummary[Account_ID],A6),0)) | J6: =IF(A6="","",SUM(G6:I6)) | K6: =IF(A6="","",IF(IFERROR(XLOOKUP(A6,tblAccounts[Account_ID],tblAccounts[Include],FALSE),FALSE),SUMIFS(tblAcctSummary[Realized_GL_Base],tblAcctSummary[Account_ID],A6),0)) | L6: =IF(A6="","",IF(IFERROR(XLOOKUP(A6,tblAccounts[Account_ID],tblAccounts[Include],FALSE),FALSE),SUMIFS(tblAcctSummary[Fees_Base],tblAcctSummary[Account_ID],A6),0)) | M6: =IF(A6="","",IF(IFERROR(XLOOKUP(A6,tblAccounts[Account_ID],tblAccounts[Include],FALSE),FALSE),SUMIFS(tblAcctSummary[Taxes_Base],tblAcctSummary[Account_ID],A6),0)) | N6: =IF(A6="","",IF(IFERROR(XLOOKUP(A6,tblAccounts[Account_ID],tblAccounts[Include],FALSE),FALSE),IFERROR(SUMPRODUCT(tblAcctSummary[Return_Period],tblAcctSummary[Begin_Balance_Base],--(tblAcctSummary[Account_ID]=A6))/IF(SUMIFS(tblAcctSummary[Begin_Balance_Base],tblAcctSummary[Account_ID],A6)=0,NA(),SUMIFS(tblAcctSummary[Begin_Balance_Base],tblAcctSummary[Account_ID],A6)),0),0))
A7: =IFERROR(INDEX(tblAccounts[Account_ID],4),"") | B7: =IF(A7="","",IFERROR(XLOOKUP(A7,tblAccounts[Account_ID],tblAccounts[Account_Name],""),"")) | C7: =IF(A7="","",IFERROR(XLOOKUP(A7,tblAccounts[Account_ID],tblAccounts[Household_ID],""),"")) | D7: =IF(A7="","",IF(IFERROR(XLOOKUP(A7,tblAccounts[Account_ID],tblAccounts[Include],FALSE),FALSE),SUMIFS(tblAcctSummary[Begin_Balance_Base],tblAcctSummary[Account_ID],A7),0)) | E7: =IF(A7="","",IF(IFERROR(XLOOKUP(A7,tblAccounts[Account_ID],tblAccounts[Include],FALSE),FALSE),SUMIFS(tblAcctSummary[End_Balance_Base],tblAcctSummary[Account_ID],A7),0)) | F7: =IF(A7="","",IF(IFERROR(XLOOKUP(A7,tblAccounts[Account_ID],tblAccounts[Include],FALSE),FALSE),SUMIFS(tblAcctSummary[Net_Contrib_Base],tblAcctSummary[Account_ID],A7),0)) | G7: =IF(A7="","",IF(IFERROR(XLOOKUP(A7,tblAccounts[Account_ID],tblAccounts[Include],FALSE),FALSE),SUMIFS(tblAcctSummary[Income_Interest_Base],tblAcctSummary[Account_ID],A7),0)) | H7: =IF(A7="","",IF(IFERROR(XLOOKUP(A7,tblAccounts[Account_ID],tblAccounts[Include],FALSE),FALSE),SUMIFS(tblAcctSummary[Income_Dividends_Base],tblAcctSummary[Account_ID],A7),0)) | I7: =IF(A7="","",IF(IFERROR(XLOOKUP(A7,tblAccounts[Account_ID],tblAccounts[Include],FALSE),FALSE),SUMIFS(tblAcctSummary[Income_Other_Base],tblAcctSummary[Account_ID],A7),0)) | J7: =IF(A7="","",SUM(G7:I7)) | K7: =IF(A7="","",IF(IFERROR(XLOOKUP(A7,tblAccounts[Account_ID],tblAccounts[Include],FALSE),FALSE),SUMIFS(tblAcctSummary[Realized_GL_Base],tblAcctSummary[Account_ID],A7),0)) | L7: =IF(A7="","",IF(IFERROR(XLOOKUP(A7,tblAccounts[Account_ID],tblAccounts[Include],FALSE),FALSE),SUMIFS(tblAcctSummary[Fees_Base],tblAcctSummary[Account_ID],A7),0)) | M7: =IF(A7="","",IF(IFERROR(XLOOKUP(A7,tblAccounts[Account_ID],tblAccounts[Include],FALSE),FALSE),SUMIFS(tblAcctSummary[Taxes_Base],tblAcctSummary[Account_ID],A7),0)) | N7: =IF(A7="","",IF(IFERROR(XLOOKUP(A7,tblAccounts[Account_ID],tblAccounts[Include],FALSE),FALSE),IFERROR(SUMPRODUCT(tblAcctSummary[Return_Period],tblAcctSummary[Begin_Balance_Base],--(tblAcctSummary[Account_ID]=A7))/IF(SUMIFS(tblAcctSummary[Begin_Balance_Base],tblAcctSummary[Account_ID],A7)=0,NA(),SUMIFS(tblAcctSummary[Begin_Balance_Base],tblAcctSummary[Account_ID],A7)),0),0))
A8: =IFERROR(INDEX(tblAccounts[Account_ID],5),"") | B8: =IF(A8="","",IFERROR(XLOOKUP(A8,tblAccounts[Account_ID],tblAccounts[Account_Name],""),"")) | C8: =IF(A8="","",IFERROR(XLOOKUP(A8,tblAccounts[Account_ID],tblAccounts[Household_ID],""),"")) | D8: =IF(A8="","",IF(IFERROR(XLOOKUP(A8,tblAccounts[Account_ID],tblAccounts[Include],FALSE),FALSE),SUMIFS(tblAcctSummary[Begin_Balance_Base],tblAcctSummary[Account_ID],A8),0)) | E8: =IF(A8="","",IF(IFERROR(XLOOKUP(A8,tblAccounts[Account_ID],tblAccounts[Include],FALSE),FALSE),SUMIFS(tblAcctSummary[End_Balance_Base],tblAcctSummary[Account_ID],A8),0)) | F8: =IF(A8="","",IF(IFERROR(XLOOKUP(A8,tblAccounts[Account_ID],tblAccounts[Include],FALSE),FALSE),SUMIFS(tblAcctSummary[Net_Contrib_Base],tblAcctSummary[Account_ID],A8),0)) | G8: =IF(A8="","",IF(IFERROR(XLOOKUP(A8,tblAccounts[Account_ID],tblAccounts[Include],FALSE),FALSE),SUMIFS(tblAcctSummary[Income_Interest_Base],tblAcctSummary[Account_ID],A8),0)) | H8: =IF(A8="","",IF(IFERROR(XLOOKUP(A8,tblAccounts[Account_ID],tblAccounts[Include],FALSE),FALSE),SUMIFS(tblAcctSummary[Income_Dividends_Base],tblAcctSummary[Account_ID],A8),0)) | I8: =IF(A8="","",IF(IFERROR(XLOOKUP(A8,tblAccounts[Account_ID],tblAccounts[Include],FALSE),FALSE),SUMIFS(tblAcctSummary[Income_Other_Base],tblAcctSummary[Account_ID],A8),0)) | J8: =IF(A8="","",SUM(G8:I8)) | K8: =IF(A8="","",IF(IFERROR(XLOOKUP(A8,tblAccounts[Account_ID],tblAccounts[Include],FALSE),FALSE),SUMIFS(tblAcctSummary[Realized_GL_Base],tblAcctSummary[Account_ID],A8),0)) | L8: =IF(A8="","",IF(IFERROR(XLOOKUP(A8,tblAccounts[Account_ID],tblAccounts[Include],FALSE),FALSE),SUMIFS(tblAcctSummary[Fees_Base],tblAcctSummary[Account_ID],A8),0)) | M8: =IF(A8="","",IF(IFERROR(XLOOKUP(A8,tblAccounts[Account_ID],tblAccounts[Include],FALSE),FALSE),SUMIFS(tblAcctSummary[Taxes_Base],tblAcctSummary[Account_ID],A8),0)) | N8: =IF(A8="","",IF(IFERROR(XLOOKUP(A8,tblAccounts[Account_ID],tblAccounts[Include],FALSE),FALSE),IFERROR(SUMPRODUCT(tblAcctSummary[Return_Period],tblAcctSummary[Begin_Balance_Base],--(tblAcctSummary[Account_ID]=A8))/IF(SUMIFS(tblAcctSummary[Begin_Balance_Base],tblAcctSummary[Account_ID],A8)=0,NA(),SUMIFS(tblAcctSummary[Begin_Balance_Base],tblAcctSummary[Account_ID],A8)),0),0))
A9: =IFERROR(INDEX(tblAccounts[Account_ID],6),"") | B9: =IF(A9="","",IFERROR(XLOOKUP(A9,tblAccounts[Account_ID],tblAccounts[Account_Name],""),"")) | C9: =IF(A9="","",IFERROR(XLOOKUP(A9,tblAccounts[Account_ID],tblAccounts[Household_ID],""),"")) | D9: =IF(A9="","",IF(IFERROR(XLOOKUP(A9,tblAccounts[Account_ID],tblAccounts[Include],FALSE),FALSE),SUMIFS(tblAcctSummary[Begin_Balance_Base],tblAcctSummary[Account_ID],A9),0)) | E9: =IF(A9="","",IF(IFERROR(XLOOKUP(A9,tblAccounts[Account_ID],tblAccounts[Include],FALSE),FALSE),SUMIFS(tblAcctSummary[End_Balance_Base],tblAcctSummary[Account_ID],A9),0)) | F9: =IF(A9="","",IF(IFERROR(XLOOKUP(A9,tblAccounts[Account_ID],tblAccounts[Include],FALSE),FALSE),SUMIFS(tblAcctSummary[Net_Contrib_Base],tblAcctSummary[Account_ID],A9),0)) | G9: =IF(A9="","",IF(IFERROR(XLOOKUP(A9,tblAccounts[Account_ID],tblAccounts[Include],FALSE),FALSE),SUMIFS(tblAcctSummary[Income_Interest_Base],tblAcctSummary[Account_ID],A9),0)) | H9: =IF(A9="","",IF(IFERROR(XLOOKUP(A9,tblAccounts[Account_ID],tblAccounts[Include],FALSE),FALSE),SUMIFS(tblAcctSummary[Income_Dividends_Base],tblAcctSummary[Account_ID],A9),0)) | I9: =IF(A9="","",IF(IFERROR(XLOOKUP(A9,tblAccounts[Account_ID],tblAccounts[Include],FALSE),FALSE),SUMIFS(tblAcctSummary[Income_Other_Base],tblAcctSummary[Account_ID],A9),0)) | J9: =IF(A9="","",SUM(G9:I9)) | K9: =IF(A9="","",IF(IFERROR(XLOOKUP(A9,tblAccounts[Account_ID],tblAccounts[Include],FALSE),FALSE),SUMIFS(tblAcctSummary[Realized_GL_Base],tblAcctSummary[Account_ID],A9),0)) | L9: =IF(A9="","",IF(IFERROR(XLOOKUP(A9,tblAccounts[Account_ID],tblAccounts[Include],FALSE),FALSE),SUMIFS(tblAcctSummary[Fees_Base],tblAcctSummary[Account_ID],A9),0)) | M9: =IF(A9="","",IF(IFERROR(XLOOKUP(A9,tblAccounts[Account_ID],tblAccounts[Include],FALSE),FALSE),SUMIFS(tblAcctSummary[Taxes_Base],tblAcctSummary[Account_ID],A9),0)) | N9: =IF(A9="","",IF(IFERROR(XLOOKUP(A9,tblAccounts[Account_ID],tblAccounts[Include],FALSE),FALSE),IFERROR(SUMPRODUCT(tblAcctSummary[Return_Period],tblAcctSummary[Begin_Balance_Base],--(tblAcctSummary[Account_ID]=A9))/IF(SUMIFS(tblAcctSummary[Begin_Balance_Base],tblAcctSummary[Account_ID],A9)=0,NA(),SUMIFS(tblAcctSummary[Begin_Balance_Base],tblAcctSummary[Account_ID],A9)),0),0))
A10: =IFERROR(INDEX(tblAccounts[Account_ID],7),"") | B10: =IF(A10="","",IFERROR(XLOOKUP(A10,tblAccounts[Account_ID],tblAccounts[Account_Name],""),"")) | C10: =IF(A10="","",IFERROR(XLOOKUP(A10,tblAccounts[Account_ID],tblAccounts[Household_ID],""),"")) | D10: =IF(A10="","",IF(IFERROR(XLOOKUP(A10,tblAccounts[Account_ID],tblAccounts[Include],FALSE),FALSE),SUMIFS(tblAcctSummary[Begin_Balance_Base],tblAcctSummary[Account_ID],A10),0)) | E10: =IF(A10="","",IF(IFERROR(XLOOKUP(A10,tblAccounts[Account_ID],tblAccounts[Include],FALSE),FALSE),SUMIFS(tblAcctSummary[End_Balance_Base],tblAcctSummary[Account_ID],A10),0)) | F10: =IF(A10="","",IF(IFERROR(XLOOKUP(A10,tblAccounts[Account_ID],tblAccounts[Include],FALSE),FALSE),SUMIFS(tblAcctSummary[Net_Contrib_Base],tblAcctSummary[Account_ID],A10),0)) | G10: =IF(A10="","",IF(IFERROR(XLOOKUP(A10,tblAccounts[Account_ID],tblAccounts[Include],FALSE),FALSE),SUMIFS(tblAcctSummary[Income_Interest_Base],tblAcctSummary[Account_ID],A10),0)) | H10: =IF(A10="","",IF(IFERROR(XLOOKUP(A10,tblAccounts[Account_ID],tblAccounts[Include],FALSE),FALSE),SUMIFS(tblAcctSummary[Income_Dividends_Base],tblAcctSummary[Account_ID],A10),0)) | I10: =IF(A10="","",IF(IFERROR(XLOOKUP(A10,tblAccounts[Account_ID],tblAccounts[Include],FALSE),FALSE),SUMIFS(tblAcctSummary[Income_Other_Base],tblAcctSummary[Account_ID],A10),0)) | J10: =IF(A10="","",SUM(G10:I10)) | K10: =IF(A10="","",IF(IFERROR(XLOOKUP(A10,tblAccounts[Account_ID],tblAccounts[Include],FALSE),FALSE),SUMIFS(tblAcctSummary[Realized_GL_Base],tblAcctSummary[Account_ID],A10),0)) | L10: =IF(A10="","",IF(IFERROR(XLOOKUP(A10,tblAccounts[Account_ID],tblAccounts[Include],FALSE),FALSE),SUMIFS(tblAcctSummary[Fees_Base],tblAcctSummary[Account_ID],A10),0)) | M10: =IF(A10="","",IF(IFERROR(XLOOKUP(A10,tblAccounts[Account_ID],tblAccounts[Include],FALSE),FALSE),SUMIFS(tblAcctSummary[Taxes_Base],tblAcctSummary[Account_ID],A10),0)) | N10: =IF(A10="","",IF(IFERROR(XLOOKUP(A10,tblAccounts[Account_ID],tblAccounts[Include],FALSE),FALSE),IFERROR(SUMPRODUCT(tblAcctSummary[Return_Period],tblAcctSummary[Begin_Balance_Base],--(tblAcctSummary[Account_ID]=A10))/IF(SUMIFS(tblAcctSummary[Begin_Balance_Base],tblAcctSummary[Account_ID],A10)=0,NA(),SUMIFS(tblAcctSummary[Begin_Balance_Base],tblAcctSummary[Account_ID],A10)),0),0))
A11: =IFERROR(INDEX(tblAccounts[Account_ID],8),"") | B11: =IF(A11="","",IFERROR(XLOOKUP(A11,tblAccounts[Account_ID],tblAccounts[Account_Name],""),"")) | C11: =IF(A11="","",IFERROR(XLOOKUP(A11,tblAccounts[Account_ID],tblAccounts[Household_ID],""),"")) | D11: =IF(A11="","",IF(IFERROR(XLOOKUP(A11,tblAccounts[Account_ID],tblAccounts[Include],FALSE),FALSE),SUMIFS(tblAcctSummary[Begin_Balance_Base],tblAcctSummary[Account_ID],A11),0)) | E11: =IF(A11="","",IF(IFERROR(XLOOKUP(A11,tblAccounts[Account_ID],tblAccounts[Include],FALSE),FALSE),SUMIFS(tblAcctSummary[End_Balance_Base],tblAcctSummary[Account_ID],A11),0)) | F11: =IF(A11="","",IF(IFERROR(XLOOKUP(A11,tblAccounts[Account_ID],tblAccounts[Include],FALSE),FALSE),SUMIFS(tblAcctSummary[Net_Contrib_Base],tblAcctSummary[Account_ID],A11),0)) | G11: =IF(A11="","",IF(IFERROR(XLOOKUP(A11,tblAccounts[Account_ID],tblAccounts[Include],FALSE),FALSE),SUMIFS(tblAcctSummary[Income_Interest_Base],tblAcctSummary[Account_ID],A11),0)) | H11: =IF(A11="","",IF(IFERROR(XLOOKUP(A11,tblAccounts[Account_ID],tblAccounts[Include],FALSE),FALSE),SUMIFS(tblAcctSummary[Income_Dividends_Base],tblAcctSummary[Account_ID],A11),0)) | I11: =IF(A11="","",IF(IFERROR(XLOOKUP(A11,tblAccounts[Account_ID],tblAccounts[Include],FALSE),FALSE),SUMIFS(tblAcctSummary[Income_Other_Base],tblAcctSummary[Account_ID],A11),0)) | J11: =IF(A11="","",SUM(G11:I11)) | K11: =IF(A11="","",IF(IFERROR(XLOOKUP(A11,tblAccounts[Account_ID],tblAccounts[Include],FALSE),FALSE),SUMIFS(tblAcctSummary[Realized_GL_Base],tblAcctSummary[Account_ID],A11),0)) | L11: =IF(A11="","",IF(IFERROR(XLOOKUP(A11,tblAccounts[Account_ID],tblAccounts[Include],FALSE),FALSE),SUMIFS(tblAcctSummary[Fees_Base],tblAcctSummary[Account_ID],A11),0)) | M11: =IF(A11="","",IF(IFERROR(XLOOKUP(A11,tblAccounts[Account_ID],tblAccounts[Include],FALSE),FALSE),SUMIFS(tblAcctSummary[Taxes_Base],tblAcctSummary[Account_ID],A11),0)) | N11: =IF(A11="","",IF(IFERROR(XLOOKUP(A11,tblAccounts[Account_ID],tblAccounts[Include],FALSE),FALSE),IFERROR(SUMPRODUCT(tblAcctSummary[Return_Period],tblAcctSummary[Begin_Balance_Base],--(tblAcctSummary[Account_ID]=A11))/IF(SUMIFS(tblAcctSummary[Begin_Balance_Base],tblAcctSummary[Account_ID],A11)=0,NA(),SUMIFS(tblAcctSummary[Begin_Balance_Base],tblAcctSummary[Account_ID],A11)),0),0))
A12: =IFERROR(INDEX(tblAccounts[Account_ID],9),"") | B12: =IF(A12="","",IFERROR(XLOOKUP(A12,tblAccounts[Account_ID],tblAccounts[Account_Name],""),"")) | C12: =IF(A12="","",IFERROR(XLOOKUP(A12,tblAccounts[Account_ID],tblAccounts[Household_ID],""),"")) | D12: =IF(A12="","",IF(IFERROR(XLOOKUP(A12,tblAccounts[Account_ID],tblAccounts[Include],FALSE),FALSE),SUMIFS(tblAcctSummary[Begin_Balance_Base],tblAcctSummary[Account_ID],A12),0)) | E12: =IF(A12="","",IF(IFERROR(XLOOKUP(A12,tblAccounts[Account_ID],tblAccounts[Include],FALSE),FALSE),SUMIFS(tblAcctSummary[End_Balance_Base],tblAcctSummary[Account_ID],A12),0)) | F12: =IF(A12="","",IF(IFERROR(XLOOKUP(A12,tblAccounts[Account_ID],tblAccounts[Include],FALSE),FALSE),SUMIFS(tblAcctSummary[Net_Contrib_Base],tblAcctSummary[Account_ID],A12),0)) | G12: =IF(A12="","",IF(IFERROR(XLOOKUP(A12,tblAccounts[Account_ID],tblAccounts[Include],FALSE),FALSE),SUMIFS(tblAcctSummary[Income_Interest_Base],tblAcctSummary[Account_ID],A12),0)) | H12: =IF(A12="","",IF(IFERROR(XLOOKUP(A12,tblAccounts[Account_ID],tblAccounts[Include],FALSE),FALSE),SUMIFS(tblAcctSummary[Income_Dividends_Base],tblAcctSummary[Account_ID],A12),0)) | I12: =IF(A12="","",IF(IFERROR(XLOOKUP(A12,tblAccounts[Account_ID],tblAccounts[Include],FALSE),FALSE),SUMIFS(tblAcctSummary[Income_Other_Base],tblAcctSummary[Account_ID],A12),0)) | J12: =IF(A12="","",SUM(G12:I12)) | K12: =IF(A12="","",IF(IFERROR(XLOOKUP(A12,tblAccounts[Account_ID],tblAccounts[Include],FALSE),FALSE),SUMIFS(tblAcctSummary[Realized_GL_Base],tblAcctSummary[Account_ID],A12),0)) | L12: =IF(A12="","",IF(IFERROR(XLOOKUP(A12,tblAccounts[Account_ID],tblAccounts[Include],FALSE),FALSE),SUMIFS(tblAcctSummary[Fees_Base],tblAcctSummary[Account_ID],A12),0)) | M12: =IF(A12="","",IF(IFERROR(XLOOKUP(A12,tblAccounts[Account_ID],tblAccounts[Include],FALSE),FALSE),SUMIFS(tblAcctSummary[Taxes_Base],tblAcctSummary[Account_ID],A12),0)) | N12: =IF(A12="","",IF(IFERROR(XLOOKUP(A12,tblAccounts[Account_ID],tblAccounts[Include],FALSE),FALSE),IFERROR(SUMPRODUCT(tblAcctSummary[Return_Period],tblAcctSummary[Begin_Balance_Base],--(tblAcctSummary[Account_ID]=A12))/IF(SUMIFS(tblAcctSummary[Begin_Balance_Base],tblAcctSummary[Account_ID],A12)=0,NA(),SUMIFS(tblAcctSummary[Begin_Balance_Base],tblAcctSummary[Account_ID],A12)),0),0))
A13: =IFERROR(INDEX(tblAccounts[Account_ID],10),"") | B13: =IF(A13="","",IFERROR(XLOOKUP(A13,tblAccounts[Account_ID],tblAccounts[Account_Name],""),"")) | C13: =IF(A13="","",IFERROR(XLOOKUP(A13,tblAccounts[Account_ID],tblAccounts[Household_ID],""),"")) | D13: =IF(A13="","",IF(IFERROR(XLOOKUP(A13,tblAccounts[Account_ID],tblAccounts[Include],FALSE),FALSE),SUMIFS(tblAcctSummary[Begin_Balance_Base],tblAcctSummary[Account_ID],A13),0)) | E13: =IF(A13="","",IF(IFERROR(XLOOKUP(A13,tblAccounts[Account_ID],tblAccounts[Include],FALSE),FALSE),SUMIFS(tblAcctSummary[End_Balance_Base],tblAcctSummary[Account_ID],A13),0)) | F13: =IF(A13="","",IF(IFERROR(XLOOKUP(A13,tblAccounts[Account_ID],tblAccounts[Include],FALSE),FALSE),SUMIFS(tblAcctSummary[Net_Contrib_Base],tblAcctSummary[Account_ID],A13),0)) | G13: =IF(A13="","",IF(IFERROR(XLOOKUP(A13,tblAccounts[Account_ID],tblAccounts[Include],FALSE),FALSE),SUMIFS(tblAcctSummary[Income_Interest_Base],tblAcctSummary[Account_ID],A13),0)) | H13: =IF(A13="","",IF(IFERROR(XLOOKUP(A13,tblAccounts[Account_ID],tblAccounts[Include],FALSE),FALSE),SUMIFS(tblAcctSummary[Income_Dividends_Base],tblAcctSummary[Account_ID],A13),0)) | I13: =IF(A13="","",IF(IFERROR(XLOOKUP(A13,tblAccounts[Account_ID],tblAccounts[Include],FALSE),FALSE),SUMIFS(tblAcctSummary[Income_Other_Base],tblAcctSummary[Account_ID],A13),0)) | J13: =IF(A13="","",SUM(G13:I13)) | K13: =IF(A13="","",IF(IFERROR(XLOOKUP(A13,tblAccounts[Account_ID],tblAccounts[Include],FALSE),FALSE),SUMIFS(tblAcctSummary[Realized_GL_Base],tblAcctSummary[Account_ID],A13),0)) | L13: =IF(A13="","",IF(IFERROR(XLOOKUP(A13,tblAccounts[Account_ID],tblAccounts[Include],FALSE),FALSE),SUMIFS(tblAcctSummary[Fees_Base],tblAcctSummary[Account_ID],A13),0)) | M13: =IF(A13="","",IF(IFERROR(XLOOKUP(A13,tblAccounts[Account_ID],tblAccounts[Include],FALSE),FALSE),SUMIFS(tblAcctSummary[Taxes_Base],tblAcctSummary[Account_ID],A13),0)) | N13: =IF(A13="","",IF(IFERROR(XLOOKUP(A13,tblAccounts[Account_ID],tblAccounts[Include],FALSE),FALSE),IFERROR(SUMPRODUCT(tblAcctSummary[Return_Period],tblAcctSummary[Begin_Balance_Base],--(tblAcctSummary[Account_ID]=A13))/IF(SUMIFS(tblAcctSummary[Begin_Balance_Base],tblAcctSummary[Account_ID],A13)=0,NA(),SUMIFS(tblAcctSummary[Begin_Balance_Base],tblAcctSummary[Account_ID],A13)),0),0))
A14: =IFERROR(INDEX(tblAccounts[Account_ID],11),"") | B14: =IF(A14="","",IFERROR(XLOOKUP(A14,tblAccounts[Account_ID],tblAccounts[Account_Name],""),"")) | C14: =IF(A14="","",IFERROR(XLOOKUP(A14,tblAccounts[Account_ID],tblAccounts[Household_ID],""),"")) | D14: =IF(A14="","",IF(IFERROR(XLOOKUP(A14,tblAccounts[Account_ID],tblAccounts[Include],FALSE),FALSE),SUMIFS(tblAcctSummary[Begin_Balance_Base],tblAcctSummary[Account_ID],A14),0)) | E14: =IF(A14="","",IF(IFERROR(XLOOKUP(A14,tblAccounts[Account_ID],tblAccounts[Include],FALSE),FALSE),SUMIFS(tblAcctSummary[End_Balance_Base],tblAcctSummary[Account_ID],A14),0)) | F14: =IF(A14="","",IF(IFERROR(XLOOKUP(A14,tblAccounts[Account_ID],tblAccounts[Include],FALSE),FALSE),SUMIFS(tblAcctSummary[Net_Contrib_Base],tblAcctSummary[Account_ID],A14),0)) | G14: =IF(A14="","",IF(IFERROR(XLOOKUP(A14,tblAccounts[Account_ID],tblAccounts[Include],FALSE),FALSE),SUMIFS(tblAcctSummary[Income_Interest_Base],tblAcctSummary[Account_ID],A14),0)) | H14: =IF(A14="","",IF(IFERROR(XLOOKUP(A14,tblAccounts[Account_ID],tblAccounts[Include],FALSE),FALSE),SUMIFS(tblAcctSummary[Income_Dividends_Base],tblAcctSummary[Account_ID],A14),0)) | I14: =IF(A14="","",IF(IFERROR(XLOOKUP(A14,tblAccounts[Account_ID],tblAccounts[Include],FALSE),FALSE),SUMIFS(tblAcctSummary[Income_Other_Base],tblAcctSummary[Account_ID],A14),0)) | J14: =IF(A14="","",SUM(G14:I14)) | K14: =IF(A14="","",IF(IFERROR(XLOOKUP(A14,tblAccounts[Account_ID],tblAccounts[Include],FALSE),FALSE),SUMIFS(tblAcctSummary[Realized_GL_Base],tblAcctSummary[Account_ID],A14),0)) | L14: =IF(A14="","",IF(IFERROR(XLOOKUP(A14,tblAccounts[Account_ID],tblAccounts[Include],FALSE),FALSE),SUMIFS(tblAcctSummary[Fees_Base],tblAcctSummary[Account_ID],A14),0)) | M14: =IF(A14="","",IF(IFERROR(XLOOKUP(A14,tblAccounts[Account_ID],tblAccounts[Include],FALSE),FALSE),SUMIFS(tblAcctSummary[Taxes_Base],tblAcctSummary[Account_ID],A14),0)) | N14: =IF(A14="","",IF(IFERROR(XLOOKUP(A14,tblAccounts[Account_ID],tblAccounts[Include],FALSE),FALSE),IFERROR(SUMPRODUCT(tblAcctSummary[Return_Period],tblAcctSummary[Begin_Balance_Base],--(tblAcctSummary[Account_ID]=A14))/IF(SUMIFS(tblAcctSummary[Begin_Balance_Base],tblAcctSummary[Account_ID],A14)=0,NA(),SUMIFS(tblAcctSummary[Begin_Balance_Base],tblAcctSummary[Account_ID],A14)),0),0))
A15: =IFERROR(INDEX(tblAccounts[Account_ID],12),"") | B15: =IF(A15="","",IFERROR(XLOOKUP(A15,tblAccounts[Account_ID],tblAccounts[Account_Name],""),"")) | C15: =IF(A15="","",IFERROR(XLOOKUP(A15,tblAccounts[Account_ID],tblAccounts[Household_ID],""),"")) | D15: =IF(A15="","",IF(IFERROR(XLOOKUP(A15,tblAccounts[Account_ID],tblAccounts[Include],FALSE),FALSE),SUMIFS(tblAcctSummary[Begin_Balance_Base],tblAcctSummary[Account_ID],A15),0)) | E15: =IF(A15="","",IF(IFERROR(XLOOKUP(A15,tblAccounts[Account_ID],tblAccounts[Include],FALSE),FALSE),SUMIFS(tblAcctSummary[End_Balance_Base],tblAcctSummary[Account_ID],A15),0)) | F15: =IF(A15="","",IF(IFERROR(XLOOKUP(A15,tblAccounts[Account_ID],tblAccounts[Include],FALSE),FALSE),SUMIFS(tblAcctSummary[Net_Contrib_Base],tblAcctSummary[Account_ID],A15),0)) | G15: =IF(A15="","",IF(IFERROR(XLOOKUP(A15,tblAccounts[Account_ID],tblAccounts[Include],FALSE),FALSE),SUMIFS(tblAcctSummary[Income_Interest_Base],tblAcctSummary[Account_ID],A15),0)) | H15: =IF(A15="","",IF(IFERROR(XLOOKUP(A15,tblAccounts[Account_ID],tblAccounts[Include],FALSE),FALSE),SUMIFS(tblAcctSummary[Income_Dividends_Base],tblAcctSummary[Account_ID],A15),0)) | I15: =IF(A15="","",IF(IFERROR(XLOOKUP(A15,tblAccounts[Account_ID],tblAccounts[Include],FALSE),FALSE),SUMIFS(tblAcctSummary[Income_Other_Base],tblAcctSummary[Account_ID],A15),0)) | J15: =IF(A15="","",SUM(G15:I15)) | K15: =IF(A15="","",IF(IFERROR(XLOOKUP(A15,tblAccounts[Account_ID],tblAccounts[Include],FALSE),FALSE),SUMIFS(tblAcctSummary[Realized_GL_Base],tblAcctSummary[Account_ID],A15),0)) | L15: =IF(A15="","",IF(IFERROR(XLOOKUP(A15,tblAccounts[Account_ID],tblAccounts[Include],FALSE),FALSE),SUMIFS(tblAcctSummary[Fees_Base],tblAcctSummary[Account_ID],A15),0)) | M15: =IF(A15="","",IF(IFERROR(XLOOKUP(A15,tblAccounts[Account_ID],tblAccounts[Include],FALSE),FALSE),SUMIFS(tblAcctSummary[Taxes_Base],tblAcctSummary[Account_ID],A15),0)) | N15: =IF(A15="","",IF(IFERROR(XLOOKUP(A15,tblAccounts[Account_ID],tblAccounts[Include],FALSE),FALSE),IFERROR(SUMPRODUCT(tblAcctSummary[Return_Period],tblAcctSummary[Begin_Balance_Base],--(tblAcctSummary[Account_ID]=A15))/IF(SUMIFS(tblAcctSummary[Begin_Balance_Base],tblAcctSummary[Account_ID],A15)=0,NA(),SUMIFS(tblAcctSummary[Begin_Balance_Base],tblAcctSummary[Account_ID],A15)),0),0))
A16: =IFERROR(INDEX(tblAccounts[Account_ID],13),"") | B16: =IF(A16="","",IFERROR(XLOOKUP(A16,tblAccounts[Account_ID],tblAccounts[Account_Name],""),"")) | C16: =IF(A16="","",IFERROR(XLOOKUP(A16,tblAccounts[Account_ID],tblAccounts[Household_ID],""),"")) | D16: =IF(A16="","",IF(IFERROR(XLOOKUP(A16,tblAccounts[Account_ID],tblAccounts[Include],FALSE),FALSE),SUMIFS(tblAcctSummary[Begin_Balance_Base],tblAcctSummary[Account_ID],A16),0)) | E16: =IF(A16="","",IF(IFERROR(XLOOKUP(A16,tblAccounts[Account_ID],tblAccounts[Include],FALSE),FALSE),SUMIFS(tblAcctSummary[End_Balance_Base],tblAcctSummary[Account_ID],A16),0)) | F16: =IF(A16="","",IF(IFERROR(XLOOKUP(A16,tblAccounts[Account_ID],tblAccounts[Include],FALSE),FALSE),SUMIFS(tblAcctSummary[Net_Contrib_Base],tblAcctSummary[Account_ID],A16),0)) | G16: =IF(A16="","",IF(IFERROR(XLOOKUP(A16,tblAccounts[Account_ID],tblAccounts[Include],FALSE),FALSE),SUMIFS(tblAcctSummary[Income_Interest_Base],tblAcctSummary[Account_ID],A16),0)) | H16: =IF(A16="","",IF(IFERROR(XLOOKUP(A16,tblAccounts[Account_ID],tblAccounts[Include],FALSE),FALSE),SUMIFS(tblAcctSummary[Income_Dividends_Base],tblAcctSummary[Account_ID],A16),0)) | I16: =IF(A16="","",IF(IFERROR(XLOOKUP(A16,tblAccounts[Account_ID],tblAccounts[Include],FALSE),FALSE),SUMIFS(tblAcctSummary[Income_Other_Base],tblAcctSummary[Account_ID],A16),0)) | J16: =IF(A16="","",SUM(G16:I16)) | K16: =IF(A16="","",IF(IFERROR(XLOOKUP(A16,tblAccounts[Account_ID],tblAccounts[Include],FALSE),FALSE),SUMIFS(tblAcctSummary[Realized_GL_Base],tblAcctSummary[Account_ID],A16),0)) | L16: =IF(A16="","",IF(IFERROR(XLOOKUP(A16,tblAccounts[Account_ID],tblAccounts[Include],FALSE),FALSE),SUMIFS(tblAcctSummary[Fees_Base],tblAcctSummary[Account_ID],A16),0)) | M16: =IF(A16="","",IF(IFERROR(XLOOKUP(A16,tblAccounts[Account_ID],tblAccounts[Include],FALSE),FALSE),SUMIFS(tblAcctSummary[Taxes_Base],tblAcctSummary[Account_ID],A16),0)) | N16: =IF(A16="","",IF(IFERROR(XLOOKUP(A16,tblAccounts[Account_ID],tblAccounts[Include],FALSE),FALSE),IFERROR(SUMPRODUCT(tblAcctSummary[Return_Period],tblAcctSummary[Begin_Balance_Base],--(tblAcctSummary[Account_ID]=A16))/IF(SUMIFS(tblAcctSummary[Begin_Balance_Base],tblAcctSummary[Account_ID],A16)=0,NA(),SUMIFS(tblAcctSummary[Begin_Balance_Base],tblAcctSummary[Account_ID],A16)),0),0))
A17: =IFERROR(INDEX(tblAccounts[Account_ID],14),"") | B17: =IF(A17="","",IFERROR(XLOOKUP(A17,tblAccounts[Account_ID],tblAccounts[Account_Name],""),"")) | C17: =IF(A17="","",IFERROR(XLOOKUP(A17,tblAccounts[Account_ID],tblAccounts[Household_ID],""),"")) | D17: =IF(A17="","",IF(IFERROR(XLOOKUP(A17,tblAccounts[Account_ID],tblAccounts[Include],FALSE),FALSE),SUMIFS(tblAcctSummary[Begin_Balance_Base],tblAcctSummary[Account_ID],A17),0)) | E17: =IF(A17="","",IF(IFERROR(XLOOKUP(A17,tblAccounts[Account_ID],tblAccounts[Include],FALSE),FALSE),SUMIFS(tblAcctSummary[End_Balance_Base],tblAcctSummary[Account_ID],A17),0)) | F17: =IF(A17="","",IF(IFERROR(XLOOKUP(A17,tblAccounts[Account_ID],tblAccounts[Include],FALSE),FALSE),SUMIFS(tblAcctSummary[Net_Contrib_Base],tblAcctSummary[Account_ID],A17),0)) | G17: =IF(A17="","",IF(IFERROR(XLOOKUP(A17,tblAccounts[Account_ID],tblAccounts[Include],FALSE),FALSE),SUMIFS(tblAcctSummary[Income_Interest_Base],tblAcctSummary[Account_ID],A17),0)) | H17: =IF(A17="","",IF(IFERROR(XLOOKUP(A17,tblAccounts[Account_ID],tblAccounts[Include],FALSE),FALSE),SUMIFS(tblAcctSummary[Income_Dividends_Base],tblAcctSummary[Account_ID],A17),0)) | I17: =IF(A17="","",IF(IFERROR(XLOOKUP(A17,tblAccounts[Account_ID],tblAccounts[Include],FALSE),FALSE),SUMIFS(tblAcctSummary[Income_Other_Base],tblAcctSummary[Account_ID],A17),0)) | J17: =IF(A17="","",SUM(G17:I17)) | K17: =IF(A17="","",IF(IFERROR(XLOOKUP(A17,tblAccounts[Account_ID],tblAccounts[Include],FALSE),FALSE),SUMIFS(tblAcctSummary[Realized_GL_Base],tblAcctSummary[Account_ID],A17),0)) | L17: =IF(A17="","",IF(IFERROR(XLOOKUP(A17,tblAccounts[Account_ID],tblAccounts[Include],FALSE),FALSE),SUMIFS(tblAcctSummary[Fees_Base],tblAcctSummary[Account_ID],A17),0)) | M17: =IF(A17="","",IF(IFERROR(XLOOKUP(A17,tblAccounts[Account_ID],tblAccounts[Include],FALSE),FALSE),SUMIFS(tblAcctSummary[Taxes_Base],tblAcctSummary[Account_ID],A17),0)) | N17: =IF(A17="","",IF(IFERROR(XLOOKUP(A17,tblAccounts[Account_ID],tblAccounts[Include],FALSE),FALSE),IFERROR(SUMPRODUCT(tblAcctSummary[Return_Period],tblAcctSummary[Begin_Balance_Base],--(tblAcctSummary[Account_ID]=A17))/IF(SUMIFS(tblAcctSummary[Begin_Balance_Base],tblAcctSummary[Account_ID],A17)=0,NA(),SUMIFS(tblAcctSummary[Begin_Balance_Base],tblAcctSummary[Account_ID],A17)),0),0))
A18: =IFERROR(INDEX(tblAccounts[Account_ID],15),"") | B18: =IF(A18="","",IFERROR(XLOOKUP(A18,tblAccounts[Account_ID],tblAccounts[Account_Name],""),"")) | C18: =IF(A18="","",IFERROR(XLOOKUP(A18,tblAccounts[Account_ID],tblAccounts[Household_ID],""),"")) | D18: =IF(A18="","",IF(IFERROR(XLOOKUP(A18,tblAccounts[Account_ID],tblAccounts[Include],FALSE),FALSE),SUMIFS(tblAcctSummary[Begin_Balance_Base],tblAcctSummary[Account_ID],A18),0)) | E18: =IF(A18="","",IF(IFERROR(XLOOKUP(A18,tblAccounts[Account_ID],tblAccounts[Include],FALSE),FALSE),SUMIFS(tblAcctSummary[End_Balance_Base],tblAcctSummary[Account_ID],A18),0)) | F18: =IF(A18="","",IF(IFERROR(XLOOKUP(A18,tblAccounts[Account_ID],tblAccounts[Include],FALSE),FALSE),SUMIFS(tblAcctSummary[Net_Contrib_Base],tblAcctSummary[Account_ID],A18),0)) | G18: =IF(A18="","",IF(IFERROR(XLOOKUP(A18,tblAccounts[Account_ID],tblAccounts[Include],FALSE),FALSE),SUMIFS(tblAcctSummary[Income_Interest_Base],tblAcctSummary[Account_ID],A18),0)) | H18: =IF(A18="","",IF(IFERROR(XLOOKUP(A18,tblAccounts[Account_ID],tblAccounts[Include],FALSE),FALSE),SUMIFS(tblAcctSummary[Income_Dividends_Base],tblAcctSummary[Account_ID],A18),0)) | I18: =IF(A18="","",IF(IFERROR(XLOOKUP(A18,tblAccounts[Account_ID],tblAccounts[Include],FALSE),FALSE),SUMIFS(tblAcctSummary[Income_Other_Base],tblAcctSummary[Account_ID],A18),0)) | J18: =IF(A18="","",SUM(G18:I18)) | K18: =IF(A18="","",IF(IFERROR(XLOOKUP(A18,tblAccounts[Account_ID],tblAccounts[Include],FALSE),FALSE),SUMIFS(tblAcctSummary[Realized_GL_Base],tblAcctSummary[Account_ID],A18),0)) | L18: =IF(A18="","",IF(IFERROR(XLOOKUP(A18,tblAccounts[Account_ID],tblAccounts[Include],FALSE),FALSE),SUMIFS(tblAcctSummary[Fees_Base],tblAcctSummary[Account_ID],A18),0)) | M18: =IF(A18="","",IF(IFERROR(XLOOKUP(A18,tblAccounts[Account_ID],tblAccounts[Include],FALSE),FALSE),SUMIFS(tblAcctSummary[Taxes_Base],tblAcctSummary[Account_ID],A18),0)) | N18: =IF(A18="","",IF(IFERROR(XLOOKUP(A18,tblAccounts[Account_ID],tblAccounts[Include],FALSE),FALSE),IFERROR(SUMPRODUCT(tblAcctSummary[Return_Period],tblAcctSummary[Begin_Balance_Base],--(tblAcctSummary[Account_ID]=A18))/IF(SUMIFS(tblAcctSummary[Begin_Balance_Base],tblAcctSummary[Account_ID],A18)=0,NA(),SUMIFS(tblAcctSummary[Begin_Balance_Base],tblAcctSummary[Account_ID],A18)),0),0))
A19: =IFERROR(INDEX(tblAccounts[Account_ID],16),"") | B19: =IF(A19="","",IFERROR(XLOOKUP(A19,tblAccounts[Account_ID],tblAccounts[Account_Name],""),"")) | C19: =IF(A19="","",IFERROR(XLOOKUP(A19,tblAccounts[Account_ID],tblAccounts[Household_ID],""),"")) | D19: =IF(A19="","",IF(IFERROR(XLOOKUP(A19,tblAccounts[Account_ID],tblAccounts[Include],FALSE),FALSE),SUMIFS(tblAcctSummary[Begin_Balance_Base],tblAcctSummary[Account_ID],A19),0)) | E19: =IF(A19="","",IF(IFERROR(XLOOKUP(A19,tblAccounts[Account_ID],tblAccounts[Include],FALSE),FALSE),SUMIFS(tblAcctSummary[End_Balance_Base],tblAcctSummary[Account_ID],A19),0)) | F19: =IF(A19="","",IF(IFERROR(XLOOKUP(A19,tblAccounts[Account_ID],tblAccounts[Include],FALSE),FALSE),SUMIFS(tblAcctSummary[Net_Contrib_Base],tblAcctSummary[Account_ID],A19),0)) | G19: =IF(A19="","",IF(IFERROR(XLOOKUP(A19,tblAccounts[Account_ID],tblAccounts[Include],FALSE),FALSE),SUMIFS(tblAcctSummary[Income_Interest_Base],tblAcctSummary[Account_ID],A19),0)) | H19: =IF(A19="","",IF(IFERROR(XLOOKUP(A19,tblAccounts[Account_ID],tblAccounts[Include],FALSE),FALSE),SUMIFS(tblAcctSummary[Income_Dividends_Base],tblAcctSummary[Account_ID],A19),0)) | I19: =IF(A19="","",IF(IFERROR(XLOOKUP(A19,tblAccounts[Account_ID],tblAccounts[Include],FALSE),FALSE),SUMIFS(tblAcctSummary[Income_Other_Base],tblAcctSummary[Account_ID],A19),0)) | J19: =IF(A19="","",SUM(G19:I19)) | K19: =IF(A19="","",IF(IFERROR(XLOOKUP(A19,tblAccounts[Account_ID],tblAccounts[Include],FALSE),FALSE),SUMIFS(tblAcctSummary[Realized_GL_Base],tblAcctSummary[Account_ID],A19),0)) | L19: =IF(A19="","",IF(IFERROR(XLOOKUP(A19,tblAccounts[Account_ID],tblAccounts[Include],FALSE),FALSE),SUMIFS(tblAcctSummary[Fees_Base],tblAcctSummary[Account_ID],A19),0)) | M19: =IF(A19="","",IF(IFERROR(XLOOKUP(A19,tblAccounts[Account_ID],tblAccounts[Include],FALSE),FALSE),SUMIFS(tblAcctSummary[Taxes_Base],tblAcctSummary[Account_ID],A19),0)) | N19: =IF(A19="","",IF(IFERROR(XLOOKUP(A19,tblAccounts[Account_ID],tblAccounts[Include],FALSE),FALSE),IFERROR(SUMPRODUCT(tblAcctSummary[Return_Period],tblAcctSummary[Begin_Balance_Base],--(tblAcctSummary[Account_ID]=A19))/IF(SUMIFS(tblAcctSummary[Begin_Balance_Base],tblAcctSummary[Account_ID],A19)=0,NA(),SUMIFS(tblAcctSummary[Begin_Balance_Base],tblAcctSummary[Account_ID],A19)),0),0))
A20: =IFERROR(INDEX(tblAccounts[Account_ID],17),"") | B20: =IF(A20="","",IFERROR(XLOOKUP(A20,tblAccounts[Account_ID],tblAccounts[Account_Name],""),"")) | C20: =IF(A20="","",IFERROR(XLOOKUP(A20,tblAccounts[Account_ID],tblAccounts[Household_ID],""),"")) | D20: =IF(A20="","",IF(IFERROR(XLOOKUP(A20,tblAccounts[Account_ID],tblAccounts[Include],FALSE),FALSE),SUMIFS(tblAcctSummary[Begin_Balance_Base],tblAcctSummary[Account_ID],A20),0)) | E20: =IF(A20="","",IF(IFERROR(XLOOKUP(A20,tblAccounts[Account_ID],tblAccounts[Include],FALSE),FALSE),SUMIFS(tblAcctSummary[End_Balance_Base],tblAcctSummary[Account_ID],A20),0)) | F20: =IF(A20="","",IF(IFERROR(XLOOKUP(A20,tblAccounts[Account_ID],tblAccounts[Include],FALSE),FALSE),SUMIFS(tblAcctSummary[Net_Contrib_Base],tblAcctSummary[Account_ID],A20),0)) | G20: =IF(A20="","",IF(IFERROR(XLOOKUP(A20,tblAccounts[Account_ID],tblAccounts[Include],FALSE),FALSE),SUMIFS(tblAcctSummary[Income_Interest_Base],tblAcctSummary[Account_ID],A20),0)) | H20: =IF(A20="","",IF(IFERROR(XLOOKUP(A20,tblAccounts[Account_ID],tblAccounts[Include],FALSE),FALSE),SUMIFS(tblAcctSummary[Income_Dividends_Base],tblAcctSummary[Account_ID],A20),0)) | I20: =IF(A20="","",IF(IFERROR(XLOOKUP(A20,tblAccounts[Account_ID],tblAccounts[Include],FALSE),FALSE),SUMIFS(tblAcctSummary[Income_Other_Base],tblAcctSummary[Account_ID],A20),0)) | J20: =IF(A20="","",SUM(G20:I20)) | K20: =IF(A20="","",IF(IFERROR(XLOOKUP(A20,tblAccounts[Account_ID],tblAccounts[Include],FALSE),FALSE),SUMIFS(tblAcctSummary[Realized_GL_Base],tblAcctSummary[Account_ID],A20),0)) | L20: =IF(A20="","",IF(IFERROR(XLOOKUP(A20,tblAccounts[Account_ID],tblAccounts[Include],FALSE),FALSE),SUMIFS(tblAcctSummary[Fees_Base],tblAcctSummary[Account_ID],A20),0)) | M20: =IF(A20="","",IF(IFERROR(XLOOKUP(A20,tblAccounts[Account_ID],tblAccounts[Include],FALSE),FALSE),SUMIFS(tblAcctSummary[Taxes_Base],tblAcctSummary[Account_ID],A20),0)) | N20: =IF(A20="","",IF(IFERROR(XLOOKUP(A20,tblAccounts[Account_ID],tblAccounts[Include],FALSE),FALSE),IFERROR(SUMPRODUCT(tblAcctSummary[Return_Period],tblAcctSummary[Begin_Balance_Base],--(tblAcctSummary[Account_ID]=A20))/IF(SUMIFS(tblAcctSummary[Begin_Balance_Base],tblAcctSummary[Account_ID],A20)=0,NA(),SUMIFS(tblAcctSummary[Begin_Balance_Base],tblAcctSummary[Account_ID],A20)),0),0))
A21: =IFERROR(INDEX(tblAccounts[Account_ID],18),"") | B21: =IF(A21="","",IFERROR(XLOOKUP(A21,tblAccounts[Account_ID],tblAccounts[Account_Name],""),"")) | C21: =IF(A21="","",IFERROR(XLOOKUP(A21,tblAccounts[Account_ID],tblAccounts[Household_ID],""),"")) | D21: =IF(A21="","",IF(IFERROR(XLOOKUP(A21,tblAccounts[Account_ID],tblAccounts[Include],FALSE),FALSE),SUMIFS(tblAcctSummary[Begin_Balance_Base],tblAcctSummary[Account_ID],A21),0)) | E21: =IF(A21="","",IF(IFERROR(XLOOKUP(A21,tblAccounts[Account_ID],tblAccounts[Include],FALSE),FALSE),SUMIFS(tblAcctSummary[End_Balance_Base],tblAcctSummary[Account_ID],A21),0)) | F21: =IF(A21="","",IF(IFERROR(XLOOKUP(A21,tblAccounts[Account_ID],tblAccounts[Include],FALSE),FALSE),SUMIFS(tblAcctSummary[Net_Contrib_Base],tblAcctSummary[Account_ID],A21),0)) | G21: =IF(A21="","",IF(IFERROR(XLOOKUP(A21,tblAccounts[Account_ID],tblAccounts[Include],FALSE),FALSE),SUMIFS(tblAcctSummary[Income_Interest_Base],tblAcctSummary[Account_ID],A21),0)) | H21: =IF(A21="","",IF(IFERROR(XLOOKUP(A21,tblAccounts[Account_ID],tblAccounts[Include],FALSE),FALSE),SUMIFS(tblAcctSummary[Income_Dividends_Base],tblAcctSummary[Account_ID],A21),0)) | I21: =IF(A21="","",IF(IFERROR(XLOOKUP(A21,tblAccounts[Account_ID],tblAccounts[Include],FALSE),FALSE),SUMIFS(tblAcctSummary[Income_Other_Base],tblAcctSummary[Account_ID],A21),0)) | J21: =IF(A21="","",SUM(G21:I21)) | K21: =IF(A21="","",IF(IFERROR(XLOOKUP(A21,tblAccounts[Account_ID],tblAccounts[Include],FALSE),FALSE),SUMIFS(tblAcctSummary[Realized_GL_Base],tblAcctSummary[Account_ID],A21),0)) | L21: =IF(A21="","",IF(IFERROR(XLOOKUP(A21,tblAccounts[Account_ID],tblAccounts[Include],FALSE),FALSE),SUMIFS(tblAcctSummary[Fees_Base],tblAcctSummary[Account_ID],A21),0)) | M21: =IF(A21="","",IF(IFERROR(XLOOKUP(A21,tblAccounts[Account_ID],tblAccounts[Include],FALSE),FALSE),SUMIFS(tblAcctSummary[Taxes_Base],tblAcctSummary[Account_ID],A21),0)) | N21: =IF(A21="","",IF(IFERROR(XLOOKUP(A21,tblAccounts[Account_ID],tblAccounts[Include],FALSE),FALSE),IFERROR(SUMPRODUCT(tblAcctSummary[Return_Period],tblAcctSummary[Begin_Balance_Base],--(tblAcctSummary[Account_ID]=A21))/IF(SUMIFS(tblAcctSummary[Begin_Balance_Base],tblAcctSummary[Account_ID],A21)=0,NA(),SUMIFS(tblAcctSummary[Begin_Balance_Base],tblAcctSummary[Account_ID],A21)),0),0))
A22: =IFERROR(INDEX(tblAccounts[Account_ID],19),"") | B22: =IF(A22="","",IFERROR(XLOOKUP(A22,tblAccounts[Account_ID],tblAccounts[Account_Name],""),"")) | C22: =IF(A22="","",IFERROR(XLOOKUP(A22,tblAccounts[Account_ID],tblAccounts[Household_ID],""),"")) | D22: =IF(A22="","",IF(IFERROR(XLOOKUP(A22,tblAccounts[Account_ID],tblAccounts[Include],FALSE),FALSE),SUMIFS(tblAcctSummary[Begin_Balance_Base],tblAcctSummary[Account_ID],A22),0)) | E22: =IF(A22="","",IF(IFERROR(XLOOKUP(A22,tblAccounts[Account_ID],tblAccounts[Include],FALSE),FALSE),SUMIFS(tblAcctSummary[End_Balance_Base],tblAcctSummary[Account_ID],A22),0)) | F22: =IF(A22="","",IF(IFERROR(XLOOKUP(A22,tblAccounts[Account_ID],tblAccounts[Include],FALSE),FALSE),SUMIFS(tblAcctSummary[Net_Contrib_Base],tblAcctSummary[Account_ID],A22),0)) | G22: =IF(A22="","",IF(IFERROR(XLOOKUP(A22,tblAccounts[Account_ID],tblAccounts[Include],FALSE),FALSE),SUMIFS(tblAcctSummary[Income_Interest_Base],tblAcctSummary[Account_ID],A22),0)) | H22: =IF(A22="","",IF(IFERROR(XLOOKUP(A22,tblAccounts[Account_ID],tblAccounts[Include],FALSE),FALSE),SUMIFS(tblAcctSummary[Income_Dividends_Base],tblAcctSummary[Account_ID],A22),0)) | I22: =IF(A22="","",IF(IFERROR(XLOOKUP(A22,tblAccounts[Account_ID],tblAccounts[Include],FALSE),FALSE),SUMIFS(tblAcctSummary[Income_Other_Base],tblAcctSummary[Account_ID],A22),0)) | J22: =IF(A22="","",SUM(G22:I22)) | K22: =IF(A22="","",IF(IFERROR(XLOOKUP(A22,tblAccounts[Account_ID],tblAccounts[Include],FALSE),FALSE),SUMIFS(tblAcctSummary[Realized_GL_Base],tblAcctSummary[Account_ID],A22),0)) | L22: =IF(A22="","",IF(IFERROR(XLOOKUP(A22,tblAccounts[Account_ID],tblAccounts[Include],FALSE),FALSE),SUMIFS(tblAcctSummary[Fees_Base],tblAcctSummary[Account_ID],A22),0)) | M22: =IF(A22="","",IF(IFERROR(XLOOKUP(A22,tblAccounts[Account_ID],tblAccounts[Include],FALSE),FALSE),SUMIFS(tblAcctSummary[Taxes_Base],tblAcctSummary[Account_ID],A22),0)) | N22: =IF(A22="","",IF(IFERROR(XLOOKUP(A22,tblAccounts[Account_ID],tblAccounts[Include],FALSE),FALSE),IFERROR(SUMPRODUCT(tblAcctSummary[Return_Period],tblAcctSummary[Begin_Balance_Base],--(tblAcctSummary[Account_ID]=A22))/IF(SUMIFS(tblAcctSummary[Begin_Balance_Base],tblAcctSummary[Account_ID],A22)=0,NA(),SUMIFS(tblAcctSummary[Begin_Balance_Base],tblAcctSummary[Account_ID],A22)),0),0))
A23: =IFERROR(INDEX(tblAccounts[Account_ID],20),"") | B23: =IF(A23="","",IFERROR(XLOOKUP(A23,tblAccounts[Account_ID],tblAccounts[Account_Name],""),"")) | C23: =IF(A23="","",IFERROR(XLOOKUP(A23,tblAccounts[Account_ID],tblAccounts[Household_ID],""),"")) | D23: =IF(A23="","",IF(IFERROR(XLOOKUP(A23,tblAccounts[Account_ID],tblAccounts[Include],FALSE),FALSE),SUMIFS(tblAcctSummary[Begin_Balance_Base],tblAcctSummary[Account_ID],A23),0)) | E23: =IF(A23="","",IF(IFERROR(XLOOKUP(A23,tblAccounts[Account_ID],tblAccounts[Include],FALSE),FALSE),SUMIFS(tblAcctSummary[End_Balance_Base],tblAcctSummary[Account_ID],A23),0)) | F23: =IF(A23="","",IF(IFERROR(XLOOKUP(A23,tblAccounts[Account_ID],tblAccounts[Include],FALSE),FALSE),SUMIFS(tblAcctSummary[Net_Contrib_Base],tblAcctSummary[Account_ID],A23),0)) | G23: =IF(A23="","",IF(IFERROR(XLOOKUP(A23,tblAccounts[Account_ID],tblAccounts[Include],FALSE),FALSE),SUMIFS(tblAcctSummary[Income_Interest_Base],tblAcctSummary[Account_ID],A23),0)) | H23: =IF(A23="","",IF(IFERROR(XLOOKUP(A23,tblAccounts[Account_ID],tblAccounts[Include],FALSE),FALSE),SUMIFS(tblAcctSummary[Income_Dividends_Base],tblAcctSummary[Account_ID],A23),0)) | I23: =IF(A23="","",IF(IFERROR(XLOOKUP(A23,tblAccounts[Account_ID],tblAccounts[Include],FALSE),FALSE),SUMIFS(tblAcctSummary[Income_Other_Base],tblAcctSummary[Account_ID],A23),0)) | J23: =IF(A23="","",SUM(G23:I23)) | K23: =IF(A23="","",IF(IFERROR(XLOOKUP(A23,tblAccounts[Account_ID],tblAccounts[Include],FALSE),FALSE),SUMIFS(tblAcctSummary[Realized_GL_Base],tblAcctSummary[Account_ID],A23),0)) | L23: =IF(A23="","",IF(IFERROR(XLOOKUP(A23,tblAccounts[Account_ID],tblAccounts[Include],FALSE),FALSE),SUMIFS(tblAcctSummary[Fees_Base],tblAcctSummary[Account_ID],A23),0)) | M23: =IF(A23="","",IF(IFERROR(XLOOKUP(A23,tblAccounts[Account_ID],tblAccounts[Include],FALSE),FALSE),SUMIFS(tblAcctSummary[Taxes_Base],tblAcctSummary[Account_ID],A23),0)) | N23: =IF(A23="","",IF(IFERROR(XLOOKUP(A23,tblAccounts[Account_ID],tblAccounts[Include],FALSE),FALSE),IFERROR(SUMPRODUCT(tblAcctSummary[Return_Period],tblAcctSummary[Begin_Balance_Base],--(tblAcctSummary[Account_ID]=A23))/IF(SUMIFS(tblAcctSummary[Begin_Balance_Base],tblAcctSummary[Account_ID],A23)=0,NA(),SUMIFS(tblAcctSummary[Begin_Balance_Base],tblAcctSummary[Account_ID],A23)),0),0))
A24: =IFERROR(INDEX(tblAccounts[Account_ID],21),"") | B24: =IF(A24="","",IFERROR(XLOOKUP(A24,tblAccounts[Account_ID],tblAccounts[Account_Name],""),"")) | C24: =IF(A24="","",IFERROR(XLOOKUP(A24,tblAccounts[Account_ID],tblAccounts[Household_ID],""),"")) | D24: =IF(A24="","",IF(IFERROR(XLOOKUP(A24,tblAccounts[Account_ID],tblAccounts[Include],FALSE),FALSE),SUMIFS(tblAcctSummary[Begin_Balance_Base],tblAcctSummary[Account_ID],A24),0)) | E24: =IF(A24="","",IF(IFERROR(XLOOKUP(A24,tblAccounts[Account_ID],tblAccounts[Include],FALSE),FALSE),SUMIFS(tblAcctSummary[End_Balance_Base],tblAcctSummary[Account_ID],A24),0)) | F24: =IF(A24="","",IF(IFERROR(XLOOKUP(A24,tblAccounts[Account_ID],tblAccounts[Include],FALSE),FALSE),SUMIFS(tblAcctSummary[Net_Contrib_Base],tblAcctSummary[Account_ID],A24),0)) | G24: =IF(A24="","",IF(IFERROR(XLOOKUP(A24,tblAccounts[Account_ID],tblAccounts[Include],FALSE),FALSE),SUMIFS(tblAcctSummary[Income_Interest_Base],tblAcctSummary[Account_ID],A24),0)) | H24: =IF(A24="","",IF(IFERROR(XLOOKUP(A24,tblAccounts[Account_ID],tblAccounts[Include],FALSE),FALSE),SUMIFS(tblAcctSummary[Income_Dividends_Base],tblAcctSummary[Account_ID],A24),0)) | I24: =IF(A24="","",IF(IFERROR(XLOOKUP(A24,tblAccounts[Account_ID],tblAccounts[Include],FALSE),FALSE),SUMIFS(tblAcctSummary[Income_Other_Base],tblAcctSummary[Account_ID],A24),0)) | J24: =IF(A24="","",SUM(G24:I24)) | K24: =IF(A24="","",IF(IFERROR(XLOOKUP(A24,tblAccounts[Account_ID],tblAccounts[Include],FALSE),FALSE),SUMIFS(tblAcctSummary[Realized_GL_Base],tblAcctSummary[Account_ID],A24),0)) | L24: =IF(A24="","",IF(IFERROR(XLOOKUP(A24,tblAccounts[Account_ID],tblAccounts[Include],FALSE),FALSE),SUMIFS(tblAcctSummary[Fees_Base],tblAcctSummary[Account_ID],A24),0)) | M24: =IF(A24="","",IF(IFERROR(XLOOKUP(A24,tblAccounts[Account_ID],tblAccounts[Include],FALSE),FALSE),SUMIFS(tblAcctSummary[Taxes_Base],tblAcctSummary[Account_ID],A24),0)) | N24: =IF(A24="","",IF(IFERROR(XLOOKUP(A24,tblAccounts[Account_ID],tblAccounts[Include],FALSE),FALSE),IFERROR(SUMPRODUCT(tblAcctSummary[Return_Period],tblAcctSummary[Begin_Balance_Base],--(tblAcctSummary[Account_ID]=A24))/IF(SUMIFS(tblAcctSummary[Begin_Balance_Base],tblAcctSummary[Account_ID],A24)=0,NA(),SUMIFS(tblAcctSummary[Begin_Balance_Base],tblAcctSummary[Account_ID],A24)),0),0))
A25: =IFERROR(INDEX(tblAccounts[Account_ID],22),"") | B25: =IF(A25="","",IFERROR(XLOOKUP(A25,tblAccounts[Account_ID],tblAccounts[Account_Name],""),"")) | C25: =IF(A25="","",IFERROR(XLOOKUP(A25,tblAccounts[Account_ID],tblAccounts[Household_ID],""),"")) | D25: =IF(A25="","",IF(IFERROR(XLOOKUP(A25,tblAccounts[Account_ID],tblAccounts[Include],FALSE),FALSE),SUMIFS(tblAcctSummary[Begin_Balance_Base],tblAcctSummary[Account_ID],A25),0)) | E25: =IF(A25="","",IF(IFERROR(XLOOKUP(A25,tblAccounts[Account_ID],tblAccounts[Include],FALSE),FALSE),SUMIFS(tblAcctSummary[End_Balance_Base],tblAcctSummary[Account_ID],A25),0)) | F25: =IF(A25="","",IF(IFERROR(XLOOKUP(A25,tblAccounts[Account_ID],tblAccounts[Include],FALSE),FALSE),SUMIFS(tblAcctSummary[Net_Contrib_Base],tblAcctSummary[Account_ID],A25),0)) | G25: =IF(A25="","",IF(IFERROR(XLOOKUP(A25,tblAccounts[Account_ID],tblAccounts[Include],FALSE),FALSE),SUMIFS(tblAcctSummary[Income_Interest_Base],tblAcctSummary[Account_ID],A25),0)) | H25: =IF(A25="","",IF(IFERROR(XLOOKUP(A25,tblAccounts[Account_ID],tblAccounts[Include],FALSE),FALSE),SUMIFS(tblAcctSummary[Income_Dividends_Base],tblAcctSummary[Account_ID],A25),0)) | I25: =IF(A25="","",IF(IFERROR(XLOOKUP(A25,tblAccounts[Account_ID],tblAccounts[Include],FALSE),FALSE),SUMIFS(tblAcctSummary[Income_Other_Base],tblAcctSummary[Account_ID],A25),0)) | J25: =IF(A25="","",SUM(G25:I25)) | K25: =IF(A25="","",IF(IFERROR(XLOOKUP(A25,tblAccounts[Account_ID],tblAccounts[Include],FALSE),FALSE),SUMIFS(tblAcctSummary[Realized_GL_Base],tblAcctSummary[Account_ID],A25),0)) | L25: =IF(A25="","",IF(IFERROR(XLOOKUP(A25,tblAccounts[Account_ID],tblAccounts[Include],FALSE),FALSE),SUMIFS(tblAcctSummary[Fees_Base],tblAcctSummary[Account_ID],A25),0)) | M25: =IF(A25="","",IF(IFERROR(XLOOKUP(A25,tblAccounts[Account_ID],tblAccounts[Include],FALSE),FALSE),SUMIFS(tblAcctSummary[Taxes_Base],tblAcctSummary[Account_ID],A25),0)) | N25: =IF(A25="","",IF(IFERROR(XLOOKUP(A25,tblAccounts[Account_ID],tblAccounts[Include],FALSE),FALSE),IFERROR(SUMPRODUCT(tblAcctSummary[Return_Period],tblAcctSummary[Begin_Balance_Base],--(tblAcctSummary[Account_ID]=A25))/IF(SUMIFS(tblAcctSummary[Begin_Balance_Base],tblAcctSummary[Account_ID],A25)=0,NA(),SUMIFS(tblAcctSummary[Begin_Balance_Base],tblAcctSummary[Account_ID],A25)),0),0))
A26: =IFERROR(INDEX(tblAccounts[Account_ID],23),"") | B26: =IF(A26="","",IFERROR(XLOOKUP(A26,tblAccounts[Account_ID],tblAccounts[Account_Name],""),"")) | C26: =IF(A26="","",IFERROR(XLOOKUP(A26,tblAccounts[Account_ID],tblAccounts[Household_ID],""),"")) | D26: =IF(A26="","",IF(IFERROR(XLOOKUP(A26,tblAccounts[Account_ID],tblAccounts[Include],FALSE),FALSE),SUMIFS(tblAcctSummary[Begin_Balance_Base],tblAcctSummary[Account_ID],A26),0)) | E26: =IF(A26="","",IF(IFERROR(XLOOKUP(A26,tblAccounts[Account_ID],tblAccounts[Include],FALSE),FALSE),SUMIFS(tblAcctSummary[End_Balance_Base],tblAcctSummary[Account_ID],A26),0)) | F26: =IF(A26="","",IF(IFERROR(XLOOKUP(A26,tblAccounts[Account_ID],tblAccounts[Include],FALSE),FALSE),SUMIFS(tblAcctSummary[Net_Contrib_Base],tblAcctSummary[Account_ID],A26),0)) | G26: =IF(A26="","",IF(IFERROR(XLOOKUP(A26,tblAccounts[Account_ID],tblAccounts[Include],FALSE),FALSE),SUMIFS(tblAcctSummary[Income_Interest_Base],tblAcctSummary[Account_ID],A26),0)) | H26: =IF(A26="","",IF(IFERROR(XLOOKUP(A26,tblAccounts[Account_ID],tblAccounts[Include],FALSE),FALSE),SUMIFS(tblAcctSummary[Income_Dividends_Base],tblAcctSummary[Account_ID],A26),0)) | I26: =IF(A26="","",IF(IFERROR(XLOOKUP(A26,tblAccounts[Account_ID],tblAccounts[Include],FALSE),FALSE),SUMIFS(tblAcctSummary[Income_Other_Base],tblAcctSummary[Account_ID],A26),0)) | J26: =IF(A26="","",SUM(G26:I26)) | K26: =IF(A26="","",IF(IFERROR(XLOOKUP(A26,tblAccounts[Account_ID],tblAccounts[Include],FALSE),FALSE),SUMIFS(tblAcctSummary[Realized_GL_Base],tblAcctSummary[Account_ID],A26),0)) | L26: =IF(A26="","",IF(IFERROR(XLOOKUP(A26,tblAccounts[Account_ID],tblAccounts[Include],FALSE),FALSE),SUMIFS(tblAcctSummary[Fees_Base],tblAcctSummary[Account_ID],A26),0)) | M26: =IF(A26="","",IF(IFERROR(XLOOKUP(A26,tblAccounts[Account_ID],tblAccounts[Include],FALSE),FALSE),SUMIFS(tblAcctSummary[Taxes_Base],tblAcctSummary[Account_ID],A26),0)) | N26: =IF(A26="","",IF(IFERROR(XLOOKUP(A26,tblAccounts[Account_ID],tblAccounts[Include],FALSE),FALSE),IFERROR(SUMPRODUCT(tblAcctSummary[Return_Period],tblAcctSummary[Begin_Balance_Base],--(tblAcctSummary[Account_ID]=A26))/IF(SUMIFS(tblAcctSummary[Begin_Balance_Base],tblAcctSummary[Account_ID],A26)=0,NA(),SUMIFS(tblAcctSummary[Begin_Balance_Base],tblAcctSummary[Account_ID],A26)),0),0))
A27: =IFERROR(INDEX(tblAccounts[Account_ID],24),"") | B27: =IF(A27="","",IFERROR(XLOOKUP(A27,tblAccounts[Account_ID],tblAccounts[Account_Name],""),"")) | C27: =IF(A27="","",IFERROR(XLOOKUP(A27,tblAccounts[Account_ID],tblAccounts[Household_ID],""),"")) | D27: =IF(A27="","",IF(IFERROR(XLOOKUP(A27,tblAccounts[Account_ID],tblAccounts[Include],FALSE),FALSE),SUMIFS(tblAcctSummary[Begin_Balance_Base],tblAcctSummary[Account_ID],A27),0)) | E27: =IF(A27="","",IF(IFERROR(XLOOKUP(A27,tblAccounts[Account_ID],tblAccounts[Include],FALSE),FALSE),SUMIFS(tblAcctSummary[End_Balance_Base],tblAcctSummary[Account_ID],A27),0)) | F27: =IF(A27="","",IF(IFERROR(XLOOKUP(A27,tblAccounts[Account_ID],tblAccounts[Include],FALSE),FALSE),SUMIFS(tblAcctSummary[Net_Contrib_Base],tblAcctSummary[Account_ID],A27),0)) | G27: =IF(A27="","",IF(IFERROR(XLOOKUP(A27,tblAccounts[Account_ID],tblAccounts[Include],FALSE),FALSE),SUMIFS(tblAcctSummary[Income_Interest_Base],tblAcctSummary[Account_ID],A27),0)) | H27: =IF(A27="","",IF(IFERROR(XLOOKUP(A27,tblAccounts[Account_ID],tblAccounts[Include],FALSE),FALSE),SUMIFS(tblAcctSummary[Income_Dividends_Base],tblAcctSummary[Account_ID],A27),0)) | I27: =IF(A27="","",IF(IFERROR(XLOOKUP(A27,tblAccounts[Account_ID],tblAccounts[Include],FALSE),FALSE),SUMIFS(tblAcctSummary[Income_Other_Base],tblAcctSummary[Account_ID],A27),0)) | J27: =IF(A27="","",SUM(G27:I27)) | K27: =IF(A27="","",IF(IFERROR(XLOOKUP(A27,tblAccounts[Account_ID],tblAccounts[Include],FALSE),FALSE),SUMIFS(tblAcctSummary[Realized_GL_Base],tblAcctSummary[Account_ID],A27),0)) | L27: =IF(A27="","",IF(IFERROR(XLOOKUP(A27,tblAccounts[Account_ID],tblAccounts[Include],FALSE),FALSE),SUMIFS(tblAcctSummary[Fees_Base],tblAcctSummary[Account_ID],A27),0)) | M27: =IF(A27="","",IF(IFERROR(XLOOKUP(A27,tblAccounts[Account_ID],tblAccounts[Include],FALSE),FALSE),SUMIFS(tblAcctSummary[Taxes_Base],tblAcctSummary[Account_ID],A27),0)) | N27: =IF(A27="","",IF(IFERROR(XLOOKUP(A27,tblAccounts[Account_ID],tblAccounts[Include],FALSE),FALSE),IFERROR(SUMPRODUCT(tblAcctSummary[Return_Period],tblAcctSummary[Begin_Balance_Base],--(tblAcctSummary[Account_ID]=A27))/IF(SUMIFS(tblAcctSummary[Begin_Balance_Base],tblAcctSummary[Account_ID],A27)=0,NA(),SUMIFS(tblAcctSummary[Begin_Balance_Base],tblAcctSummary[Account_ID],A27)),0),0))
A28: =IFERROR(INDEX(tblAccounts[Account_ID],25),"") | B28: =IF(A28="","",IFERROR(XLOOKUP(A28,tblAccounts[Account_ID],tblAccounts[Account_Name],""),"")) | C28: =IF(A28="","",IFERROR(XLOOKUP(A28,tblAccounts[Account_ID],tblAccounts[Household_ID],""),"")) | D28: =IF(A28="","",IF(IFERROR(XLOOKUP(A28,tblAccounts[Account_ID],tblAccounts[Include],FALSE),FALSE),SUMIFS(tblAcctSummary[Begin_Balance_Base],tblAcctSummary[Account_ID],A28),0)) | E28: =IF(A28="","",IF(IFERROR(XLOOKUP(A28,tblAccounts[Account_ID],tblAccounts[Include],FALSE),FALSE),SUMIFS(tblAcctSummary[End_Balance_Base],tblAcctSummary[Account_ID],A28),0)) | F28: =IF(A28="","",IF(IFERROR(XLOOKUP(A28,tblAccounts[Account_ID],tblAccounts[Include],FALSE),FALSE),SUMIFS(tblAcctSummary[Net_Contrib_Base],tblAcctSummary[Account_ID],A28),0)) | G28: =IF(A28="","",IF(IFERROR(XLOOKUP(A28,tblAccounts[Account_ID],tblAccounts[Include],FALSE),FALSE),SUMIFS(tblAcctSummary[Income_Interest_Base],tblAcctSummary[Account_ID],A28),0)) | H28: =IF(A28="","",IF(IFERROR(XLOOKUP(A28,tblAccounts[Account_ID],tblAccounts[Include],FALSE),FALSE),SUMIFS(tblAcctSummary[Income_Dividends_Base],tblAcctSummary[Account_ID],A28),0)) | I28: =IF(A28="","",IF(IFERROR(XLOOKUP(A28,tblAccounts[Account_ID],tblAccounts[Include],FALSE),FALSE),SUMIFS(tblAcctSummary[Income_Other_Base],tblAcctSummary[Account_ID],A28),0)) | J28: =IF(A28="","",SUM(G28:I28)) | K28: =IF(A28="","",IF(IFERROR(XLOOKUP(A28,tblAccounts[Account_ID],tblAccounts[Include],FALSE),FALSE),SUMIFS(tblAcctSummary[Realized_GL_Base],tblAcctSummary[Account_ID],A28),0)) | L28: =IF(A28="","",IF(IFERROR(XLOOKUP(A28,tblAccounts[Account_ID],tblAccounts[Include],FALSE),FALSE),SUMIFS(tblAcctSummary[Fees_Base],tblAcctSummary[Account_ID],A28),0)) | M28: =IF(A28="","",IF(IFERROR(XLOOKUP(A28,tblAccounts[Account_ID],tblAccounts[Include],FALSE),FALSE),SUMIFS(tblAcctSummary[Taxes_Base],tblAcctSummary[Account_ID],A28),0)) | N28: =IF(A28="","",IF(IFERROR(XLOOKUP(A28,tblAccounts[Account_ID],tblAccounts[Include],FALSE),FALSE),IFERROR(SUMPRODUCT(tblAcctSummary[Return_Period],tblAcctSummary[Begin_Balance_Base],--(tblAcctSummary[Account_ID]=A28))/IF(SUMIFS(tblAcctSummary[Begin_Balance_Base],tblAcctSummary[Account_ID],A28)=0,NA(),SUMIFS(tblAcctSummary[Begin_Balance_Base],tblAcctSummary[Account_ID],A28)),0),0))
A29: =IFERROR(INDEX(tblAccounts[Account_ID],26),"") | B29: =IF(A29="","",IFERROR(XLOOKUP(A29,tblAccounts[Account_ID],tblAccounts[Account_Name],""),"")) | C29: =IF(A29="","",IFERROR(XLOOKUP(A29,tblAccounts[Account_ID],tblAccounts[Household_ID],""),"")) | D29: =IF(A29="","",IF(IFERROR(XLOOKUP(A29,tblAccounts[Account_ID],tblAccounts[Include],FALSE),FALSE),SUMIFS(tblAcctSummary[Begin_Balance_Base],tblAcctSummary[Account_ID],A29),0)) | E29: =IF(A29="","",IF(IFERROR(XLOOKUP(A29,tblAccounts[Account_ID],tblAccounts[Include],FALSE),FALSE),SUMIFS(tblAcctSummary[End_Balance_Base],tblAcctSummary[Account_ID],A29),0)) | F29: =IF(A29="","",IF(IFERROR(XLOOKUP(A29,tblAccounts[Account_ID],tblAccounts[Include],FALSE),FALSE),SUMIFS(tblAcctSummary[Net_Contrib_Base],tblAcctSummary[Account_ID],A29),0)) | G29: =IF(A29="","",IF(IFERROR(XLOOKUP(A29,tblAccounts[Account_ID],tblAccounts[Include],FALSE),FALSE),SUMIFS(tblAcctSummary[Income_Interest_Base],tblAcctSummary[Account_ID],A29),0)) | H29: =IF(A29="","",IF(IFERROR(XLOOKUP(A29,tblAccounts[Account_ID],tblAccounts[Include],FALSE),FALSE),SUMIFS(tblAcctSummary[Income_Dividends_Base],tblAcctSummary[Account_ID],A29),0)) | I29: =IF(A29="","",IF(IFERROR(XLOOKUP(A29,tblAccounts[Account_ID],tblAccounts[Include],FALSE),FALSE),SUMIFS(tblAcctSummary[Income_Other_Base],tblAcctSummary[Account_ID],A29),0)) | J29: =IF(A29="","",SUM(G29:I29)) | K29: =IF(A29="","",IF(IFERROR(XLOOKUP(A29,tblAccounts[Account_ID],tblAccounts[Include],FALSE),FALSE),SUMIFS(tblAcctSummary[Realized_GL_Base],tblAcctSummary[Account_ID],A29),0)) | L29: =IF(A29="","",IF(IFERROR(XLOOKUP(A29,tblAccounts[Account_ID],tblAccounts[Include],FALSE),FALSE),SUMIFS(tblAcctSummary[Fees_Base],tblAcctSummary[Account_ID],A29),0)) | M29: =IF(A29="","",IF(IFERROR(XLOOKUP(A29,tblAccounts[Account_ID],tblAccounts[Include],FALSE),FALSE),SUMIFS(tblAcctSummary[Taxes_Base],tblAcctSummary[Account_ID],A29),0)) | N29: =IF(A29="","",IF(IFERROR(XLOOKUP(A29,tblAccounts[Account_ID],tblAccounts[Include],FALSE),FALSE),IFERROR(SUMPRODUCT(tblAcctSummary[Return_Period],tblAcctSummary[Begin_Balance_Base],--(tblAcctSummary[Account_ID]=A29))/IF(SUMIFS(tblAcctSummary[Begin_Balance_Base],tblAcctSummary[Account_ID],A29)=0,NA(),SUMIFS(tblAcctSummary[Begin_Balance_Base],tblAcctSummary[Account_ID],A29)),0),0))
A30: =IFERROR(INDEX(tblAccounts[Account_ID],27),"") | B30: =IF(A30="","",IFERROR(XLOOKUP(A30,tblAccounts[Account_ID],tblAccounts[Account_Name],""),"")) | C30: =IF(A30="","",IFERROR(XLOOKUP(A30,tblAccounts[Account_ID],tblAccounts[Household_ID],""),"")) | D30: =IF(A30="","",IF(IFERROR(XLOOKUP(A30,tblAccounts[Account_ID],tblAccounts[Include],FALSE),FALSE),SUMIFS(tblAcctSummary[Begin_Balance_Base],tblAcctSummary[Account_ID],A30),0)) | E30: =IF(A30="","",IF(IFERROR(XLOOKUP(A30,tblAccounts[Account_ID],tblAccounts[Include],FALSE),FALSE),SUMIFS(tblAcctSummary[End_Balance_Base],tblAcctSummary[Account_ID],A30),0)) | F30: =IF(A30="","",IF(IFERROR(XLOOKUP(A30,tblAccounts[Account_ID],tblAccounts[Include],FALSE),FALSE),SUMIFS(tblAcctSummary[Net_Contrib_Base],tblAcctSummary[Account_ID],A30),0)) | G30: =IF(A30="","",IF(IFERROR(XLOOKUP(A30,tblAccounts[Account_ID],tblAccounts[Include],FALSE),FALSE),SUMIFS(tblAcctSummary[Income_Interest_Base],tblAcctSummary[Account_ID],A30),0)) | H30: =IF(A30="","",IF(IFERROR(XLOOKUP(A30,tblAccounts[Account_ID],tblAccounts[Include],FALSE),FALSE),SUMIFS(tblAcctSummary[Income_Dividends_Base],tblAcctSummary[Account_ID],A30),0)) | I30: =IF(A30="","",IF(IFERROR(XLOOKUP(A30,tblAccounts[Account_ID],tblAccounts[Include],FALSE),FALSE),SUMIFS(tblAcctSummary[Income_Other_Base],tblAcctSummary[Account_ID],A30),0)) | J30: =IF(A30="","",SUM(G30:I30)) | K30: =IF(A30="","",IF(IFERROR(XLOOKUP(A30,tblAccounts[Account_ID],tblAccounts[Include],FALSE),FALSE),SUMIFS(tblAcctSummary[Realized_GL_Base],tblAcctSummary[Account_ID],A30),0)) | L30: =IF(A30="","",IF(IFERROR(XLOOKUP(A30,tblAccounts[Account_ID],tblAccounts[Include],FALSE),FALSE),SUMIFS(tblAcctSummary[Fees_Base],tblAcctSummary[Account_ID],A30),0)) | M30: =IF(A30="","",IF(IFERROR(XLOOKUP(A30,tblAccounts[Account_ID],tblAccounts[Include],FALSE),FALSE),SUMIFS(tblAcctSummary[Taxes_Base],tblAcctSummary[Account_ID],A30),0)) | N30: =IF(A30="","",IF(IFERROR(XLOOKUP(A30,tblAccounts[Account_ID],tblAccounts[Include],FALSE),FALSE),IFERROR(SUMPRODUCT(tblAcctSummary[Return_Period],tblAcctSummary[Begin_Balance_Base],--(tblAcctSummary[Account_ID]=A30))/IF(SUMIFS(tblAcctSummary[Begin_Balance_Base],tblAcctSummary[Account_ID],A30)=0,NA(),SUMIFS(tblAcctSummary[Begin_Balance_Base],tblAcctSummary[Account_ID],A30)),0),0))
A31: =IFERROR(INDEX(tblAccounts[Account_ID],28),"") | B31: =IF(A31="","",IFERROR(XLOOKUP(A31,tblAccounts[Account_ID],tblAccounts[Account_Name],""),"")) | C31: =IF(A31="","",IFERROR(XLOOKUP(A31,tblAccounts[Account_ID],tblAccounts[Household_ID],""),"")) | D31: =IF(A31="","",IF(IFERROR(XLOOKUP(A31,tblAccounts[Account_ID],tblAccounts[Include],FALSE),FALSE),SUMIFS(tblAcctSummary[Begin_Balance_Base],tblAcctSummary[Account_ID],A31),0)) | E31: =IF(A31="","",IF(IFERROR(XLOOKUP(A31,tblAccounts[Account_ID],tblAccounts[Include],FALSE),FALSE),SUMIFS(tblAcctSummary[End_Balance_Base],tblAcctSummary[Account_ID],A31),0)) | F31: =IF(A31="","",IF(IFERROR(XLOOKUP(A31,tblAccounts[Account_ID],tblAccounts[Include],FALSE),FALSE),SUMIFS(tblAcctSummary[Net_Contrib_Base],tblAcctSummary[Account_ID],A31),0)) | G31: =IF(A31="","",IF(IFERROR(XLOOKUP(A31,tblAccounts[Account_ID],tblAccounts[Include],FALSE),FALSE),SUMIFS(tblAcctSummary[Income_Interest_Base],tblAcctSummary[Account_ID],A31),0)) | H31: =IF(A31="","",IF(IFERROR(XLOOKUP(A31,tblAccounts[Account_ID],tblAccounts[Include],FALSE),FALSE),SUMIFS(tblAcctSummary[Income_Dividends_Base],tblAcctSummary[Account_ID],A31),0)) | I31: =IF(A31="","",IF(IFERROR(XLOOKUP(A31,tblAccounts[Account_ID],tblAccounts[Include],FALSE),FALSE),SUMIFS(tblAcctSummary[Income_Other_Base],tblAcctSummary[Account_ID],A31),0)) | J31: =IF(A31="","",SUM(G31:I31)) | K31: =IF(A31="","",IF(IFERROR(XLOOKUP(A31,tblAccounts[Account_ID],tblAccounts[Include],FALSE),FALSE),SUMIFS(tblAcctSummary[Realized_GL_Base],tblAcctSummary[Account_ID],A31),0)) | L31: =IF(A31="","",IF(IFERROR(XLOOKUP(A31,tblAccounts[Account_ID],tblAccounts[Include],FALSE),FALSE),SUMIFS(tblAcctSummary[Fees_Base],tblAcctSummary[Account_ID],A31),0)) | M31: =IF(A31="","",IF(IFERROR(XLOOKUP(A31,tblAccounts[Account_ID],tblAccounts[Include],FALSE),FALSE),SUMIFS(tblAcctSummary[Taxes_Base],tblAcctSummary[Account_ID],A31),0)) | N31: =IF(A31="","",IF(IFERROR(XLOOKUP(A31,tblAccounts[Account_ID],tblAccounts[Include],FALSE),FALSE),IFERROR(SUMPRODUCT(tblAcctSummary[Return_Period],tblAcctSummary[Begin_Balance_Base],--(tblAcctSummary[Account_ID]=A31))/IF(SUMIFS(tblAcctSummary[Begin_Balance_Base],tblAcctSummary[Account_ID],A31)=0,NA(),SUMIFS(tblAcctSummary[Begin_Balance_Base],tblAcctSummary[Account_ID],A31)),0),0))
A32: =IFERROR(INDEX(tblAccounts[Account_ID],29),"") | B32: =IF(A32="","",IFERROR(XLOOKUP(A32,tblAccounts[Account_ID],tblAccounts[Account_Name],""),"")) | C32: =IF(A32="","",IFERROR(XLOOKUP(A32,tblAccounts[Account_ID],tblAccounts[Household_ID],""),"")) | D32: =IF(A32="","",IF(IFERROR(XLOOKUP(A32,tblAccounts[Account_ID],tblAccounts[Include],FALSE),FALSE),SUMIFS(tblAcctSummary[Begin_Balance_Base],tblAcctSummary[Account_ID],A32),0)) | E32: =IF(A32="","",IF(IFERROR(XLOOKUP(A32,tblAccounts[Account_ID],tblAccounts[Include],FALSE),FALSE),SUMIFS(tblAcctSummary[End_Balance_Base],tblAcctSummary[Account_ID],A32),0)) | F32: =IF(A32="","",IF(IFERROR(XLOOKUP(A32,tblAccounts[Account_ID],tblAccounts[Include],FALSE),FALSE),SUMIFS(tblAcctSummary[Net_Contrib_Base],tblAcctSummary[Account_ID],A32),0)) | G32: =IF(A32="","",IF(IFERROR(XLOOKUP(A32,tblAccounts[Account_ID],tblAccounts[Include],FALSE),FALSE),SUMIFS(tblAcctSummary[Income_Interest_Base],tblAcctSummary[Account_ID],A32),0)) | H32: =IF(A32="","",IF(IFERROR(XLOOKUP(A32,tblAccounts[Account_ID],tblAccounts[Include],FALSE),FALSE),SUMIFS(tblAcctSummary[Income_Dividends_Base],tblAcctSummary[Account_ID],A32),0)) | I32: =IF(A32="","",IF(IFERROR(XLOOKUP(A32,tblAccounts[Account_ID],tblAccounts[Include],FALSE),FALSE),SUMIFS(tblAcctSummary[Income_Other_Base],tblAcctSummary[Account_ID],A32),0)) | J32: =IF(A32="","",SUM(G32:I32)) | K32: =IF(A32="","",IF(IFERROR(XLOOKUP(A32,tblAccounts[Account_ID],tblAccounts[Include],FALSE),FALSE),SUMIFS(tblAcctSummary[Realized_GL_Base],tblAcctSummary[Account_ID],A32),0)) | L32: =IF(A32="","",IF(IFERROR(XLOOKUP(A32,tblAccounts[Account_ID],tblAccounts[Include],FALSE),FALSE),SUMIFS(tblAcctSummary[Fees_Base],tblAcctSummary[Account_ID],A32),0)) | M32: =IF(A32="","",IF(IFERROR(XLOOKUP(A32,tblAccounts[Account_ID],tblAccounts[Include],FALSE),FALSE),SUMIFS(tblAcctSummary[Taxes_Base],tblAcctSummary[Account_ID],A32),0)) | N32: =IF(A32="","",IF(IFERROR(XLOOKUP(A32,tblAccounts[Account_ID],tblAccounts[Include],FALSE),FALSE),IFERROR(SUMPRODUCT(tblAcctSummary[Return_Period],tblAcctSummary[Begin_Balance_Base],--(tblAcctSummary[Account_ID]=A32))/IF(SUMIFS(tblAcctSummary[Begin_Balance_Base],tblAcctSummary[Account_ID],A32)=0,NA(),SUMIFS(tblAcctSummary[Begin_Balance_Base],tblAcctSummary[Account_ID],A32)),0),0))
A33: =IFERROR(INDEX(tblAccounts[Account_ID],30),"") | B33: =IF(A33="","",IFERROR(XLOOKUP(A33,tblAccounts[Account_ID],tblAccounts[Account_Name],""),"")) | C33: =IF(A33="","",IFERROR(XLOOKUP(A33,tblAccounts[Account_ID],tblAccounts[Household_ID],""),"")) | D33: =IF(A33="","",IF(IFERROR(XLOOKUP(A33,tblAccounts[Account_ID],tblAccounts[Include],FALSE),FALSE),SUMIFS(tblAcctSummary[Begin_Balance_Base],tblAcctSummary[Account_ID],A33),0)) | E33: =IF(A33="","",IF(IFERROR(XLOOKUP(A33,tblAccounts[Account_ID],tblAccounts[Include],FALSE),FALSE),SUMIFS(tblAcctSummary[End_Balance_Base],tblAcctSummary[Account_ID],A33),0)) | F33: =IF(A33="","",IF(IFERROR(XLOOKUP(A33,tblAccounts[Account_ID],tblAccounts[Include],FALSE),FALSE),SUMIFS(tblAcctSummary[Net_Contrib_Base],tblAcctSummary[Account_ID],A33),0)) | G33: =IF(A33="","",IF(IFERROR(XLOOKUP(A33,tblAccounts[Account_ID],tblAccounts[Include],FALSE),FALSE),SUMIFS(tblAcctSummary[Income_Interest_Base],tblAcctSummary[Account_ID],A33),0)) | H33: =IF(A33="","",IF(IFERROR(XLOOKUP(A33,tblAccounts[Account_ID],tblAccounts[Include],FALSE),FALSE),SUMIFS(tblAcctSummary[Income_Dividends_Base],tblAcctSummary[Account_ID],A33),0)) | I33: =IF(A33="","",IF(IFERROR(XLOOKUP(A33,tblAccounts[Account_ID],tblAccounts[Include],FALSE),FALSE),SUMIFS(tblAcctSummary[Income_Other_Base],tblAcctSummary[Account_ID],A33),0)) | J33: =IF(A33="","",SUM(G33:I33)) | K33: =IF(A33="","",IF(IFERROR(XLOOKUP(A33,tblAccounts[Account_ID],tblAccounts[Include],FALSE),FALSE),SUMIFS(tblAcctSummary[Realized_GL_Base],tblAcctSummary[Account_ID],A33),0)) | L33: =IF(A33="","",IF(IFERROR(XLOOKUP(A33,tblAccounts[Account_ID],tblAccounts[Include],FALSE),FALSE),SUMIFS(tblAcctSummary[Fees_Base],tblAcctSummary[Account_ID],A33),0)) | M33: =IF(A33="","",IF(IFERROR(XLOOKUP(A33,tblAccounts[Account_ID],tblAccounts[Include],FALSE),FALSE),SUMIFS(tblAcctSummary[Taxes_Base],tblAcctSummary[Account_ID],A33),0)) | N33: =IF(A33="","",IF(IFERROR(XLOOKUP(A33,tblAccounts[Account_ID],tblAccounts[Include],FALSE),FALSE),IFERROR(SUMPRODUCT(tblAcctSummary[Return_Period],tblAcctSummary[Begin_Balance_Base],--(tblAcctSummary[Account_ID]=A33))/IF(SUMIFS(tblAcctSummary[Begin_Balance_Base],tblAcctSummary[Account_ID],A33)=0,NA(),SUMIFS(tblAcctSummary[Begin_Balance_Base],tblAcctSummary[Account_ID],A33)),0),0))
A34: =IFERROR(INDEX(tblAccounts[Account_ID],31),"") | B34: =IF(A34="","",IFERROR(XLOOKUP(A34,tblAccounts[Account_ID],tblAccounts[Account_Name],""),"")) | C34: =IF(A34="","",IFERROR(XLOOKUP(A34,tblAccounts[Account_ID],tblAccounts[Household_ID],""),"")) | D34: =IF(A34="","",IF(IFERROR(XLOOKUP(A34,tblAccounts[Account_ID],tblAccounts[Include],FALSE),FALSE),SUMIFS(tblAcctSummary[Begin_Balance_Base],tblAcctSummary[Account_ID],A34),0)) | E34: =IF(A34="","",IF(IFERROR(XLOOKUP(A34,tblAccounts[Account_ID],tblAccounts[Include],FALSE),FALSE),SUMIFS(tblAcctSummary[End_Balance_Base],tblAcctSummary[Account_ID],A34),0)) | F34: =IF(A34="","",IF(IFERROR(XLOOKUP(A34,tblAccounts[Account_ID],tblAccounts[Include],FALSE),FALSE),SUMIFS(tblAcctSummary[Net_Contrib_Base],tblAcctSummary[Account_ID],A34),0)) | G34: =IF(A34="","",IF(IFERROR(XLOOKUP(A34,tblAccounts[Account_ID],tblAccounts[Include],FALSE),FALSE),SUMIFS(tblAcctSummary[Income_Interest_Base],tblAcctSummary[Account_ID],A34),0)) | H34: =IF(A34="","",IF(IFERROR(XLOOKUP(A34,tblAccounts[Account_ID],tblAccounts[Include],FALSE),FALSE),SUMIFS(tblAcctSummary[Income_Dividends_Base],tblAcctSummary[Account_ID],A34),0)) | I34: =IF(A34="","",IF(IFERROR(XLOOKUP(A34,tblAccounts[Account_ID],tblAccounts[Include],FALSE),FALSE),SUMIFS(tblAcctSummary[Income_Other_Base],tblAcctSummary[Account_ID],A34),0)) | J34: =IF(A34="","",SUM(G34:I34)) | K34: =IF(A34="","",IF(IFERROR(XLOOKUP(A34,tblAccounts[Account_ID],tblAccounts[Include],FALSE),FALSE),SUMIFS(tblAcctSummary[Realized_GL_Base],tblAcctSummary[Account_ID],A34),0)) | L34: =IF(A34="","",IF(IFERROR(XLOOKUP(A34,tblAccounts[Account_ID],tblAccounts[Include],FALSE),FALSE),SUMIFS(tblAcctSummary[Fees_Base],tblAcctSummary[Account_ID],A34),0)) | M34: =IF(A34="","",IF(IFERROR(XLOOKUP(A34,tblAccounts[Account_ID],tblAccounts[Include],FALSE),FALSE),SUMIFS(tblAcctSummary[Taxes_Base],tblAcctSummary[Account_ID],A34),0)) | N34: =IF(A34="","",IF(IFERROR(XLOOKUP(A34,tblAccounts[Account_ID],tblAccounts[Include],FALSE),FALSE),IFERROR(SUMPRODUCT(tblAcctSummary[Return_Period],tblAcctSummary[Begin_Balance_Base],--(tblAcctSummary[Account_ID]=A34))/IF(SUMIFS(tblAcctSummary[Begin_Balance_Base],tblAcctSummary[Account_ID],A34)=0,NA(),SUMIFS(tblAcctSummary[Begin_Balance_Base],tblAcctSummary[Account_ID],A34)),0),0))
A35: =IFERROR(INDEX(tblAccounts[Account_ID],32),"") | B35: =IF(A35="","",IFERROR(XLOOKUP(A35,tblAccounts[Account_ID],tblAccounts[Account_Name],""),"")) | C35: =IF(A35="","",IFERROR(XLOOKUP(A35,tblAccounts[Account_ID],tblAccounts[Household_ID],""),"")) | D35: =IF(A35="","",IF(IFERROR(XLOOKUP(A35,tblAccounts[Account_ID],tblAccounts[Include],FALSE),FALSE),SUMIFS(tblAcctSummary[Begin_Balance_Base],tblAcctSummary[Account_ID],A35),0)) | E35: =IF(A35="","",IF(IFERROR(XLOOKUP(A35,tblAccounts[Account_ID],tblAccounts[Include],FALSE),FALSE),SUMIFS(tblAcctSummary[End_Balance_Base],tblAcctSummary[Account_ID],A35),0)) | F35: =IF(A35="","",IF(IFERROR(XLOOKUP(A35,tblAccounts[Account_ID],tblAccounts[Include],FALSE),FALSE),SUMIFS(tblAcctSummary[Net_Contrib_Base],tblAcctSummary[Account_ID],A35),0)) | G35: =IF(A35="","",IF(IFERROR(XLOOKUP(A35,tblAccounts[Account_ID],tblAccounts[Include],FALSE),FALSE),SUMIFS(tblAcctSummary[Income_Interest_Base],tblAcctSummary[Account_ID],A35),0)) | H35: =IF(A35="","",IF(IFERROR(XLOOKUP(A35,tblAccounts[Account_ID],tblAccounts[Include],FALSE),FALSE),SUMIFS(tblAcctSummary[Income_Dividends_Base],tblAcctSummary[Account_ID],A35),0)) | I35: =IF(A35="","",IF(IFERROR(XLOOKUP(A35,tblAccounts[Account_ID],tblAccounts[Include],FALSE),FALSE),SUMIFS(tblAcctSummary[Income_Other_Base],tblAcctSummary[Account_ID],A35),0)) | J35: =IF(A35="","",SUM(G35:I35)) | K35: =IF(A35="","",IF(IFERROR(XLOOKUP(A35,tblAccounts[Account_ID],tblAccounts[Include],FALSE),FALSE),SUMIFS(tblAcctSummary[Realized_GL_Base],tblAcctSummary[Account_ID],A35),0)) | L35: =IF(A35="","",IF(IFERROR(XLOOKUP(A35,tblAccounts[Account_ID],tblAccounts[Include],FALSE),FALSE),SUMIFS(tblAcctSummary[Fees_Base],tblAcctSummary[Account_ID],A35),0)) | M35: =IF(A35="","",IF(IFERROR(XLOOKUP(A35,tblAccounts[Account_ID],tblAccounts[Include],FALSE),FALSE),SUMIFS(tblAcctSummary[Taxes_Base],tblAcctSummary[Account_ID],A35),0)) | N35: =IF(A35="","",IF(IFERROR(XLOOKUP(A35,tblAccounts[Account_ID],tblAccounts[Include],FALSE),FALSE),IFERROR(SUMPRODUCT(tblAcctSummary[Return_Period],tblAcctSummary[Begin_Balance_Base],--(tblAcctSummary[Account_ID]=A35))/IF(SUMIFS(tblAcctSummary[Begin_Balance_Base],tblAcctSummary[Account_ID],A35)=0,NA(),SUMIFS(tblAcctSummary[Begin_Balance_Base],tblAcctSummary[Account_ID],A35)),0),0))
A36: =IFERROR(INDEX(tblAccounts[Account_ID],33),"") | B36: =IF(A36="","",IFERROR(XLOOKUP(A36,tblAccounts[Account_ID],tblAccounts[Account_Name],""),"")) | C36: =IF(A36="","",IFERROR(XLOOKUP(A36,tblAccounts[Account_ID],tblAccounts[Household_ID],""),"")) | D36: =IF(A36="","",IF(IFERROR(XLOOKUP(A36,tblAccounts[Account_ID],tblAccounts[Include],FALSE),FALSE),SUMIFS(tblAcctSummary[Begin_Balance_Base],tblAcctSummary[Account_ID],A36),0)) | E36: =IF(A36="","",IF(IFERROR(XLOOKUP(A36,tblAccounts[Account_ID],tblAccounts[Include],FALSE),FALSE),SUMIFS(tblAcctSummary[End_Balance_Base],tblAcctSummary[Account_ID],A36),0)) | F36: =IF(A36="","",IF(IFERROR(XLOOKUP(A36,tblAccounts[Account_ID],tblAccounts[Include],FALSE),FALSE),SUMIFS(tblAcctSummary[Net_Contrib_Base],tblAcctSummary[Account_ID],A36),0)) | G36: =IF(A36="","",IF(IFERROR(XLOOKUP(A36,tblAccounts[Account_ID],tblAccounts[Include],FALSE),FALSE),SUMIFS(tblAcctSummary[Income_Interest_Base],tblAcctSummary[Account_ID],A36),0)) | H36: =IF(A36="","",IF(IFERROR(XLOOKUP(A36,tblAccounts[Account_ID],tblAccounts[Include],FALSE),FALSE),SUMIFS(tblAcctSummary[Income_Dividends_Base],tblAcctSummary[Account_ID],A36),0)) | I36: =IF(A36="","",IF(IFERROR(XLOOKUP(A36,tblAccounts[Account_ID],tblAccounts[Include],FALSE),FALSE),SUMIFS(tblAcctSummary[Income_Other_Base],tblAcctSummary[Account_ID],A36),0)) | J36: =IF(A36="","",SUM(G36:I36)) | K36: =IF(A36="","",IF(IFERROR(XLOOKUP(A36,tblAccounts[Account_ID],tblAccounts[Include],FALSE),FALSE),SUMIFS(tblAcctSummary[Realized_GL_Base],tblAcctSummary[Account_ID],A36),0)) | L36: =IF(A36="","",IF(IFERROR(XLOOKUP(A36,tblAccounts[Account_ID],tblAccounts[Include],FALSE),FALSE),SUMIFS(tblAcctSummary[Fees_Base],tblAcctSummary[Account_ID],A36),0)) | M36: =IF(A36="","",IF(IFERROR(XLOOKUP(A36,tblAccounts[Account_ID],tblAccounts[Include],FALSE),FALSE),SUMIFS(tblAcctSummary[Taxes_Base],tblAcctSummary[Account_ID],A36),0)) | N36: =IF(A36="","",IF(IFERROR(XLOOKUP(A36,tblAccounts[Account_ID],tblAccounts[Include],FALSE),FALSE),IFERROR(SUMPRODUCT(tblAcctSummary[Return_Period],tblAcctSummary[Begin_Balance_Base],--(tblAcctSummary[Account_ID]=A36))/IF(SUMIFS(tblAcctSummary[Begin_Balance_Base],tblAcctSummary[Account_ID],A36)=0,NA(),SUMIFS(tblAcctSummary[Begin_Balance_Base],tblAcctSummary[Account_ID],A36)),0),0))
A37: =IFERROR(INDEX(tblAccounts[Account_ID],34),"") | B37: =IF(A37="","",IFERROR(XLOOKUP(A37,tblAccounts[Account_ID],tblAccounts[Account_Name],""),"")) | C37: =IF(A37="","",IFERROR(XLOOKUP(A37,tblAccounts[Account_ID],tblAccounts[Household_ID],""),"")) | D37: =IF(A37="","",IF(IFERROR(XLOOKUP(A37,tblAccounts[Account_ID],tblAccounts[Include],FALSE),FALSE),SUMIFS(tblAcctSummary[Begin_Balance_Base],tblAcctSummary[Account_ID],A37),0)) | E37: =IF(A37="","",IF(IFERROR(XLOOKUP(A37,tblAccounts[Account_ID],tblAccounts[Include],FALSE),FALSE),SUMIFS(tblAcctSummary[End_Balance_Base],tblAcctSummary[Account_ID],A37),0)) | F37: =IF(A37="","",IF(IFERROR(XLOOKUP(A37,tblAccounts[Account_ID],tblAccounts[Include],FALSE),FALSE),SUMIFS(tblAcctSummary[Net_Contrib_Base],tblAcctSummary[Account_ID],A37),0)) | G37: =IF(A37="","",IF(IFERROR(XLOOKUP(A37,tblAccounts[Account_ID],tblAccounts[Include],FALSE),FALSE),SUMIFS(tblAcctSummary[Income_Interest_Base],tblAcctSummary[Account_ID],A37),0)) | H37: =IF(A37="","",IF(IFERROR(XLOOKUP(A37,tblAccounts[Account_ID],tblAccounts[Include],FALSE),FALSE),SUMIFS(tblAcctSummary[Income_Dividends_Base],tblAcctSummary[Account_ID],A37),0)) | I37: =IF(A37="","",IF(IFERROR(XLOOKUP(A37,tblAccounts[Account_ID],tblAccounts[Include],FALSE),FALSE),SUMIFS(tblAcctSummary[Income_Other_Base],tblAcctSummary[Account_ID],A37),0)) | J37: =IF(A37="","",SUM(G37:I37)) | K37: =IF(A37="","",IF(IFERROR(XLOOKUP(A37,tblAccounts[Account_ID],tblAccounts[Include],FALSE),FALSE),SUMIFS(tblAcctSummary[Realized_GL_Base],tblAcctSummary[Account_ID],A37),0)) | L37: =IF(A37="","",IF(IFERROR(XLOOKUP(A37,tblAccounts[Account_ID],tblAccounts[Include],FALSE),FALSE),SUMIFS(tblAcctSummary[Fees_Base],tblAcctSummary[Account_ID],A37),0)) | M37: =IF(A37="","",IF(IFERROR(XLOOKUP(A37,tblAccounts[Account_ID],tblAccounts[Include],FALSE),FALSE),SUMIFS(tblAcctSummary[Taxes_Base],tblAcctSummary[Account_ID],A37),0)) | N37: =IF(A37="","",IF(IFERROR(XLOOKUP(A37,tblAccounts[Account_ID],tblAccounts[Include],FALSE),FALSE),IFERROR(SUMPRODUCT(tblAcctSummary[Return_Period],tblAcctSummary[Begin_Balance_Base],--(tblAcctSummary[Account_ID]=A37))/IF(SUMIFS(tblAcctSummary[Begin_Balance_Base],tblAcctSummary[Account_ID],A37)=0,NA(),SUMIFS(tblAcctSummary[Begin_Balance_Base],tblAcctSummary[Account_ID],A37)),0),0))
A38: =IFERROR(INDEX(tblAccounts[Account_ID],35),"") | B38: =IF(A38="","",IFERROR(XLOOKUP(A38,tblAccounts[Account_ID],tblAccounts[Account_Name],""),"")) | C38: =IF(A38="","",IFERROR(XLOOKUP(A38,tblAccounts[Account_ID],tblAccounts[Household_ID],""),"")) | D38: =IF(A38="","",IF(IFERROR(XLOOKUP(A38,tblAccounts[Account_ID],tblAccounts[Include],FALSE),FALSE),SUMIFS(tblAcctSummary[Begin_Balance_Base],tblAcctSummary[Account_ID],A38),0)) | E38: =IF(A38="","",IF(IFERROR(XLOOKUP(A38,tblAccounts[Account_ID],tblAccounts[Include],FALSE),FALSE),SUMIFS(tblAcctSummary[End_Balance_Base],tblAcctSummary[Account_ID],A38),0)) | F38: =IF(A38="","",IF(IFERROR(XLOOKUP(A38,tblAccounts[Account_ID],tblAccounts[Include],FALSE),FALSE),SUMIFS(tblAcctSummary[Net_Contrib_Base],tblAcctSummary[Account_ID],A38),0)) | G38: =IF(A38="","",IF(IFERROR(XLOOKUP(A38,tblAccounts[Account_ID],tblAccounts[Include],FALSE),FALSE),SUMIFS(tblAcctSummary[Income_Interest_Base],tblAcctSummary[Account_ID],A38),0)) | H38: =IF(A38="","",IF(IFERROR(XLOOKUP(A38,tblAccounts[Account_ID],tblAccounts[Include],FALSE),FALSE),SUMIFS(tblAcctSummary[Income_Dividends_Base],tblAcctSummary[Account_ID],A38),0)) | I38: =IF(A38="","",IF(IFERROR(XLOOKUP(A38,tblAccounts[Account_ID],tblAccounts[Include],FALSE),FALSE),SUMIFS(tblAcctSummary[Income_Other_Base],tblAcctSummary[Account_ID],A38),0)) | J38: =IF(A38="","",SUM(G38:I38)) | K38: =IF(A38="","",IF(IFERROR(XLOOKUP(A38,tblAccounts[Account_ID],tblAccounts[Include],FALSE),FALSE),SUMIFS(tblAcctSummary[Realized_GL_Base],tblAcctSummary[Account_ID],A38),0)) | L38: =IF(A38="","",IF(IFERROR(XLOOKUP(A38,tblAccounts[Account_ID],tblAccounts[Include],FALSE),FALSE),SUMIFS(tblAcctSummary[Fees_Base],tblAcctSummary[Account_ID],A38),0)) | M38: =IF(A38="","",IF(IFERROR(XLOOKUP(A38,tblAccounts[Account_ID],tblAccounts[Include],FALSE),FALSE),SUMIFS(tblAcctSummary[Taxes_Base],tblAcctSummary[Account_ID],A38),0)) | N38: =IF(A38="","",IF(IFERROR(XLOOKUP(A38,tblAccounts[Account_ID],tblAccounts[Include],FALSE),FALSE),IFERROR(SUMPRODUCT(tblAcctSummary[Return_Period],tblAcctSummary[Begin_Balance_Base],--(tblAcctSummary[Account_ID]=A38))/IF(SUMIFS(tblAcctSummary[Begin_Balance_Base],tblAcctSummary[Account_ID],A38)=0,NA(),SUMIFS(tblAcctSummary[Begin_Balance_Base],tblAcctSummary[Account_ID],A38)),0),0))
A39: =IFERROR(INDEX(tblAccounts[Account_ID],36),"") | B39: =IF(A39="","",IFERROR(XLOOKUP(A39,tblAccounts[Account_ID],tblAccounts[Account_Name],""),"")) | C39: =IF(A39="","",IFERROR(XLOOKUP(A39,tblAccounts[Account_ID],tblAccounts[Household_ID],""),"")) | D39: =IF(A39="","",IF(IFERROR(XLOOKUP(A39,tblAccounts[Account_ID],tblAccounts[Include],FALSE),FALSE),SUMIFS(tblAcctSummary[Begin_Balance_Base],tblAcctSummary[Account_ID],A39),0)) | E39: =IF(A39="","",IF(IFERROR(XLOOKUP(A39,tblAccounts[Account_ID],tblAccounts[Include],FALSE),FALSE),SUMIFS(tblAcctSummary[End_Balance_Base],tblAcctSummary[Account_ID],A39),0)) | F39: =IF(A39="","",IF(IFERROR(XLOOKUP(A39,tblAccounts[Account_ID],tblAccounts[Include],FALSE),FALSE),SUMIFS(tblAcctSummary[Net_Contrib_Base],tblAcctSummary[Account_ID],A39),0)) | G39: =IF(A39="","",IF(IFERROR(XLOOKUP(A39,tblAccounts[Account_ID],tblAccounts[Include],FALSE),FALSE),SUMIFS(tblAcctSummary[Income_Interest_Base],tblAcctSummary[Account_ID],A39),0)) | H39: =IF(A39="","",IF(IFERROR(XLOOKUP(A39,tblAccounts[Account_ID],tblAccounts[Include],FALSE),FALSE),SUMIFS(tblAcctSummary[Income_Dividends_Base],tblAcctSummary[Account_ID],A39),0)) | I39: =IF(A39="","",IF(IFERROR(XLOOKUP(A39,tblAccounts[Account_ID],tblAccounts[Include],FALSE),FALSE),SUMIFS(tblAcctSummary[Income_Other_Base],tblAcctSummary[Account_ID],A39),0)) | J39: =IF(A39="","",SUM(G39:I39)) | K39: =IF(A39="","",IF(IFERROR(XLOOKUP(A39,tblAccounts[Account_ID],tblAccounts[Include],FALSE),FALSE),SUMIFS(tblAcctSummary[Realized_GL_Base],tblAcctSummary[Account_ID],A39),0)) | L39: =IF(A39="","",IF(IFERROR(XLOOKUP(A39,tblAccounts[Account_ID],tblAccounts[Include],FALSE),FALSE),SUMIFS(tblAcctSummary[Fees_Base],tblAcctSummary[Account_ID],A39),0)) | M39: =IF(A39="","",IF(IFERROR(XLOOKUP(A39,tblAccounts[Account_ID],tblAccounts[Include],FALSE),FALSE),SUMIFS(tblAcctSummary[Taxes_Base],tblAcctSummary[Account_ID],A39),0)) | N39: =IF(A39="","",IF(IFERROR(XLOOKUP(A39,tblAccounts[Account_ID],tblAccounts[Include],FALSE),FALSE),IFERROR(SUMPRODUCT(tblAcctSummary[Return_Period],tblAcctSummary[Begin_Balance_Base],--(tblAcctSummary[Account_ID]=A39))/IF(SUMIFS(tblAcctSummary[Begin_Balance_Base],tblAcctSummary[Account_ID],A39)=0,NA(),SUMIFS(tblAcctSummary[Begin_Balance_Base],tblAcctSummary[Account_ID],A39)),0),0))
A40: =IFERROR(INDEX(tblAccounts[Account_ID],37),"") | B40: =IF(A40="","",IFERROR(XLOOKUP(A40,tblAccounts[Account_ID],tblAccounts[Account_Name],""),"")) | C40: =IF(A40="","",IFERROR(XLOOKUP(A40,tblAccounts[Account_ID],tblAccounts[Household_ID],""),"")) | D40: =IF(A40="","",IF(IFERROR(XLOOKUP(A40,tblAccounts[Account_ID],tblAccounts[Include],FALSE),FALSE),SUMIFS(tblAcctSummary[Begin_Balance_Base],tblAcctSummary[Account_ID],A40),0)) | E40: =IF(A40="","",IF(IFERROR(XLOOKUP(A40,tblAccounts[Account_ID],tblAccounts[Include],FALSE),FALSE),SUMIFS(tblAcctSummary[End_Balance_Base],tblAcctSummary[Account_ID],A40),0)) | F40: =IF(A40="","",IF(IFERROR(XLOOKUP(A40,tblAccounts[Account_ID],tblAccounts[Include],FALSE),FALSE),SUMIFS(tblAcctSummary[Net_Contrib_Base],tblAcctSummary[Account_ID],A40),0)) | G40: =IF(A40="","",IF(IFERROR(XLOOKUP(A40,tblAccounts[Account_ID],tblAccounts[Include],FALSE),FALSE),SUMIFS(tblAcctSummary[Income_Interest_Base],tblAcctSummary[Account_ID],A40),0)) | H40: =IF(A40="","",IF(IFERROR(XLOOKUP(A40,tblAccounts[Account_ID],tblAccounts[Include],FALSE),FALSE),SUMIFS(tblAcctSummary[Income_Dividends_Base],tblAcctSummary[Account_ID],A40),0)) | I40: =IF(A40="","",IF(IFERROR(XLOOKUP(A40,tblAccounts[Account_ID],tblAccounts[Include],FALSE),FALSE),SUMIFS(tblAcctSummary[Income_Other_Base],tblAcctSummary[Account_ID],A40),0)) | J40: =IF(A40="","",SUM(G40:I40)) | K40: =IF(A40="","",IF(IFERROR(XLOOKUP(A40,tblAccounts[Account_ID],tblAccounts[Include],FALSE),FALSE),SUMIFS(tblAcctSummary[Realized_GL_Base],tblAcctSummary[Account_ID],A40),0)) | L40: =IF(A40="","",IF(IFERROR(XLOOKUP(A40,tblAccounts[Account_ID],tblAccounts[Include],FALSE),FALSE),SUMIFS(tblAcctSummary[Fees_Base],tblAcctSummary[Account_ID],A40),0)) | M40: =IF(A40="","",IF(IFERROR(XLOOKUP(A40,tblAccounts[Account_ID],tblAccounts[Include],FALSE),FALSE),SUMIFS(tblAcctSummary[Taxes_Base],tblAcctSummary[Account_ID],A40),0)) | N40: =IF(A40="","",IF(IFERROR(XLOOKUP(A40,tblAccounts[Account_ID],tblAccounts[Include],FALSE),FALSE),IFERROR(SUMPRODUCT(tblAcctSummary[Return_Period],tblAcctSummary[Begin_Balance_Base],--(tblAcctSummary[Account_ID]=A40))/IF(SUMIFS(tblAcctSummary[Begin_Balance_Base],tblAcctSummary[Account_ID],A40)=0,NA(),SUMIFS(tblAcctSummary[Begin_Balance_Base],tblAcctSummary[Account_ID],A40)),0),0))
A41: =IFERROR(INDEX(tblAccounts[Account_ID],38),"") | B41: =IF(A41="","",IFERROR(XLOOKUP(A41,tblAccounts[Account_ID],tblAccounts[Account_Name],""),"")) | C41: =IF(A41="","",IFERROR(XLOOKUP(A41,tblAccounts[Account_ID],tblAccounts[Household_ID],""),"")) | D41: =IF(A41="","",IF(IFERROR(XLOOKUP(A41,tblAccounts[Account_ID],tblAccounts[Include],FALSE),FALSE),SUMIFS(tblAcctSummary[Begin_Balance_Base],tblAcctSummary[Account_ID],A41),0)) | E41: =IF(A41="","",IF(IFERROR(XLOOKUP(A41,tblAccounts[Account_ID],tblAccounts[Include],FALSE),FALSE),SUMIFS(tblAcctSummary[End_Balance_Base],tblAcctSummary[Account_ID],A41),0)) | F41: =IF(A41="","",IF(IFERROR(XLOOKUP(A41,tblAccounts[Account_ID],tblAccounts[Include],FALSE),FALSE),SUMIFS(tblAcctSummary[Net_Contrib_Base],tblAcctSummary[Account_ID],A41),0)) | G41: =IF(A41="","",IF(IFERROR(XLOOKUP(A41,tblAccounts[Account_ID],tblAccounts[Include],FALSE),FALSE),SUMIFS(tblAcctSummary[Income_Interest_Base],tblAcctSummary[Account_ID],A41),0)) | H41: =IF(A41="","",IF(IFERROR(XLOOKUP(A41,tblAccounts[Account_ID],tblAccounts[Include],FALSE),FALSE),SUMIFS(tblAcctSummary[Income_Dividends_Base],tblAcctSummary[Account_ID],A41),0)) | I41: =IF(A41="","",IF(IFERROR(XLOOKUP(A41,tblAccounts[Account_ID],tblAccounts[Include],FALSE),FALSE),SUMIFS(tblAcctSummary[Income_Other_Base],tblAcctSummary[Account_ID],A41),0)) | J41: =IF(A41="","",SUM(G41:I41)) | K41: =IF(A41="","",IF(IFERROR(XLOOKUP(A41,tblAccounts[Account_ID],tblAccounts[Include],FALSE),FALSE),SUMIFS(tblAcctSummary[Realized_GL_Base],tblAcctSummary[Account_ID],A41),0)) | L41: =IF(A41="","",IF(IFERROR(XLOOKUP(A41,tblAccounts[Account_ID],tblAccounts[Include],FALSE),FALSE),SUMIFS(tblAcctSummary[Fees_Base],tblAcctSummary[Account_ID],A41),0)) | M41: =IF(A41="","",IF(IFERROR(XLOOKUP(A41,tblAccounts[Account_ID],tblAccounts[Include],FALSE),FALSE),SUMIFS(tblAcctSummary[Taxes_Base],tblAcctSummary[Account_ID],A41),0)) | N41: =IF(A41="","",IF(IFERROR(XLOOKUP(A41,tblAccounts[Account_ID],tblAccounts[Include],FALSE),FALSE),IFERROR(SUMPRODUCT(tblAcctSummary[Return_Period],tblAcctSummary[Begin_Balance_Base],--(tblAcctSummary[Account_ID]=A41))/IF(SUMIFS(tblAcctSummary[Begin_Balance_Base],tblAcctSummary[Account_ID],A41)=0,NA(),SUMIFS(tblAcctSummary[Begin_Balance_Base],tblAcctSummary[Account_ID],A41)),0),0))
A42: =IFERROR(INDEX(tblAccounts[Account_ID],39),"") | B42: =IF(A42="","",IFERROR(XLOOKUP(A42,tblAccounts[Account_ID],tblAccounts[Account_Name],""),"")) | C42: =IF(A42="","",IFERROR(XLOOKUP(A42,tblAccounts[Account_ID],tblAccounts[Household_ID],""),"")) | D42: =IF(A42="","",IF(IFERROR(XLOOKUP(A42,tblAccounts[Account_ID],tblAccounts[Include],FALSE),FALSE),SUMIFS(tblAcctSummary[Begin_Balance_Base],tblAcctSummary[Account_ID],A42),0)) | E42: =IF(A42="","",IF(IFERROR(XLOOKUP(A42,tblAccounts[Account_ID],tblAccounts[Include],FALSE),FALSE),SUMIFS(tblAcctSummary[End_Balance_Base],tblAcctSummary[Account_ID],A42),0)) | F42: =IF(A42="","",IF(IFERROR(XLOOKUP(A42,tblAccounts[Account_ID],tblAccounts[Include],FALSE),FALSE),SUMIFS(tblAcctSummary[Net_Contrib_Base],tblAcctSummary[Account_ID],A42),0)) | G42: =IF(A42="","",IF(IFERROR(XLOOKUP(A42,tblAccounts[Account_ID],tblAccounts[Include],FALSE),FALSE),SUMIFS(tblAcctSummary[Income_Interest_Base],tblAcctSummary[Account_ID],A42),0)) | H42: =IF(A42="","",IF(IFERROR(XLOOKUP(A42,tblAccounts[Account_ID],tblAccounts[Include],FALSE),FALSE),SUMIFS(tblAcctSummary[Income_Dividends_Base],tblAcctSummary[Account_ID],A42),0)) | I42: =IF(A42="","",IF(IFERROR(XLOOKUP(A42,tblAccounts[Account_ID],tblAccounts[Include],FALSE),FALSE),SUMIFS(tblAcctSummary[Income_Other_Base],tblAcctSummary[Account_ID],A42),0)) | J42: =IF(A42="","",SUM(G42:I42)) | K42: =IF(A42="","",IF(IFERROR(XLOOKUP(A42,tblAccounts[Account_ID],tblAccounts[Include],FALSE),FALSE),SUMIFS(tblAcctSummary[Realized_GL_Base],tblAcctSummary[Account_ID],A42),0)) | L42: =IF(A42="","",IF(IFERROR(XLOOKUP(A42,tblAccounts[Account_ID],tblAccounts[Include],FALSE),FALSE),SUMIFS(tblAcctSummary[Fees_Base],tblAcctSummary[Account_ID],A42),0)) | M42: =IF(A42="","",IF(IFERROR(XLOOKUP(A42,tblAccounts[Account_ID],tblAccounts[Include],FALSE),FALSE),SUMIFS(tblAcctSummary[Taxes_Base],tblAcctSummary[Account_ID],A42),0)) | N42: =IF(A42="","",IF(IFERROR(XLOOKUP(A42,tblAccounts[Account_ID],tblAccounts[Include],FALSE),FALSE),IFERROR(SUMPRODUCT(tblAcctSummary[Return_Period],tblAcctSummary[Begin_Balance_Base],--(tblAcctSummary[Account_ID]=A42))/IF(SUMIFS(tblAcctSummary[Begin_Balance_Base],tblAcctSummary[Account_ID],A42)=0,NA(),SUMIFS(tblAcctSummary[Begin_Balance_Base],tblAcctSummary[Account_ID],A42)),0),0))
A43: =IFERROR(INDEX(tblAccounts[Account_ID],40),"") | B43: =IF(A43="","",IFERROR(XLOOKUP(A43,tblAccounts[Account_ID],tblAccounts[Account_Name],""),"")) | C43: =IF(A43="","",IFERROR(XLOOKUP(A43,tblAccounts[Account_ID],tblAccounts[Household_ID],""),"")) | D43: =IF(A43="","",IF(IFERROR(XLOOKUP(A43,tblAccounts[Account_ID],tblAccounts[Include],FALSE),FALSE),SUMIFS(tblAcctSummary[Begin_Balance_Base],tblAcctSummary[Account_ID],A43),0)) | E43: =IF(A43="","",IF(IFERROR(XLOOKUP(A43,tblAccounts[Account_ID],tblAccounts[Include],FALSE),FALSE),SUMIFS(tblAcctSummary[End_Balance_Base],tblAcctSummary[Account_ID],A43),0)) | F43: =IF(A43="","",IF(IFERROR(XLOOKUP(A43,tblAccounts[Account_ID],tblAccounts[Include],FALSE),FALSE),SUMIFS(tblAcctSummary[Net_Contrib_Base],tblAcctSummary[Account_ID],A43),0)) | G43: =IF(A43="","",IF(IFERROR(XLOOKUP(A43,tblAccounts[Account_ID],tblAccounts[Include],FALSE),FALSE),SUMIFS(tblAcctSummary[Income_Interest_Base],tblAcctSummary[Account_ID],A43),0)) | H43: =IF(A43="","",IF(IFERROR(XLOOKUP(A43,tblAccounts[Account_ID],tblAccounts[Include],FALSE),FALSE),SUMIFS(tblAcctSummary[Income_Dividends_Base],tblAcctSummary[Account_ID],A43),0)) | I43: =IF(A43="","",IF(IFERROR(XLOOKUP(A43,tblAccounts[Account_ID],tblAccounts[Include],FALSE),FALSE),SUMIFS(tblAcctSummary[Income_Other_Base],tblAcctSummary[Account_ID],A43),0)) | J43: =IF(A43="","",SUM(G43:I43)) | K43: =IF(A43="","",IF(IFERROR(XLOOKUP(A43,tblAccounts[Account_ID],tblAccounts[Include],FALSE),FALSE),SUMIFS(tblAcctSummary[Realized_GL_Base],tblAcctSummary[Account_ID],A43),0)) | L43: =IF(A43="","",IF(IFERROR(XLOOKUP(A43,tblAccounts[Account_ID],tblAccounts[Include],FALSE),FALSE),SUMIFS(tblAcctSummary[Fees_Base],tblAcctSummary[Account_ID],A43),0)) | M43: =IF(A43="","",IF(IFERROR(XLOOKUP(A43,tblAccounts[Account_ID],tblAccounts[Include],FALSE),FALSE),SUMIFS(tblAcctSummary[Taxes_Base],tblAcctSummary[Account_ID],A43),0)) | N43: =IF(A43="","",IF(IFERROR(XLOOKUP(A43,tblAccounts[Account_ID],tblAccounts[Include],FALSE),FALSE),IFERROR(SUMPRODUCT(tblAcctSummary[Return_Period],tblAcctSummary[Begin_Balance_Base],--(tblAcctSummary[Account_ID]=A43))/IF(SUMIFS(tblAcctSummary[Begin_Balance_Base],tblAcctSummary[Account_ID],A43)=0,NA(),SUMIFS(tblAcctSummary[Begin_Balance_Base],tblAcctSummary[Account_ID],A43)),0),0))
A44: =IFERROR(INDEX(tblAccounts[Account_ID],41),"") | B44: =IF(A44="","",IFERROR(XLOOKUP(A44,tblAccounts[Account_ID],tblAccounts[Account_Name],""),"")) | C44: =IF(A44="","",IFERROR(XLOOKUP(A44,tblAccounts[Account_ID],tblAccounts[Household_ID],""),"")) | D44: =IF(A44="","",IF(IFERROR(XLOOKUP(A44,tblAccounts[Account_ID],tblAccounts[Include],FALSE),FALSE),SUMIFS(tblAcctSummary[Begin_Balance_Base],tblAcctSummary[Account_ID],A44),0)) | E44: =IF(A44="","",IF(IFERROR(XLOOKUP(A44,tblAccounts[Account_ID],tblAccounts[Include],FALSE),FALSE),SUMIFS(tblAcctSummary[End_Balance_Base],tblAcctSummary[Account_ID],A44),0)) | F44: =IF(A44="","",IF(IFERROR(XLOOKUP(A44,tblAccounts[Account_ID],tblAccounts[Include],FALSE),FALSE),SUMIFS(tblAcctSummary[Net_Contrib_Base],tblAcctSummary[Account_ID],A44),0)) | G44: =IF(A44="","",IF(IFERROR(XLOOKUP(A44,tblAccounts[Account_ID],tblAccounts[Include],FALSE),FALSE),SUMIFS(tblAcctSummary[Income_Interest_Base],tblAcctSummary[Account_ID],A44),0)) | H44: =IF(A44="","",IF(IFERROR(XLOOKUP(A44,tblAccounts[Account_ID],tblAccounts[Include],FALSE),FALSE),SUMIFS(tblAcctSummary[Income_Dividends_Base],tblAcctSummary[Account_ID],A44),0)) | I44: =IF(A44="","",IF(IFERROR(XLOOKUP(A44,tblAccounts[Account_ID],tblAccounts[Include],FALSE),FALSE),SUMIFS(tblAcctSummary[Income_Other_Base],tblAcctSummary[Account_ID],A44),0)) | J44: =IF(A44="","",SUM(G44:I44)) | K44: =IF(A44="","",IF(IFERROR(XLOOKUP(A44,tblAccounts[Account_ID],tblAccounts[Include],FALSE),FALSE),SUMIFS(tblAcctSummary[Realized_GL_Base],tblAcctSummary[Account_ID],A44),0)) | L44: =IF(A44="","",IF(IFERROR(XLOOKUP(A44,tblAccounts[Account_ID],tblAccounts[Include],FALSE),FALSE),SUMIFS(tblAcctSummary[Fees_Base],tblAcctSummary[Account_ID],A44),0)) | M44: =IF(A44="","",IF(IFERROR(XLOOKUP(A44,tblAccounts[Account_ID],tblAccounts[Include],FALSE),FALSE),SUMIFS(tblAcctSummary[Taxes_Base],tblAcctSummary[Account_ID],A44),0)) | N44: =IF(A44="","",IF(IFERROR(XLOOKUP(A44,tblAccounts[Account_ID],tblAccounts[Include],FALSE),FALSE),IFERROR(SUMPRODUCT(tblAcctSummary[Return_Period],tblAcctSummary[Begin_Balance_Base],--(tblAcctSummary[Account_ID]=A44))/IF(SUMIFS(tblAcctSummary[Begin_Balance_Base],tblAcctSummary[Account_ID],A44)=0,NA(),SUMIFS(tblAcctSummary[Begin_Balance_Base],tblAcctSummary[Account_ID],A44)),0),0))
A45: =IFERROR(INDEX(tblAccounts[Account_ID],42),"") | B45: =IF(A45="","",IFERROR(XLOOKUP(A45,tblAccounts[Account_ID],tblAccounts[Account_Name],""),"")) | C45: =IF(A45="","",IFERROR(XLOOKUP(A45,tblAccounts[Account_ID],tblAccounts[Household_ID],""),"")) | D45: =IF(A45="","",IF(IFERROR(XLOOKUP(A45,tblAccounts[Account_ID],tblAccounts[Include],FALSE),FALSE),SUMIFS(tblAcctSummary[Begin_Balance_Base],tblAcctSummary[Account_ID],A45),0)) | E45: =IF(A45="","",IF(IFERROR(XLOOKUP(A45,tblAccounts[Account_ID],tblAccounts[Include],FALSE),FALSE),SUMIFS(tblAcctSummary[End_Balance_Base],tblAcctSummary[Account_ID],A45),0)) | F45: =IF(A45="","",IF(IFERROR(XLOOKUP(A45,tblAccounts[Account_ID],tblAccounts[Include],FALSE),FALSE),SUMIFS(tblAcctSummary[Net_Contrib_Base],tblAcctSummary[Account_ID],A45),0)) | G45: =IF(A45="","",IF(IFERROR(XLOOKUP(A45,tblAccounts[Account_ID],tblAccounts[Include],FALSE),FALSE),SUMIFS(tblAcctSummary[Income_Interest_Base],tblAcctSummary[Account_ID],A45),0)) | H45: =IF(A45="","",IF(IFERROR(XLOOKUP(A45,tblAccounts[Account_ID],tblAccounts[Include],FALSE),FALSE),SUMIFS(tblAcctSummary[Income_Dividends_Base],tblAcctSummary[Account_ID],A45),0)) | I45: =IF(A45="","",IF(IFERROR(XLOOKUP(A45,tblAccounts[Account_ID],tblAccounts[Include],FALSE),FALSE),SUMIFS(tblAcctSummary[Income_Other_Base],tblAcctSummary[Account_ID],A45),0)) | J45: =IF(A45="","",SUM(G45:I45)) | K45: =IF(A45="","",IF(IFERROR(XLOOKUP(A45,tblAccounts[Account_ID],tblAccounts[Include],FALSE),FALSE),SUMIFS(tblAcctSummary[Realized_GL_Base],tblAcctSummary[Account_ID],A45),0)) | L45: =IF(A45="","",IF(IFERROR(XLOOKUP(A45,tblAccounts[Account_ID],tblAccounts[Include],FALSE),FALSE),SUMIFS(tblAcctSummary[Fees_Base],tblAcctSummary[Account_ID],A45),0)) | M45: =IF(A45="","",IF(IFERROR(XLOOKUP(A45,tblAccounts[Account_ID],tblAccounts[Include],FALSE),FALSE),SUMIFS(tblAcctSummary[Taxes_Base],tblAcctSummary[Account_ID],A45),0)) | N45: =IF(A45="","",IF(IFERROR(XLOOKUP(A45,tblAccounts[Account_ID],tblAccounts[Include],FALSE),FALSE),IFERROR(SUMPRODUCT(tblAcctSummary[Return_Period],tblAcctSummary[Begin_Balance_Base],--(tblAcctSummary[Account_ID]=A45))/IF(SUMIFS(tblAcctSummary[Begin_Balance_Base],tblAcctSummary[Account_ID],A45)=0,NA(),SUMIFS(tblAcctSummary[Begin_Balance_Base],tblAcctSummary[Account_ID],A45)),0),0))
A46: =IFERROR(INDEX(tblAccounts[Account_ID],43),"") | B46: =IF(A46="","",IFERROR(XLOOKUP(A46,tblAccounts[Account_ID],tblAccounts[Account_Name],""),"")) | C46: =IF(A46="","",IFERROR(XLOOKUP(A46,tblAccounts[Account_ID],tblAccounts[Household_ID],""),"")) | D46: =IF(A46="","",IF(IFERROR(XLOOKUP(A46,tblAccounts[Account_ID],tblAccounts[Include],FALSE),FALSE),SUMIFS(tblAcctSummary[Begin_Balance_Base],tblAcctSummary[Account_ID],A46),0)) | E46: =IF(A46="","",IF(IFERROR(XLOOKUP(A46,tblAccounts[Account_ID],tblAccounts[Include],FALSE),FALSE),SUMIFS(tblAcctSummary[End_Balance_Base],tblAcctSummary[Account_ID],A46),0)) | F46: =IF(A46="","",IF(IFERROR(XLOOKUP(A46,tblAccounts[Account_ID],tblAccounts[Include],FALSE),FALSE),SUMIFS(tblAcctSummary[Net_Contrib_Base],tblAcctSummary[Account_ID],A46),0)) | G46: =IF(A46="","",IF(IFERROR(XLOOKUP(A46,tblAccounts[Account_ID],tblAccounts[Include],FALSE),FALSE),SUMIFS(tblAcctSummary[Income_Interest_Base],tblAcctSummary[Account_ID],A46),0)) | H46: =IF(A46="","",IF(IFERROR(XLOOKUP(A46,tblAccounts[Account_ID],tblAccounts[Include],FALSE),FALSE),SUMIFS(tblAcctSummary[Income_Dividends_Base],tblAcctSummary[Account_ID],A46),0)) | I46: =IF(A46="","",IF(IFERROR(XLOOKUP(A46,tblAccounts[Account_ID],tblAccounts[Include],FALSE),FALSE),SUMIFS(tblAcctSummary[Income_Other_Base],tblAcctSummary[Account_ID],A46),0)) | J46: =IF(A46="","",SUM(G46:I46)) | K46: =IF(A46="","",IF(IFERROR(XLOOKUP(A46,tblAccounts[Account_ID],tblAccounts[Include],FALSE),FALSE),SUMIFS(tblAcctSummary[Realized_GL_Base],tblAcctSummary[Account_ID],A46),0)) | L46: =IF(A46="","",IF(IFERROR(XLOOKUP(A46,tblAccounts[Account_ID],tblAccounts[Include],FALSE),FALSE),SUMIFS(tblAcctSummary[Fees_Base],tblAcctSummary[Account_ID],A46),0)) | M46: =IF(A46="","",IF(IFERROR(XLOOKUP(A46,tblAccounts[Account_ID],tblAccounts[Include],FALSE),FALSE),SUMIFS(tblAcctSummary[Taxes_Base],tblAcctSummary[Account_ID],A46),0)) | N46: =IF(A46="","",IF(IFERROR(XLOOKUP(A46,tblAccounts[Account_ID],tblAccounts[Include],FALSE),FALSE),IFERROR(SUMPRODUCT(tblAcctSummary[Return_Period],tblAcctSummary[Begin_Balance_Base],--(tblAcctSummary[Account_ID]=A46))/IF(SUMIFS(tblAcctSummary[Begin_Balance_Base],tblAcctSummary[Account_ID],A46)=0,NA(),SUMIFS(tblAcctSummary[Begin_Balance_Base],tblAcctSummary[Account_ID],A46)),0),0))
A47: =IFERROR(INDEX(tblAccounts[Account_ID],44),"") | B47: =IF(A47="","",IFERROR(XLOOKUP(A47,tblAccounts[Account_ID],tblAccounts[Account_Name],""),"")) | C47: =IF(A47="","",IFERROR(XLOOKUP(A47,tblAccounts[Account_ID],tblAccounts[Household_ID],""),"")) | D47: =IF(A47="","",IF(IFERROR(XLOOKUP(A47,tblAccounts[Account_ID],tblAccounts[Include],FALSE),FALSE),SUMIFS(tblAcctSummary[Begin_Balance_Base],tblAcctSummary[Account_ID],A47),0)) | E47: =IF(A47="","",IF(IFERROR(XLOOKUP(A47,tblAccounts[Account_ID],tblAccounts[Include],FALSE),FALSE),SUMIFS(tblAcctSummary[End_Balance_Base],tblAcctSummary[Account_ID],A47),0)) | F47: =IF(A47="","",IF(IFERROR(XLOOKUP(A47,tblAccounts[Account_ID],tblAccounts[Include],FALSE),FALSE),SUMIFS(tblAcctSummary[Net_Contrib_Base],tblAcctSummary[Account_ID],A47),0)) | G47: =IF(A47="","",IF(IFERROR(XLOOKUP(A47,tblAccounts[Account_ID],tblAccounts[Include],FALSE),FALSE),SUMIFS(tblAcctSummary[Income_Interest_Base],tblAcctSummary[Account_ID],A47),0)) | H47: =IF(A47="","",IF(IFERROR(XLOOKUP(A47,tblAccounts[Account_ID],tblAccounts[Include],FALSE),FALSE),SUMIFS(tblAcctSummary[Income_Dividends_Base],tblAcctSummary[Account_ID],A47),0)) | I47: =IF(A47="","",IF(IFERROR(XLOOKUP(A47,tblAccounts[Account_ID],tblAccounts[Include],FALSE),FALSE),SUMIFS(tblAcctSummary[Income_Other_Base],tblAcctSummary[Account_ID],A47),0)) | J47: =IF(A47="","",SUM(G47:I47)) | K47: =IF(A47="","",IF(IFERROR(XLOOKUP(A47,tblAccounts[Account_ID],tblAccounts[Include],FALSE),FALSE),SUMIFS(tblAcctSummary[Realized_GL_Base],tblAcctSummary[Account_ID],A47),0)) | L47: =IF(A47="","",IF(IFERROR(XLOOKUP(A47,tblAccounts[Account_ID],tblAccounts[Include],FALSE),FALSE),SUMIFS(tblAcctSummary[Fees_Base],tblAcctSummary[Account_ID],A47),0)) | M47: =IF(A47="","",IF(IFERROR(XLOOKUP(A47,tblAccounts[Account_ID],tblAccounts[Include],FALSE),FALSE),SUMIFS(tblAcctSummary[Taxes_Base],tblAcctSummary[Account_ID],A47),0)) | N47: =IF(A47="","",IF(IFERROR(XLOOKUP(A47,tblAccounts[Account_ID],tblAccounts[Include],FALSE),FALSE),IFERROR(SUMPRODUCT(tblAcctSummary[Return_Period],tblAcctSummary[Begin_Balance_Base],--(tblAcctSummary[Account_ID]=A47))/IF(SUMIFS(tblAcctSummary[Begin_Balance_Base],tblAcctSummary[Account_ID],A47)=0,NA(),SUMIFS(tblAcctSummary[Begin_Balance_Base],tblAcctSummary[Account_ID],A47)),0),0))
A48: =IFERROR(INDEX(tblAccounts[Account_ID],45),"") | B48: =IF(A48="","",IFERROR(XLOOKUP(A48,tblAccounts[Account_ID],tblAccounts[Account_Name],""),"")) | C48: =IF(A48="","",IFERROR(XLOOKUP(A48,tblAccounts[Account_ID],tblAccounts[Household_ID],""),"")) | D48: =IF(A48="","",IF(IFERROR(XLOOKUP(A48,tblAccounts[Account_ID],tblAccounts[Include],FALSE),FALSE),SUMIFS(tblAcctSummary[Begin_Balance_Base],tblAcctSummary[Account_ID],A48),0)) | E48: =IF(A48="","",IF(IFERROR(XLOOKUP(A48,tblAccounts[Account_ID],tblAccounts[Include],FALSE),FALSE),SUMIFS(tblAcctSummary[End_Balance_Base],tblAcctSummary[Account_ID],A48),0)) | F48: =IF(A48="","",IF(IFERROR(XLOOKUP(A48,tblAccounts[Account_ID],tblAccounts[Include],FALSE),FALSE),SUMIFS(tblAcctSummary[Net_Contrib_Base],tblAcctSummary[Account_ID],A48),0)) | G48: =IF(A48="","",IF(IFERROR(XLOOKUP(A48,tblAccounts[Account_ID],tblAccounts[Include],FALSE),FALSE),SUMIFS(tblAcctSummary[Income_Interest_Base],tblAcctSummary[Account_ID],A48),0)) | H48: =IF(A48="","",IF(IFERROR(XLOOKUP(A48,tblAccounts[Account_ID],tblAccounts[Include],FALSE),FALSE),SUMIFS(tblAcctSummary[Income_Dividends_Base],tblAcctSummary[Account_ID],A48),0)) | I48: =IF(A48="","",IF(IFERROR(XLOOKUP(A48,tblAccounts[Account_ID],tblAccounts[Include],FALSE),FALSE),SUMIFS(tblAcctSummary[Income_Other_Base],tblAcctSummary[Account_ID],A48),0)) | J48: =IF(A48="","",SUM(G48:I48)) | K48: =IF(A48="","",IF(IFERROR(XLOOKUP(A48,tblAccounts[Account_ID],tblAccounts[Include],FALSE),FALSE),SUMIFS(tblAcctSummary[Realized_GL_Base],tblAcctSummary[Account_ID],A48),0)) | L48: =IF(A48="","",IF(IFERROR(XLOOKUP(A48,tblAccounts[Account_ID],tblAccounts[Include],FALSE),FALSE),SUMIFS(tblAcctSummary[Fees_Base],tblAcctSummary[Account_ID],A48),0)) | M48: =IF(A48="","",IF(IFERROR(XLOOKUP(A48,tblAccounts[Account_ID],tblAccounts[Include],FALSE),FALSE),SUMIFS(tblAcctSummary[Taxes_Base],tblAcctSummary[Account_ID],A48),0)) | N48: =IF(A48="","",IF(IFERROR(XLOOKUP(A48,tblAccounts[Account_ID],tblAccounts[Include],FALSE),FALSE),IFERROR(SUMPRODUCT(tblAcctSummary[Return_Period],tblAcctSummary[Begin_Balance_Base],--(tblAcctSummary[Account_ID]=A48))/IF(SUMIFS(tblAcctSummary[Begin_Balance_Base],tblAcctSummary[Account_ID],A48)=0,NA(),SUMIFS(tblAcctSummary[Begin_Balance_Base],tblAcctSummary[Account_ID],A48)),0),0))
A49: =IFERROR(INDEX(tblAccounts[Account_ID],46),"") | B49: =IF(A49="","",IFERROR(XLOOKUP(A49,tblAccounts[Account_ID],tblAccounts[Account_Name],""),"")) | C49: =IF(A49="","",IFERROR(XLOOKUP(A49,tblAccounts[Account_ID],tblAccounts[Household_ID],""),"")) | D49: =IF(A49="","",IF(IFERROR(XLOOKUP(A49,tblAccounts[Account_ID],tblAccounts[Include],FALSE),FALSE),SUMIFS(tblAcctSummary[Begin_Balance_Base],tblAcctSummary[Account_ID],A49),0)) | E49: =IF(A49="","",IF(IFERROR(XLOOKUP(A49,tblAccounts[Account_ID],tblAccounts[Include],FALSE),FALSE),SUMIFS(tblAcctSummary[End_Balance_Base],tblAcctSummary[Account_ID],A49),0)) | F49: =IF(A49="","",IF(IFERROR(XLOOKUP(A49,tblAccounts[Account_ID],tblAccounts[Include],FALSE),FALSE),SUMIFS(tblAcctSummary[Net_Contrib_Base],tblAcctSummary[Account_ID],A49),0)) | G49: =IF(A49="","",IF(IFERROR(XLOOKUP(A49,tblAccounts[Account_ID],tblAccounts[Include],FALSE),FALSE),SUMIFS(tblAcctSummary[Income_Interest_Base],tblAcctSummary[Account_ID],A49),0)) | H49: =IF(A49="","",IF(IFERROR(XLOOKUP(A49,tblAccounts[Account_ID],tblAccounts[Include],FALSE),FALSE),SUMIFS(tblAcctSummary[Income_Dividends_Base],tblAcctSummary[Account_ID],A49),0)) | I49: =IF(A49="","",IF(IFERROR(XLOOKUP(A49,tblAccounts[Account_ID],tblAccounts[Include],FALSE),FALSE),SUMIFS(tblAcctSummary[Income_Other_Base],tblAcctSummary[Account_ID],A49),0)) | J49: =IF(A49="","",SUM(G49:I49)) | K49: =IF(A49="","",IF(IFERROR(XLOOKUP(A49,tblAccounts[Account_ID],tblAccounts[Include],FALSE),FALSE),SUMIFS(tblAcctSummary[Realized_GL_Base],tblAcctSummary[Account_ID],A49),0)) | L49: =IF(A49="","",IF(IFERROR(XLOOKUP(A49,tblAccounts[Account_ID],tblAccounts[Include],FALSE),FALSE),SUMIFS(tblAcctSummary[Fees_Base],tblAcctSummary[Account_ID],A49),0)) | M49: =IF(A49="","",IF(IFERROR(XLOOKUP(A49,tblAccounts[Account_ID],tblAccounts[Include],FALSE),FALSE),SUMIFS(tblAcctSummary[Taxes_Base],tblAcctSummary[Account_ID],A49),0)) | N49: =IF(A49="","",IF(IFERROR(XLOOKUP(A49,tblAccounts[Account_ID],tblAccounts[Include],FALSE),FALSE),IFERROR(SUMPRODUCT(tblAcctSummary[Return_Period],tblAcctSummary[Begin_Balance_Base],--(tblAcctSummary[Account_ID]=A49))/IF(SUMIFS(tblAcctSummary[Begin_Balance_Base],tblAcctSummary[Account_ID],A49)=0,NA(),SUMIFS(tblAcctSummary[Begin_Balance_Base],tblAcctSummary[Account_ID],A49)),0),0))
A50: =IFERROR(INDEX(tblAccounts[Account_ID],47),"") | B50: =IF(A50="","",IFERROR(XLOOKUP(A50,tblAccounts[Account_ID],tblAccounts[Account_Name],""),"")) | C50: =IF(A50="","",IFERROR(XLOOKUP(A50,tblAccounts[Account_ID],tblAccounts[Household_ID],""),"")) | D50: =IF(A50="","",IF(IFERROR(XLOOKUP(A50,tblAccounts[Account_ID],tblAccounts[Include],FALSE),FALSE),SUMIFS(tblAcctSummary[Begin_Balance_Base],tblAcctSummary[Account_ID],A50),0)) | E50: =IF(A50="","",IF(IFERROR(XLOOKUP(A50,tblAccounts[Account_ID],tblAccounts[Include],FALSE),FALSE),SUMIFS(tblAcctSummary[End_Balance_Base],tblAcctSummary[Account_ID],A50),0)) | F50: =IF(A50="","",IF(IFERROR(XLOOKUP(A50,tblAccounts[Account_ID],tblAccounts[Include],FALSE),FALSE),SUMIFS(tblAcctSummary[Net_Contrib_Base],tblAcctSummary[Account_ID],A50),0)) | G50: =IF(A50="","",IF(IFERROR(XLOOKUP(A50,tblAccounts[Account_ID],tblAccounts[Include],FALSE),FALSE),SUMIFS(tblAcctSummary[Income_Interest_Base],tblAcctSummary[Account_ID],A50),0)) | H50: =IF(A50="","",IF(IFERROR(XLOOKUP(A50,tblAccounts[Account_ID],tblAccounts[Include],FALSE),FALSE),SUMIFS(tblAcctSummary[Income_Dividends_Base],tblAcctSummary[Account_ID],A50),0)) | I50: =IF(A50="","",IF(IFERROR(XLOOKUP(A50,tblAccounts[Account_ID],tblAccounts[Include],FALSE),FALSE),SUMIFS(tblAcctSummary[Income_Other_Base],tblAcctSummary[Account_ID],A50),0)) | J50: =IF(A50="","",SUM(G50:I50)) | K50: =IF(A50="","",IF(IFERROR(XLOOKUP(A50,tblAccounts[Account_ID],tblAccounts[Include],FALSE),FALSE),SUMIFS(tblAcctSummary[Realized_GL_Base],tblAcctSummary[Account_ID],A50),0)) | L50: =IF(A50="","",IF(IFERROR(XLOOKUP(A50,tblAccounts[Account_ID],tblAccounts[Include],FALSE),FALSE),SUMIFS(tblAcctSummary[Fees_Base],tblAcctSummary[Account_ID],A50),0)) | M50: =IF(A50="","",IF(IFERROR(XLOOKUP(A50,tblAccounts[Account_ID],tblAccounts[Include],FALSE),FALSE),SUMIFS(tblAcctSummary[Taxes_Base],tblAcctSummary[Account_ID],A50),0)) | N50: =IF(A50="","",IF(IFERROR(XLOOKUP(A50,tblAccounts[Account_ID],tblAccounts[Include],FALSE),FALSE),IFERROR(SUMPRODUCT(tblAcctSummary[Return_Period],tblAcctSummary[Begin_Balance_Base],--(tblAcctSummary[Account_ID]=A50))/IF(SUMIFS(tblAcctSummary[Begin_Balance_Base],tblAcctSummary[Account_ID],A50)=0,NA(),SUMIFS(tblAcctSummary[Begin_Balance_Base],tblAcctSummary[Account_ID],A50)),0),0))
A51: =IFERROR(INDEX(tblAccounts[Account_ID],48),"") | B51: =IF(A51="","",IFERROR(XLOOKUP(A51,tblAccounts[Account_ID],tblAccounts[Account_Name],""),"")) | C51: =IF(A51="","",IFERROR(XLOOKUP(A51,tblAccounts[Account_ID],tblAccounts[Household_ID],""),"")) | D51: =IF(A51="","",IF(IFERROR(XLOOKUP(A51,tblAccounts[Account_ID],tblAccounts[Include],FALSE),FALSE),SUMIFS(tblAcctSummary[Begin_Balance_Base],tblAcctSummary[Account_ID],A51),0)) | E51: =IF(A51="","",IF(IFERROR(XLOOKUP(A51,tblAccounts[Account_ID],tblAccounts[Include],FALSE),FALSE),SUMIFS(tblAcctSummary[End_Balance_Base],tblAcctSummary[Account_ID],A51),0)) | F51: =IF(A51="","",IF(IFERROR(XLOOKUP(A51,tblAccounts[Account_ID],tblAccounts[Include],FALSE),FALSE),SUMIFS(tblAcctSummary[Net_Contrib_Base],tblAcctSummary[Account_ID],A51),0)) | G51: =IF(A51="","",IF(IFERROR(XLOOKUP(A51,tblAccounts[Account_ID],tblAccounts[Include],FALSE),FALSE),SUMIFS(tblAcctSummary[Income_Interest_Base],tblAcctSummary[Account_ID],A51),0)) | H51: =IF(A51="","",IF(IFERROR(XLOOKUP(A51,tblAccounts[Account_ID],tblAccounts[Include],FALSE),FALSE),SUMIFS(tblAcctSummary[Income_Dividends_Base],tblAcctSummary[Account_ID],A51),0)) | I51: =IF(A51="","",IF(IFERROR(XLOOKUP(A51,tblAccounts[Account_ID],tblAccounts[Include],FALSE),FALSE),SUMIFS(tblAcctSummary[Income_Other_Base],tblAcctSummary[Account_ID],A51),0)) | J51: =IF(A51="","",SUM(G51:I51)) | K51: =IF(A51="","",IF(IFERROR(XLOOKUP(A51,tblAccounts[Account_ID],tblAccounts[Include],FALSE),FALSE),SUMIFS(tblAcctSummary[Realized_GL_Base],tblAcctSummary[Account_ID],A51),0)) | L51: =IF(A51="","",IF(IFERROR(XLOOKUP(A51,tblAccounts[Account_ID],tblAccounts[Include],FALSE),FALSE),SUMIFS(tblAcctSummary[Fees_Base],tblAcctSummary[Account_ID],A51),0)) | M51: =IF(A51="","",IF(IFERROR(XLOOKUP(A51,tblAccounts[Account_ID],tblAccounts[Include],FALSE),FALSE),SUMIFS(tblAcctSummary[Taxes_Base],tblAcctSummary[Account_ID],A51),0)) | N51: =IF(A51="","",IF(IFERROR(XLOOKUP(A51,tblAccounts[Account_ID],tblAccounts[Include],FALSE),FALSE),IFERROR(SUMPRODUCT(tblAcctSummary[Return_Period],tblAcctSummary[Begin_Balance_Base],--(tblAcctSummary[Account_ID]=A51))/IF(SUMIFS(tblAcctSummary[Begin_Balance_Base],tblAcctSummary[Account_ID],A51)=0,NA(),SUMIFS(tblAcctSummary[Begin_Balance_Base],tblAcctSummary[Account_ID],A51)),0),0))
A52: =IFERROR(INDEX(tblAccounts[Account_ID],49),"") | B52: =IF(A52="","",IFERROR(XLOOKUP(A52,tblAccounts[Account_ID],tblAccounts[Account_Name],""),"")) | C52: =IF(A52="","",IFERROR(XLOOKUP(A52,tblAccounts[Account_ID],tblAccounts[Household_ID],""),"")) | D52: =IF(A52="","",IF(IFERROR(XLOOKUP(A52,tblAccounts[Account_ID],tblAccounts[Include],FALSE),FALSE),SUMIFS(tblAcctSummary[Begin_Balance_Base],tblAcctSummary[Account_ID],A52),0)) | E52: =IF(A52="","",IF(IFERROR(XLOOKUP(A52,tblAccounts[Account_ID],tblAccounts[Include],FALSE),FALSE),SUMIFS(tblAcctSummary[End_Balance_Base],tblAcctSummary[Account_ID],A52),0)) | F52: =IF(A52="","",IF(IFERROR(XLOOKUP(A52,tblAccounts[Account_ID],tblAccounts[Include],FALSE),FALSE),SUMIFS(tblAcctSummary[Net_Contrib_Base],tblAcctSummary[Account_ID],A52),0)) | G52: =IF(A52="","",IF(IFERROR(XLOOKUP(A52,tblAccounts[Account_ID],tblAccounts[Include],FALSE),FALSE),SUMIFS(tblAcctSummary[Income_Interest_Base],tblAcctSummary[Account_ID],A52),0)) | H52: =IF(A52="","",IF(IFERROR(XLOOKUP(A52,tblAccounts[Account_ID],tblAccounts[Include],FALSE),FALSE),SUMIFS(tblAcctSummary[Income_Dividends_Base],tblAcctSummary[Account_ID],A52),0)) | I52: =IF(A52="","",IF(IFERROR(XLOOKUP(A52,tblAccounts[Account_ID],tblAccounts[Include],FALSE),FALSE),SUMIFS(tblAcctSummary[Income_Other_Base],tblAcctSummary[Account_ID],A52),0)) | J52: =IF(A52="","",SUM(G52:I52)) | K52: =IF(A52="","",IF(IFERROR(XLOOKUP(A52,tblAccounts[Account_ID],tblAccounts[Include],FALSE),FALSE),SUMIFS(tblAcctSummary[Realized_GL_Base],tblAcctSummary[Account_ID],A52),0)) | L52: =IF(A52="","",IF(IFERROR(XLOOKUP(A52,tblAccounts[Account_ID],tblAccounts[Include],FALSE),FALSE),SUMIFS(tblAcctSummary[Fees_Base],tblAcctSummary[Account_ID],A52),0)) | M52: =IF(A52="","",IF(IFERROR(XLOOKUP(A52,tblAccounts[Account_ID],tblAccounts[Include],FALSE),FALSE),SUMIFS(tblAcctSummary[Taxes_Base],tblAcctSummary[Account_ID],A52),0)) | N52: =IF(A52="","",IF(IFERROR(XLOOKUP(A52,tblAccounts[Account_ID],tblAccounts[Include],FALSE),FALSE),IFERROR(SUMPRODUCT(tblAcctSummary[Return_Period],tblAcctSummary[Begin_Balance_Base],--(tblAcctSummary[Account_ID]=A52))/IF(SUMIFS(tblAcctSummary[Begin_Balance_Base],tblAcctSummary[Account_ID],A52)=0,NA(),SUMIFS(tblAcctSummary[Begin_Balance_Base],tblAcctSummary[Account_ID],A52)),0),0))
A53: =IFERROR(INDEX(tblAccounts[Account_ID],50),"") | B53: =IF(A53="","",IFERROR(XLOOKUP(A53,tblAccounts[Account_ID],tblAccounts[Account_Name],""),"")) | C53: =IF(A53="","",IFERROR(XLOOKUP(A53,tblAccounts[Account_ID],tblAccounts[Household_ID],""),"")) | D53: =IF(A53="","",IF(IFERROR(XLOOKUP(A53,tblAccounts[Account_ID],tblAccounts[Include],FALSE),FALSE),SUMIFS(tblAcctSummary[Begin_Balance_Base],tblAcctSummary[Account_ID],A53),0)) | E53: =IF(A53="","",IF(IFERROR(XLOOKUP(A53,tblAccounts[Account_ID],tblAccounts[Include],FALSE),FALSE),SUMIFS(tblAcctSummary[End_Balance_Base],tblAcctSummary[Account_ID],A53),0)) | F53: =IF(A53="","",IF(IFERROR(XLOOKUP(A53,tblAccounts[Account_ID],tblAccounts[Include],FALSE),FALSE),SUMIFS(tblAcctSummary[Net_Contrib_Base],tblAcctSummary[Account_ID],A53),0)) | G53: =IF(A53="","",IF(IFERROR(XLOOKUP(A53,tblAccounts[Account_ID],tblAccounts[Include],FALSE),FALSE),SUMIFS(tblAcctSummary[Income_Interest_Base],tblAcctSummary[Account_ID],A53),0)) | H53: =IF(A53="","",IF(IFERROR(XLOOKUP(A53,tblAccounts[Account_ID],tblAccounts[Include],FALSE),FALSE),SUMIFS(tblAcctSummary[Income_Dividends_Base],tblAcctSummary[Account_ID],A53),0)) | I53: =IF(A53="","",IF(IFERROR(XLOOKUP(A53,tblAccounts[Account_ID],tblAccounts[Include],FALSE),FALSE),SUMIFS(tblAcctSummary[Income_Other_Base],tblAcctSummary[Account_ID],A53),0)) | J53: =IF(A53="","",SUM(G53:I53)) | K53: =IF(A53="","",IF(IFERROR(XLOOKUP(A53,tblAccounts[Account_ID],tblAccounts[Include],FALSE),FALSE),SUMIFS(tblAcctSummary[Realized_GL_Base],tblAcctSummary[Account_ID],A53),0)) | L53: =IF(A53="","",IF(IFERROR(XLOOKUP(A53,tblAccounts[Account_ID],tblAccounts[Include],FALSE),FALSE),SUMIFS(tblAcctSummary[Fees_Base],tblAcctSummary[Account_ID],A53),0)) | M53: =IF(A53="","",IF(IFERROR(XLOOKUP(A53,tblAccounts[Account_ID],tblAccounts[Include],FALSE),FALSE),SUMIFS(tblAcctSummary[Taxes_Base],tblAcctSummary[Account_ID],A53),0)) | N53: =IF(A53="","",IF(IFERROR(XLOOKUP(A53,tblAccounts[Account_ID],tblAccounts[Include],FALSE),FALSE),IFERROR(SUMPRODUCT(tblAcctSummary[Return_Period],tblAcctSummary[Begin_Balance_Base],--(tblAcctSummary[Account_ID]=A53))/IF(SUMIFS(tblAcctSummary[Begin_Balance_Base],tblAcctSummary[Account_ID],A53)=0,NA(),SUMIFS(tblAcctSummary[Begin_Balance_Base],tblAcctSummary[Account_ID],A53)),0),0))
A54: =IFERROR(INDEX(tblAccounts[Account_ID],51),"") | B54: =IF(A54="","",IFERROR(XLOOKUP(A54,tblAccounts[Account_ID],tblAccounts[Account_Name],""),"")) | C54: =IF(A54="","",IFERROR(XLOOKUP(A54,tblAccounts[Account_ID],tblAccounts[Household_ID],""),"")) | D54: =IF(A54="","",IF(IFERROR(XLOOKUP(A54,tblAccounts[Account_ID],tblAccounts[Include],FALSE),FALSE),SUMIFS(tblAcctSummary[Begin_Balance_Base],tblAcctSummary[Account_ID],A54),0)) | E54: =IF(A54="","",IF(IFERROR(XLOOKUP(A54,tblAccounts[Account_ID],tblAccounts[Include],FALSE),FALSE),SUMIFS(tblAcctSummary[End_Balance_Base],tblAcctSummary[Account_ID],A54),0)) | F54: =IF(A54="","",IF(IFERROR(XLOOKUP(A54,tblAccounts[Account_ID],tblAccounts[Include],FALSE),FALSE),SUMIFS(tblAcctSummary[Net_Contrib_Base],tblAcctSummary[Account_ID],A54),0)) | G54: =IF(A54="","",IF(IFERROR(XLOOKUP(A54,tblAccounts[Account_ID],tblAccounts[Include],FALSE),FALSE),SUMIFS(tblAcctSummary[Income_Interest_Base],tblAcctSummary[Account_ID],A54),0)) | H54: =IF(A54="","",IF(IFERROR(XLOOKUP(A54,tblAccounts[Account_ID],tblAccounts[Include],FALSE),FALSE),SUMIFS(tblAcctSummary[Income_Dividends_Base],tblAcctSummary[Account_ID],A54),0)) | I54: =IF(A54="","",IF(IFERROR(XLOOKUP(A54,tblAccounts[Account_ID],tblAccounts[Include],FALSE),FALSE),SUMIFS(tblAcctSummary[Income_Other_Base],tblAcctSummary[Account_ID],A54),0)) | J54: =IF(A54="","",SUM(G54:I54)) | K54: =IF(A54="","",IF(IFERROR(XLOOKUP(A54,tblAccounts[Account_ID],tblAccounts[Include],FALSE),FALSE),SUMIFS(tblAcctSummary[Realized_GL_Base],tblAcctSummary[Account_ID],A54),0)) | L54: =IF(A54="","",IF(IFERROR(XLOOKUP(A54,tblAccounts[Account_ID],tblAccounts[Include],FALSE),FALSE),SUMIFS(tblAcctSummary[Fees_Base],tblAcctSummary[Account_ID],A54),0)) | M54: =IF(A54="","",IF(IFERROR(XLOOKUP(A54,tblAccounts[Account_ID],tblAccounts[Include],FALSE),FALSE),SUMIFS(tblAcctSummary[Taxes_Base],tblAcctSummary[Account_ID],A54),0)) | N54: =IF(A54="","",IF(IFERROR(XLOOKUP(A54,tblAccounts[Account_ID],tblAccounts[Include],FALSE),FALSE),IFERROR(SUMPRODUCT(tblAcctSummary[Return_Period],tblAcctSummary[Begin_Balance_Base],--(tblAcctSummary[Account_ID]=A54))/IF(SUMIFS(tblAcctSummary[Begin_Balance_Base],tblAcctSummary[Account_ID],A54)=0,NA(),SUMIFS(tblAcctSummary[Begin_Balance_Base],tblAcctSummary[Account_ID],A54)),0),0))
A55: =IFERROR(INDEX(tblAccounts[Account_ID],52),"") | B55: =IF(A55="","",IFERROR(XLOOKUP(A55,tblAccounts[Account_ID],tblAccounts[Account_Name],""),"")) | C55: =IF(A55="","",IFERROR(XLOOKUP(A55,tblAccounts[Account_ID],tblAccounts[Household_ID],""),"")) | D55: =IF(A55="","",IF(IFERROR(XLOOKUP(A55,tblAccounts[Account_ID],tblAccounts[Include],FALSE),FALSE),SUMIFS(tblAcctSummary[Begin_Balance_Base],tblAcctSummary[Account_ID],A55),0)) | E55: =IF(A55="","",IF(IFERROR(XLOOKUP(A55,tblAccounts[Account_ID],tblAccounts[Include],FALSE),FALSE),SUMIFS(tblAcctSummary[End_Balance_Base],tblAcctSummary[Account_ID],A55),0)) | F55: =IF(A55="","",IF(IFERROR(XLOOKUP(A55,tblAccounts[Account_ID],tblAccounts[Include],FALSE),FALSE),SUMIFS(tblAcctSummary[Net_Contrib_Base],tblAcctSummary[Account_ID],A55),0)) | G55: =IF(A55="","",IF(IFERROR(XLOOKUP(A55,tblAccounts[Account_ID],tblAccounts[Include],FALSE),FALSE),SUMIFS(tblAcctSummary[Income_Interest_Base],tblAcctSummary[Account_ID],A55),0)) | H55: =IF(A55="","",IF(IFERROR(XLOOKUP(A55,tblAccounts[Account_ID],tblAccounts[Include],FALSE),FALSE),SUMIFS(tblAcctSummary[Income_Dividends_Base],tblAcctSummary[Account_ID],A55),0)) | I55: =IF(A55="","",IF(IFERROR(XLOOKUP(A55,tblAccounts[Account_ID],tblAccounts[Include],FALSE),FALSE),SUMIFS(tblAcctSummary[Income_Other_Base],tblAcctSummary[Account_ID],A55),0)) | J55: =IF(A55="","",SUM(G55:I55)) | K55: =IF(A55="","",IF(IFERROR(XLOOKUP(A55,tblAccounts[Account_ID],tblAccounts[Include],FALSE),FALSE),SUMIFS(tblAcctSummary[Realized_GL_Base],tblAcctSummary[Account_ID],A55),0)) | L55: =IF(A55="","",IF(IFERROR(XLOOKUP(A55,tblAccounts[Account_ID],tblAccounts[Include],FALSE),FALSE),SUMIFS(tblAcctSummary[Fees_Base],tblAcctSummary[Account_ID],A55),0)) | M55: =IF(A55="","",IF(IFERROR(XLOOKUP(A55,tblAccounts[Account_ID],tblAccounts[Include],FALSE),FALSE),SUMIFS(tblAcctSummary[Taxes_Base],tblAcctSummary[Account_ID],A55),0)) | N55: =IF(A55="","",IF(IFERROR(XLOOKUP(A55,tblAccounts[Account_ID],tblAccounts[Include],FALSE),FALSE),IFERROR(SUMPRODUCT(tblAcctSummary[Return_Period],tblAcctSummary[Begin_Balance_Base],--(tblAcctSummary[Account_ID]=A55))/IF(SUMIFS(tblAcctSummary[Begin_Balance_Base],tblAcctSummary[Account_ID],A55)=0,NA(),SUMIFS(tblAcctSummary[Begin_Balance_Base],tblAcctSummary[Account_ID],A55)),0),0))
A56: =IFERROR(INDEX(tblAccounts[Account_ID],53),"") | B56: =IF(A56="","",IFERROR(XLOOKUP(A56,tblAccounts[Account_ID],tblAccounts[Account_Name],""),"")) | C56: =IF(A56="","",IFERROR(XLOOKUP(A56,tblAccounts[Account_ID],tblAccounts[Household_ID],""),"")) | D56: =IF(A56="","",IF(IFERROR(XLOOKUP(A56,tblAccounts[Account_ID],tblAccounts[Include],FALSE),FALSE),SUMIFS(tblAcctSummary[Begin_Balance_Base],tblAcctSummary[Account_ID],A56),0)) | E56: =IF(A56="","",IF(IFERROR(XLOOKUP(A56,tblAccounts[Account_ID],tblAccounts[Include],FALSE),FALSE),SUMIFS(tblAcctSummary[End_Balance_Base],tblAcctSummary[Account_ID],A56),0)) | F56: =IF(A56="","",IF(IFERROR(XLOOKUP(A56,tblAccounts[Account_ID],tblAccounts[Include],FALSE),FALSE),SUMIFS(tblAcctSummary[Net_Contrib_Base],tblAcctSummary[Account_ID],A56),0)) | G56: =IF(A56="","",IF(IFERROR(XLOOKUP(A56,tblAccounts[Account_ID],tblAccounts[Include],FALSE),FALSE),SUMIFS(tblAcctSummary[Income_Interest_Base],tblAcctSummary[Account_ID],A56),0)) | H56: =IF(A56="","",IF(IFERROR(XLOOKUP(A56,tblAccounts[Account_ID],tblAccounts[Include],FALSE),FALSE),SUMIFS(tblAcctSummary[Income_Dividends_Base],tblAcctSummary[Account_ID],A56),0)) | I56: =IF(A56="","",IF(IFERROR(XLOOKUP(A56,tblAccounts[Account_ID],tblAccounts[Include],FALSE),FALSE),SUMIFS(tblAcctSummary[Income_Other_Base],tblAcctSummary[Account_ID],A56),0)) | J56: =IF(A56="","",SUM(G56:I56)) | K56: =IF(A56="","",IF(IFERROR(XLOOKUP(A56,tblAccounts[Account_ID],tblAccounts[Include],FALSE),FALSE),SUMIFS(tblAcctSummary[Realized_GL_Base],tblAcctSummary[Account_ID],A56),0)) | L56: =IF(A56="","",IF(IFERROR(XLOOKUP(A56,tblAccounts[Account_ID],tblAccounts[Include],FALSE),FALSE),SUMIFS(tblAcctSummary[Fees_Base],tblAcctSummary[Account_ID],A56),0)) | M56: =IF(A56="","",IF(IFERROR(XLOOKUP(A56,tblAccounts[Account_ID],tblAccounts[Include],FALSE),FALSE),SUMIFS(tblAcctSummary[Taxes_Base],tblAcctSummary[Account_ID],A56),0)) | N56: =IF(A56="","",IF(IFERROR(XLOOKUP(A56,tblAccounts[Account_ID],tblAccounts[Include],FALSE),FALSE),IFERROR(SUMPRODUCT(tblAcctSummary[Return_Period],tblAcctSummary[Begin_Balance_Base],--(tblAcctSummary[Account_ID]=A56))/IF(SUMIFS(tblAcctSummary[Begin_Balance_Base],tblAcctSummary[Account_ID],A56)=0,NA(),SUMIFS(tblAcctSummary[Begin_Balance_Base],tblAcctSummary[Account_ID],A56)),0),0))
A57: =IFERROR(INDEX(tblAccounts[Account_ID],54),"") | B57: =IF(A57="","",IFERROR(XLOOKUP(A57,tblAccounts[Account_ID],tblAccounts[Account_Name],""),"")) | C57: =IF(A57="","",IFERROR(XLOOKUP(A57,tblAccounts[Account_ID],tblAccounts[Household_ID],""),"")) | D57: =IF(A57="","",IF(IFERROR(XLOOKUP(A57,tblAccounts[Account_ID],tblAccounts[Include],FALSE),FALSE),SUMIFS(tblAcctSummary[Begin_Balance_Base],tblAcctSummary[Account_ID],A57),0)) | E57: =IF(A57="","",IF(IFERROR(XLOOKUP(A57,tblAccounts[Account_ID],tblAccounts[Include],FALSE),FALSE),SUMIFS(tblAcctSummary[End_Balance_Base],tblAcctSummary[Account_ID],A57),0)) | F57: =IF(A57="","",IF(IFERROR(XLOOKUP(A57,tblAccounts[Account_ID],tblAccounts[Include],FALSE),FALSE),SUMIFS(tblAcctSummary[Net_Contrib_Base],tblAcctSummary[Account_ID],A57),0)) | G57: =IF(A57="","",IF(IFERROR(XLOOKUP(A57,tblAccounts[Account_ID],tblAccounts[Include],FALSE),FALSE),SUMIFS(tblAcctSummary[Income_Interest_Base],tblAcctSummary[Account_ID],A57),0)) | H57: =IF(A57="","",IF(IFERROR(XLOOKUP(A57,tblAccounts[Account_ID],tblAccounts[Include],FALSE),FALSE),SUMIFS(tblAcctSummary[Income_Dividends_Base],tblAcctSummary[Account_ID],A57),0)) | I57: =IF(A57="","",IF(IFERROR(XLOOKUP(A57,tblAccounts[Account_ID],tblAccounts[Include],FALSE),FALSE),SUMIFS(tblAcctSummary[Income_Other_Base],tblAcctSummary[Account_ID],A57),0)) | J57: =IF(A57="","",SUM(G57:I57)) | K57: =IF(A57="","",IF(IFERROR(XLOOKUP(A57,tblAccounts[Account_ID],tblAccounts[Include],FALSE),FALSE),SUMIFS(tblAcctSummary[Realized_GL_Base],tblAcctSummary[Account_ID],A57),0)) | L57: =IF(A57="","",IF(IFERROR(XLOOKUP(A57,tblAccounts[Account_ID],tblAccounts[Include],FALSE),FALSE),SUMIFS(tblAcctSummary[Fees_Base],tblAcctSummary[Account_ID],A57),0)) | M57: =IF(A57="","",IF(IFERROR(XLOOKUP(A57,tblAccounts[Account_ID],tblAccounts[Include],FALSE),FALSE),SUMIFS(tblAcctSummary[Taxes_Base],tblAcctSummary[Account_ID],A57),0)) | N57: =IF(A57="","",IF(IFERROR(XLOOKUP(A57,tblAccounts[Account_ID],tblAccounts[Include],FALSE),FALSE),IFERROR(SUMPRODUCT(tblAcctSummary[Return_Period],tblAcctSummary[Begin_Balance_Base],--(tblAcctSummary[Account_ID]=A57))/IF(SUMIFS(tblAcctSummary[Begin_Balance_Base],tblAcctSummary[Account_ID],A57)=0,NA(),SUMIFS(tblAcctSummary[Begin_Balance_Base],tblAcctSummary[Account_ID],A57)),0),0))
A58: =IFERROR(INDEX(tblAccounts[Account_ID],55),"") | B58: =IF(A58="","",IFERROR(XLOOKUP(A58,tblAccounts[Account_ID],tblAccounts[Account_Name],""),"")) | C58: =IF(A58="","",IFERROR(XLOOKUP(A58,tblAccounts[Account_ID],tblAccounts[Household_ID],""),"")) | D58: =IF(A58="","",IF(IFERROR(XLOOKUP(A58,tblAccounts[Account_ID],tblAccounts[Include],FALSE),FALSE),SUMIFS(tblAcctSummary[Begin_Balance_Base],tblAcctSummary[Account_ID],A58),0)) | E58: =IF(A58="","",IF(IFERROR(XLOOKUP(A58,tblAccounts[Account_ID],tblAccounts[Include],FALSE),FALSE),SUMIFS(tblAcctSummary[End_Balance_Base],tblAcctSummary[Account_ID],A58),0)) | F58: =IF(A58="","",IF(IFERROR(XLOOKUP(A58,tblAccounts[Account_ID],tblAccounts[Include],FALSE),FALSE),SUMIFS(tblAcctSummary[Net_Contrib_Base],tblAcctSummary[Account_ID],A58),0)) | G58: =IF(A58="","",IF(IFERROR(XLOOKUP(A58,tblAccounts[Account_ID],tblAccounts[Include],FALSE),FALSE),SUMIFS(tblAcctSummary[Income_Interest_Base],tblAcctSummary[Account_ID],A58),0)) | H58: =IF(A58="","",IF(IFERROR(XLOOKUP(A58,tblAccounts[Account_ID],tblAccounts[Include],FALSE),FALSE),SUMIFS(tblAcctSummary[Income_Dividends_Base],tblAcctSummary[Account_ID],A58),0)) | I58: =IF(A58="","",IF(IFERROR(XLOOKUP(A58,tblAccounts[Account_ID],tblAccounts[Include],FALSE),FALSE),SUMIFS(tblAcctSummary[Income_Other_Base],tblAcctSummary[Account_ID],A58),0)) | J58: =IF(A58="","",SUM(G58:I58)) | K58: =IF(A58="","",IF(IFERROR(XLOOKUP(A58,tblAccounts[Account_ID],tblAccounts[Include],FALSE),FALSE),SUMIFS(tblAcctSummary[Realized_GL_Base],tblAcctSummary[Account_ID],A58),0)) | L58: =IF(A58="","",IF(IFERROR(XLOOKUP(A58,tblAccounts[Account_ID],tblAccounts[Include],FALSE),FALSE),SUMIFS(tblAcctSummary[Fees_Base],tblAcctSummary[Account_ID],A58),0)) | M58: =IF(A58="","",IF(IFERROR(XLOOKUP(A58,tblAccounts[Account_ID],tblAccounts[Include],FALSE),FALSE),SUMIFS(tblAcctSummary[Taxes_Base],tblAcctSummary[Account_ID],A58),0)) | N58: =IF(A58="","",IF(IFERROR(XLOOKUP(A58,tblAccounts[Account_ID],tblAccounts[Include],FALSE),FALSE),IFERROR(SUMPRODUCT(tblAcctSummary[Return_Period],tblAcctSummary[Begin_Balance_Base],--(tblAcctSummary[Account_ID]=A58))/IF(SUMIFS(tblAcctSummary[Begin_Balance_Base],tblAcctSummary[Account_ID],A58)=0,NA(),SUMIFS(tblAcctSummary[Begin_Balance_Base],tblAcctSummary[Account_ID],A58)),0),0))
A59: =IFERROR(INDEX(tblAccounts[Account_ID],56),"") | B59: =IF(A59="","",IFERROR(XLOOKUP(A59,tblAccounts[Account_ID],tblAccounts[Account_Name],""),"")) | C59: =IF(A59="","",IFERROR(XLOOKUP(A59,tblAccounts[Account_ID],tblAccounts[Household_ID],""),"")) | D59: =IF(A59="","",IF(IFERROR(XLOOKUP(A59,tblAccounts[Account_ID],tblAccounts[Include],FALSE),FALSE),SUMIFS(tblAcctSummary[Begin_Balance_Base],tblAcctSummary[Account_ID],A59),0)) | E59: =IF(A59="","",IF(IFERROR(XLOOKUP(A59,tblAccounts[Account_ID],tblAccounts[Include],FALSE),FALSE),SUMIFS(tblAcctSummary[End_Balance_Base],tblAcctSummary[Account_ID],A59),0)) | F59: =IF(A59="","",IF(IFERROR(XLOOKUP(A59,tblAccounts[Account_ID],tblAccounts[Include],FALSE),FALSE),SUMIFS(tblAcctSummary[Net_Contrib_Base],tblAcctSummary[Account_ID],A59),0)) | G59: =IF(A59="","",IF(IFERROR(XLOOKUP(A59,tblAccounts[Account_ID],tblAccounts[Include],FALSE),FALSE),SUMIFS(tblAcctSummary[Income_Interest_Base],tblAcctSummary[Account_ID],A59),0)) | H59: =IF(A59="","",IF(IFERROR(XLOOKUP(A59,tblAccounts[Account_ID],tblAccounts[Include],FALSE),FALSE),SUMIFS(tblAcctSummary[Income_Dividends_Base],tblAcctSummary[Account_ID],A59),0)) | I59: =IF(A59="","",IF(IFERROR(XLOOKUP(A59,tblAccounts[Account_ID],tblAccounts[Include],FALSE),FALSE),SUMIFS(tblAcctSummary[Income_Other_Base],tblAcctSummary[Account_ID],A59),0)) | J59: =IF(A59="","",SUM(G59:I59)) | K59: =IF(A59="","",IF(IFERROR(XLOOKUP(A59,tblAccounts[Account_ID],tblAccounts[Include],FALSE),FALSE),SUMIFS(tblAcctSummary[Realized_GL_Base],tblAcctSummary[Account_ID],A59),0)) | L59: =IF(A59="","",IF(IFERROR(XLOOKUP(A59,tblAccounts[Account_ID],tblAccounts[Include],FALSE),FALSE),SUMIFS(tblAcctSummary[Fees_Base],tblAcctSummary[Account_ID],A59),0)) | M59: =IF(A59="","",IF(IFERROR(XLOOKUP(A59,tblAccounts[Account_ID],tblAccounts[Include],FALSE),FALSE),SUMIFS(tblAcctSummary[Taxes_Base],tblAcctSummary[Account_ID],A59),0)) | N59: =IF(A59="","",IF(IFERROR(XLOOKUP(A59,tblAccounts[Account_ID],tblAccounts[Include],FALSE),FALSE),IFERROR(SUMPRODUCT(tblAcctSummary[Return_Period],tblAcctSummary[Begin_Balance_Base],--(tblAcctSummary[Account_ID]=A59))/IF(SUMIFS(tblAcctSummary[Begin_Balance_Base],tblAcctSummary[Account_ID],A59)=0,NA(),SUMIFS(tblAcctSummary[Begin_Balance_Base],tblAcctSummary[Account_ID],A59)),0),0))
A60: =IFERROR(INDEX(tblAccounts[Account_ID],57),"") | B60: =IF(A60="","",IFERROR(XLOOKUP(A60,tblAccounts[Account_ID],tblAccounts[Account_Name],""),"")) | C60: =IF(A60="","",IFERROR(XLOOKUP(A60,tblAccounts[Account_ID],tblAccounts[Household_ID],""),"")) | D60: =IF(A60="","",IF(IFERROR(XLOOKUP(A60,tblAccounts[Account_ID],tblAccounts[Include],FALSE),FALSE),SUMIFS(tblAcctSummary[Begin_Balance_Base],tblAcctSummary[Account_ID],A60),0)) | E60: =IF(A60="","",IF(IFERROR(XLOOKUP(A60,tblAccounts[Account_ID],tblAccounts[Include],FALSE),FALSE),SUMIFS(tblAcctSummary[End_Balance_Base],tblAcctSummary[Account_ID],A60),0)) | F60: =IF(A60="","",IF(IFERROR(XLOOKUP(A60,tblAccounts[Account_ID],tblAccounts[Include],FALSE),FALSE),SUMIFS(tblAcctSummary[Net_Contrib_Base],tblAcctSummary[Account_ID],A60),0)) | G60: =IF(A60="","",IF(IFERROR(XLOOKUP(A60,tblAccounts[Account_ID],tblAccounts[Include],FALSE),FALSE),SUMIFS(tblAcctSummary[Income_Interest_Base],tblAcctSummary[Account_ID],A60),0)) | H60: =IF(A60="","",IF(IFERROR(XLOOKUP(A60,tblAccounts[Account_ID],tblAccounts[Include],FALSE),FALSE),SUMIFS(tblAcctSummary[Income_Dividends_Base],tblAcctSummary[Account_ID],A60),0)) | I60: =IF(A60="","",IF(IFERROR(XLOOKUP(A60,tblAccounts[Account_ID],tblAccounts[Include],FALSE),FALSE),SUMIFS(tblAcctSummary[Income_Other_Base],tblAcctSummary[Account_ID],A60),0)) | J60: =IF(A60="","",SUM(G60:I60)) | K60: =IF(A60="","",IF(IFERROR(XLOOKUP(A60,tblAccounts[Account_ID],tblAccounts[Include],FALSE),FALSE),SUMIFS(tblAcctSummary[Realized_GL_Base],tblAcctSummary[Account_ID],A60),0)) | L60: =IF(A60="","",IF(IFERROR(XLOOKUP(A60,tblAccounts[Account_ID],tblAccounts[Include],FALSE),FALSE),SUMIFS(tblAcctSummary[Fees_Base],tblAcctSummary[Account_ID],A60),0)) | M60: =IF(A60="","",IF(IFERROR(XLOOKUP(A60,tblAccounts[Account_ID],tblAccounts[Include],FALSE),FALSE),SUMIFS(tblAcctSummary[Taxes_Base],tblAcctSummary[Account_ID],A60),0)) | N60: =IF(A60="","",IF(IFERROR(XLOOKUP(A60,tblAccounts[Account_ID],tblAccounts[Include],FALSE),FALSE),IFERROR(SUMPRODUCT(tblAcctSummary[Return_Period],tblAcctSummary[Begin_Balance_Base],--(tblAcctSummary[Account_ID]=A60))/IF(SUMIFS(tblAcctSummary[Begin_Balance_Base],tblAcctSummary[Account_ID],A60)=0,NA(),SUMIFS(tblAcctSummary[Begin_Balance_Base],tblAcctSummary[Account_ID],A60)),0),0))
A61: =IFERROR(INDEX(tblAccounts[Account_ID],58),"") | B61: =IF(A61="","",IFERROR(XLOOKUP(A61,tblAccounts[Account_ID],tblAccounts[Account_Name],""),"")) | C61: =IF(A61="","",IFERROR(XLOOKUP(A61,tblAccounts[Account_ID],tblAccounts[Household_ID],""),"")) | D61: =IF(A61="","",IF(IFERROR(XLOOKUP(A61,tblAccounts[Account_ID],tblAccounts[Include],FALSE),FALSE),SUMIFS(tblAcctSummary[Begin_Balance_Base],tblAcctSummary[Account_ID],A61),0)) | E61: =IF(A61="","",IF(IFERROR(XLOOKUP(A61,tblAccounts[Account_ID],tblAccounts[Include],FALSE),FALSE),SUMIFS(tblAcctSummary[End_Balance_Base],tblAcctSummary[Account_ID],A61),0)) | F61: =IF(A61="","",IF(IFERROR(XLOOKUP(A61,tblAccounts[Account_ID],tblAccounts[Include],FALSE),FALSE),SUMIFS(tblAcctSummary[Net_Contrib_Base],tblAcctSummary[Account_ID],A61),0)) | G61: =IF(A61="","",IF(IFERROR(XLOOKUP(A61,tblAccounts[Account_ID],tblAccounts[Include],FALSE),FALSE),SUMIFS(tblAcctSummary[Income_Interest_Base],tblAcctSummary[Account_ID],A61),0)) | H61: =IF(A61="","",IF(IFERROR(XLOOKUP(A61,tblAccounts[Account_ID],tblAccounts[Include],FALSE),FALSE),SUMIFS(tblAcctSummary[Income_Dividends_Base],tblAcctSummary[Account_ID],A61),0)) | I61: =IF(A61="","",IF(IFERROR(XLOOKUP(A61,tblAccounts[Account_ID],tblAccounts[Include],FALSE),FALSE),SUMIFS(tblAcctSummary[Income_Other_Base],tblAcctSummary[Account_ID],A61),0)) | J61: =IF(A61="","",SUM(G61:I61)) | K61: =IF(A61="","",IF(IFERROR(XLOOKUP(A61,tblAccounts[Account_ID],tblAccounts[Include],FALSE),FALSE),SUMIFS(tblAcctSummary[Realized_GL_Base],tblAcctSummary[Account_ID],A61),0)) | L61: =IF(A61="","",IF(IFERROR(XLOOKUP(A61,tblAccounts[Account_ID],tblAccounts[Include],FALSE),FALSE),SUMIFS(tblAcctSummary[Fees_Base],tblAcctSummary[Account_ID],A61),0)) | M61: =IF(A61="","",IF(IFERROR(XLOOKUP(A61,tblAccounts[Account_ID],tblAccounts[Include],FALSE),FALSE),SUMIFS(tblAcctSummary[Taxes_Base],tblAcctSummary[Account_ID],A61),0)) | N61: =IF(A61="","",IF(IFERROR(XLOOKUP(A61,tblAccounts[Account_ID],tblAccounts[Include],FALSE),FALSE),IFERROR(SUMPRODUCT(tblAcctSummary[Return_Period],tblAcctSummary[Begin_Balance_Base],--(tblAcctSummary[Account_ID]=A61))/IF(SUMIFS(tblAcctSummary[Begin_Balance_Base],tblAcctSummary[Account_ID],A61)=0,NA(),SUMIFS(tblAcctSummary[Begin_Balance_Base],tblAcctSummary[Account_ID],A61)),0),0))
A62: =IFERROR(INDEX(tblAccounts[Account_ID],59),"") | B62: =IF(A62="","",IFERROR(XLOOKUP(A62,tblAccounts[Account_ID],tblAccounts[Account_Name],""),"")) | C62: =IF(A62="","",IFERROR(XLOOKUP(A62,tblAccounts[Account_ID],tblAccounts[Household_ID],""),"")) | D62: =IF(A62="","",IF(IFERROR(XLOOKUP(A62,tblAccounts[Account_ID],tblAccounts[Include],FALSE),FALSE),SUMIFS(tblAcctSummary[Begin_Balance_Base],tblAcctSummary[Account_ID],A62),0)) | E62: =IF(A62="","",IF(IFERROR(XLOOKUP(A62,tblAccounts[Account_ID],tblAccounts[Include],FALSE),FALSE),SUMIFS(tblAcctSummary[End_Balance_Base],tblAcctSummary[Account_ID],A62),0)) | F62: =IF(A62="","",IF(IFERROR(XLOOKUP(A62,tblAccounts[Account_ID],tblAccounts[Include],FALSE),FALSE),SUMIFS(tblAcctSummary[Net_Contrib_Base],tblAcctSummary[Account_ID],A62),0)) | G62: =IF(A62="","",IF(IFERROR(XLOOKUP(A62,tblAccounts[Account_ID],tblAccounts[Include],FALSE),FALSE),SUMIFS(tblAcctSummary[Income_Interest_Base],tblAcctSummary[Account_ID],A62),0)) | H62: =IF(A62="","",IF(IFERROR(XLOOKUP(A62,tblAccounts[Account_ID],tblAccounts[Include],FALSE),FALSE),SUMIFS(tblAcctSummary[Income_Dividends_Base],tblAcctSummary[Account_ID],A62),0)) | I62: =IF(A62="","",IF(IFERROR(XLOOKUP(A62,tblAccounts[Account_ID],tblAccounts[Include],FALSE),FALSE),SUMIFS(tblAcctSummary[Income_Other_Base],tblAcctSummary[Account_ID],A62),0)) | J62: =IF(A62="","",SUM(G62:I62)) | K62: =IF(A62="","",IF(IFERROR(XLOOKUP(A62,tblAccounts[Account_ID],tblAccounts[Include],FALSE),FALSE),SUMIFS(tblAcctSummary[Realized_GL_Base],tblAcctSummary[Account_ID],A62),0)) | L62: =IF(A62="","",IF(IFERROR(XLOOKUP(A62,tblAccounts[Account_ID],tblAccounts[Include],FALSE),FALSE),SUMIFS(tblAcctSummary[Fees_Base],tblAcctSummary[Account_ID],A62),0)) | M62: =IF(A62="","",IF(IFERROR(XLOOKUP(A62,tblAccounts[Account_ID],tblAccounts[Include],FALSE),FALSE),SUMIFS(tblAcctSummary[Taxes_Base],tblAcctSummary[Account_ID],A62),0)) | N62: =IF(A62="","",IF(IFERROR(XLOOKUP(A62,tblAccounts[Account_ID],tblAccounts[Include],FALSE),FALSE),IFERROR(SUMPRODUCT(tblAcctSummary[Return_Period],tblAcctSummary[Begin_Balance_Base],--(tblAcctSummary[Account_ID]=A62))/IF(SUMIFS(tblAcctSummary[Begin_Balance_Base],tblAcctSummary[Account_ID],A62)=0,NA(),SUMIFS(tblAcctSummary[Begin_Balance_Base],tblAcctSummary[Account_ID],A62)),0),0))
A63: =IFERROR(INDEX(tblAccounts[Account_ID],60),"") | B63: =IF(A63="","",IFERROR(XLOOKUP(A63,tblAccounts[Account_ID],tblAccounts[Account_Name],""),"")) | C63: =IF(A63="","",IFERROR(XLOOKUP(A63,tblAccounts[Account_ID],tblAccounts[Household_ID],""),"")) | D63: =IF(A63="","",IF(IFERROR(XLOOKUP(A63,tblAccounts[Account_ID],tblAccounts[Include],FALSE),FALSE),SUMIFS(tblAcctSummary[Begin_Balance_Base],tblAcctSummary[Account_ID],A63),0)) | E63: =IF(A63="","",IF(IFERROR(XLOOKUP(A63,tblAccounts[Account_ID],tblAccounts[Include],FALSE),FALSE),SUMIFS(tblAcctSummary[End_Balance_Base],tblAcctSummary[Account_ID],A63),0)) | F63: =IF(A63="","",IF(IFERROR(XLOOKUP(A63,tblAccounts[Account_ID],tblAccounts[Include],FALSE),FALSE),SUMIFS(tblAcctSummary[Net_Contrib_Base],tblAcctSummary[Account_ID],A63),0)) | G63: =IF(A63="","",IF(IFERROR(XLOOKUP(A63,tblAccounts[Account_ID],tblAccounts[Include],FALSE),FALSE),SUMIFS(tblAcctSummary[Income_Interest_Base],tblAcctSummary[Account_ID],A63),0)) | H63: =IF(A63="","",IF(IFERROR(XLOOKUP(A63,tblAccounts[Account_ID],tblAccounts[Include],FALSE),FALSE),SUMIFS(tblAcctSummary[Income_Dividends_Base],tblAcctSummary[Account_ID],A63),0)) | I63: =IF(A63="","",IF(IFERROR(XLOOKUP(A63,tblAccounts[Account_ID],tblAccounts[Include],FALSE),FALSE),SUMIFS(tblAcctSummary[Income_Other_Base],tblAcctSummary[Account_ID],A63),0)) | J63: =IF(A63="","",SUM(G63:I63)) | K63: =IF(A63="","",IF(IFERROR(XLOOKUP(A63,tblAccounts[Account_ID],tblAccounts[Include],FALSE),FALSE),SUMIFS(tblAcctSummary[Realized_GL_Base],tblAcctSummary[Account_ID],A63),0)) | L63: =IF(A63="","",IF(IFERROR(XLOOKUP(A63,tblAccounts[Account_ID],tblAccounts[Include],FALSE),FALSE),SUMIFS(tblAcctSummary[Fees_Base],tblAcctSummary[Account_ID],A63),0)) | M63: =IF(A63="","",IF(IFERROR(XLOOKUP(A63,tblAccounts[Account_ID],tblAccounts[Include],FALSE),FALSE),SUMIFS(tblAcctSummary[Taxes_Base],tblAcctSummary[Account_ID],A63),0)) | N63: =IF(A63="","",IF(IFERROR(XLOOKUP(A63,tblAccounts[Account_ID],tblAccounts[Include],FALSE),FALSE),IFERROR(SUMPRODUCT(tblAcctSummary[Return_Period],tblAcctSummary[Begin_Balance_Base],--(tblAcctSummary[Account_ID]=A63))/IF(SUMIFS(tblAcctSummary[Begin_Balance_Base],tblAcctSummary[Account_ID],A63)=0,NA(),SUMIFS(tblAcctSummary[Begin_Balance_Base],tblAcctSummary[Account_ID],A63)),0),0))
A64: =IFERROR(INDEX(tblAccounts[Account_ID],61),"") | B64: =IF(A64="","",IFERROR(XLOOKUP(A64,tblAccounts[Account_ID],tblAccounts[Account_Name],""),"")) | C64: =IF(A64="","",IFERROR(XLOOKUP(A64,tblAccounts[Account_ID],tblAccounts[Household_ID],""),"")) | D64: =IF(A64="","",IF(IFERROR(XLOOKUP(A64,tblAccounts[Account_ID],tblAccounts[Include],FALSE),FALSE),SUMIFS(tblAcctSummary[Begin_Balance_Base],tblAcctSummary[Account_ID],A64),0)) | E64: =IF(A64="","",IF(IFERROR(XLOOKUP(A64,tblAccounts[Account_ID],tblAccounts[Include],FALSE),FALSE),SUMIFS(tblAcctSummary[End_Balance_Base],tblAcctSummary[Account_ID],A64),0)) | F64: =IF(A64="","",IF(IFERROR(XLOOKUP(A64,tblAccounts[Account_ID],tblAccounts[Include],FALSE),FALSE),SUMIFS(tblAcctSummary[Net_Contrib_Base],tblAcctSummary[Account_ID],A64),0)) | G64: =IF(A64="","",IF(IFERROR(XLOOKUP(A64,tblAccounts[Account_ID],tblAccounts[Include],FALSE),FALSE),SUMIFS(tblAcctSummary[Income_Interest_Base],tblAcctSummary[Account_ID],A64),0)) | H64: =IF(A64="","",IF(IFERROR(XLOOKUP(A64,tblAccounts[Account_ID],tblAccounts[Include],FALSE),FALSE),SUMIFS(tblAcctSummary[Income_Dividends_Base],tblAcctSummary[Account_ID],A64),0)) | I64: =IF(A64="","",IF(IFERROR(XLOOKUP(A64,tblAccounts[Account_ID],tblAccounts[Include],FALSE),FALSE),SUMIFS(tblAcctSummary[Income_Other_Base],tblAcctSummary[Account_ID],A64),0)) | J64: =IF(A64="","",SUM(G64:I64)) | K64: =IF(A64="","",IF(IFERROR(XLOOKUP(A64,tblAccounts[Account_ID],tblAccounts[Include],FALSE),FALSE),SUMIFS(tblAcctSummary[Realized_GL_Base],tblAcctSummary[Account_ID],A64),0)) | L64: =IF(A64="","",IF(IFERROR(XLOOKUP(A64,tblAccounts[Account_ID],tblAccounts[Include],FALSE),FALSE),SUMIFS(tblAcctSummary[Fees_Base],tblAcctSummary[Account_ID],A64),0)) | M64: =IF(A64="","",IF(IFERROR(XLOOKUP(A64,tblAccounts[Account_ID],tblAccounts[Include],FALSE),FALSE),SUMIFS(tblAcctSummary[Taxes_Base],tblAcctSummary[Account_ID],A64),0)) | N64: =IF(A64="","",IF(IFERROR(XLOOKUP(A64,tblAccounts[Account_ID],tblAccounts[Include],FALSE),FALSE),IFERROR(SUMPRODUCT(tblAcctSummary[Return_Period],tblAcctSummary[Begin_Balance_Base],--(tblAcctSummary[Account_ID]=A64))/IF(SUMIFS(tblAcctSummary[Begin_Balance_Base],tblAcctSummary[Account_ID],A64)=0,NA(),SUMIFS(tblAcctSummary[Begin_Balance_Base],tblAcctSummary[Account_ID],A64)),0),0))
A65: =IFERROR(INDEX(tblAccounts[Account_ID],62),"") | B65: =IF(A65="","",IFERROR(XLOOKUP(A65,tblAccounts[Account_ID],tblAccounts[Account_Name],""),"")) | C65: =IF(A65="","",IFERROR(XLOOKUP(A65,tblAccounts[Account_ID],tblAccounts[Household_ID],""),"")) | D65: =IF(A65="","",IF(IFERROR(XLOOKUP(A65,tblAccounts[Account_ID],tblAccounts[Include],FALSE),FALSE),SUMIFS(tblAcctSummary[Begin_Balance_Base],tblAcctSummary[Account_ID],A65),0)) | E65: =IF(A65="","",IF(IFERROR(XLOOKUP(A65,tblAccounts[Account_ID],tblAccounts[Include],FALSE),FALSE),SUMIFS(tblAcctSummary[End_Balance_Base],tblAcctSummary[Account_ID],A65),0)) | F65: =IF(A65="","",IF(IFERROR(XLOOKUP(A65,tblAccounts[Account_ID],tblAccounts[Include],FALSE),FALSE),SUMIFS(tblAcctSummary[Net_Contrib_Base],tblAcctSummary[Account_ID],A65),0)) | G65: =IF(A65="","",IF(IFERROR(XLOOKUP(A65,tblAccounts[Account_ID],tblAccounts[Include],FALSE),FALSE),SUMIFS(tblAcctSummary[Income_Interest_Base],tblAcctSummary[Account_ID],A65),0)) | H65: =IF(A65="","",IF(IFERROR(XLOOKUP(A65,tblAccounts[Account_ID],tblAccounts[Include],FALSE),FALSE),SUMIFS(tblAcctSummary[Income_Dividends_Base],tblAcctSummary[Account_ID],A65),0)) | I65: =IF(A65="","",IF(IFERROR(XLOOKUP(A65,tblAccounts[Account_ID],tblAccounts[Include],FALSE),FALSE),SUMIFS(tblAcctSummary[Income_Other_Base],tblAcctSummary[Account_ID],A65),0)) | J65: =IF(A65="","",SUM(G65:I65)) | K65: =IF(A65="","",IF(IFERROR(XLOOKUP(A65,tblAccounts[Account_ID],tblAccounts[Include],FALSE),FALSE),SUMIFS(tblAcctSummary[Realized_GL_Base],tblAcctSummary[Account_ID],A65),0)) | L65: =IF(A65="","",IF(IFERROR(XLOOKUP(A65,tblAccounts[Account_ID],tblAccounts[Include],FALSE),FALSE),SUMIFS(tblAcctSummary[Fees_Base],tblAcctSummary[Account_ID],A65),0)) | M65: =IF(A65="","",IF(IFERROR(XLOOKUP(A65,tblAccounts[Account_ID],tblAccounts[Include],FALSE),FALSE),SUMIFS(tblAcctSummary[Taxes_Base],tblAcctSummary[Account_ID],A65),0)) | N65: =IF(A65="","",IF(IFERROR(XLOOKUP(A65,tblAccounts[Account_ID],tblAccounts[Include],FALSE),FALSE),IFERROR(SUMPRODUCT(tblAcctSummary[Return_Period],tblAcctSummary[Begin_Balance_Base],--(tblAcctSummary[Account_ID]=A65))/IF(SUMIFS(tblAcctSummary[Begin_Balance_Base],tblAcctSummary[Account_ID],A65)=0,NA(),SUMIFS(tblAcctSummary[Begin_Balance_Base],tblAcctSummary[Account_ID],A65)),0),0))
A66: =IFERROR(INDEX(tblAccounts[Account_ID],63),"") | B66: =IF(A66="","",IFERROR(XLOOKUP(A66,tblAccounts[Account_ID],tblAccounts[Account_Name],""),"")) | C66: =IF(A66="","",IFERROR(XLOOKUP(A66,tblAccounts[Account_ID],tblAccounts[Household_ID],""),"")) | D66: =IF(A66="","",IF(IFERROR(XLOOKUP(A66,tblAccounts[Account_ID],tblAccounts[Include],FALSE),FALSE),SUMIFS(tblAcctSummary[Begin_Balance_Base],tblAcctSummary[Account_ID],A66),0)) | E66: =IF(A66="","",IF(IFERROR(XLOOKUP(A66,tblAccounts[Account_ID],tblAccounts[Include],FALSE),FALSE),SUMIFS(tblAcctSummary[End_Balance_Base],tblAcctSummary[Account_ID],A66),0)) | F66: =IF(A66="","",IF(IFERROR(XLOOKUP(A66,tblAccounts[Account_ID],tblAccounts[Include],FALSE),FALSE),SUMIFS(tblAcctSummary[Net_Contrib_Base],tblAcctSummary[Account_ID],A66),0)) | G66: =IF(A66="","",IF(IFERROR(XLOOKUP(A66,tblAccounts[Account_ID],tblAccounts[Include],FALSE),FALSE),SUMIFS(tblAcctSummary[Income_Interest_Base],tblAcctSummary[Account_ID],A66),0)) | H66: =IF(A66="","",IF(IFERROR(XLOOKUP(A66,tblAccounts[Account_ID],tblAccounts[Include],FALSE),FALSE),SUMIFS(tblAcctSummary[Income_Dividends_Base],tblAcctSummary[Account_ID],A66),0)) | I66: =IF(A66="","",IF(IFERROR(XLOOKUP(A66,tblAccounts[Account_ID],tblAccounts[Include],FALSE),FALSE),SUMIFS(tblAcctSummary[Income_Other_Base],tblAcctSummary[Account_ID],A66),0)) | J66: =IF(A66="","",SUM(G66:I66)) | K66: =IF(A66="","",IF(IFERROR(XLOOKUP(A66,tblAccounts[Account_ID],tblAccounts[Include],FALSE),FALSE),SUMIFS(tblAcctSummary[Realized_GL_Base],tblAcctSummary[Account_ID],A66),0)) | L66: =IF(A66="","",IF(IFERROR(XLOOKUP(A66,tblAccounts[Account_ID],tblAccounts[Include],FALSE),FALSE),SUMIFS(tblAcctSummary[Fees_Base],tblAcctSummary[Account_ID],A66),0)) | M66: =IF(A66="","",IF(IFERROR(XLOOKUP(A66,tblAccounts[Account_ID],tblAccounts[Include],FALSE),FALSE),SUMIFS(tblAcctSummary[Taxes_Base],tblAcctSummary[Account_ID],A66),0)) | N66: =IF(A66="","",IF(IFERROR(XLOOKUP(A66,tblAccounts[Account_ID],tblAccounts[Include],FALSE),FALSE),IFERROR(SUMPRODUCT(tblAcctSummary[Return_Period],tblAcctSummary[Begin_Balance_Base],--(tblAcctSummary[Account_ID]=A66))/IF(SUMIFS(tblAcctSummary[Begin_Balance_Base],tblAcctSummary[Account_ID],A66)=0,NA(),SUMIFS(tblAcctSummary[Begin_Balance_Base],tblAcctSummary[Account_ID],A66)),0),0))
A67: =IFERROR(INDEX(tblAccounts[Account_ID],64),"") | B67: =IF(A67="","",IFERROR(XLOOKUP(A67,tblAccounts[Account_ID],tblAccounts[Account_Name],""),"")) | C67: =IF(A67="","",IFERROR(XLOOKUP(A67,tblAccounts[Account_ID],tblAccounts[Household_ID],""),"")) | D67: =IF(A67="","",IF(IFERROR(XLOOKUP(A67,tblAccounts[Account_ID],tblAccounts[Include],FALSE),FALSE),SUMIFS(tblAcctSummary[Begin_Balance_Base],tblAcctSummary[Account_ID],A67),0)) | E67: =IF(A67="","",IF(IFERROR(XLOOKUP(A67,tblAccounts[Account_ID],tblAccounts[Include],FALSE),FALSE),SUMIFS(tblAcctSummary[End_Balance_Base],tblAcctSummary[Account_ID],A67),0)) | F67: =IF(A67="","",IF(IFERROR(XLOOKUP(A67,tblAccounts[Account_ID],tblAccounts[Include],FALSE),FALSE),SUMIFS(tblAcctSummary[Net_Contrib_Base],tblAcctSummary[Account_ID],A67),0)) | G67: =IF(A67="","",IF(IFERROR(XLOOKUP(A67,tblAccounts[Account_ID],tblAccounts[Include],FALSE),FALSE),SUMIFS(tblAcctSummary[Income_Interest_Base],tblAcctSummary[Account_ID],A67),0)) | H67: =IF(A67="","",IF(IFERROR(XLOOKUP(A67,tblAccounts[Account_ID],tblAccounts[Include],FALSE),FALSE),SUMIFS(tblAcctSummary[Income_Dividends_Base],tblAcctSummary[Account_ID],A67),0)) | I67: =IF(A67="","",IF(IFERROR(XLOOKUP(A67,tblAccounts[Account_ID],tblAccounts[Include],FALSE),FALSE),SUMIFS(tblAcctSummary[Income_Other_Base],tblAcctSummary[Account_ID],A67),0)) | J67: =IF(A67="","",SUM(G67:I67)) | K67: =IF(A67="","",IF(IFERROR(XLOOKUP(A67,tblAccounts[Account_ID],tblAccounts[Include],FALSE),FALSE),SUMIFS(tblAcctSummary[Realized_GL_Base],tblAcctSummary[Account_ID],A67),0)) | L67: =IF(A67="","",IF(IFERROR(XLOOKUP(A67,tblAccounts[Account_ID],tblAccounts[Include],FALSE),FALSE),SUMIFS(tblAcctSummary[Fees_Base],tblAcctSummary[Account_ID],A67),0)) | M67: =IF(A67="","",IF(IFERROR(XLOOKUP(A67,tblAccounts[Account_ID],tblAccounts[Include],FALSE),FALSE),SUMIFS(tblAcctSummary[Taxes_Base],tblAcctSummary[Account_ID],A67),0)) | N67: =IF(A67="","",IF(IFERROR(XLOOKUP(A67,tblAccounts[Account_ID],tblAccounts[Include],FALSE),FALSE),IFERROR(SUMPRODUCT(tblAcctSummary[Return_Period],tblAcctSummary[Begin_Balance_Base],--(tblAcctSummary[Account_ID]=A67))/IF(SUMIFS(tblAcctSummary[Begin_Balance_Base],tblAcctSummary[Account_ID],A67)=0,NA(),SUMIFS(tblAcctSummary[Begin_Balance_Base],tblAcctSummary[Account_ID],A67)),0),0))
A68: =IFERROR(INDEX(tblAccounts[Account_ID],65),"") | B68: =IF(A68="","",IFERROR(XLOOKUP(A68,tblAccounts[Account_ID],tblAccounts[Account_Name],""),"")) | C68: =IF(A68="","",IFERROR(XLOOKUP(A68,tblAccounts[Account_ID],tblAccounts[Household_ID],""),"")) | D68: =IF(A68="","",IF(IFERROR(XLOOKUP(A68,tblAccounts[Account_ID],tblAccounts[Include],FALSE),FALSE),SUMIFS(tblAcctSummary[Begin_Balance_Base],tblAcctSummary[Account_ID],A68),0)) | E68: =IF(A68="","",IF(IFERROR(XLOOKUP(A68,tblAccounts[Account_ID],tblAccounts[Include],FALSE),FALSE),SUMIFS(tblAcctSummary[End_Balance_Base],tblAcctSummary[Account_ID],A68),0)) | F68: =IF(A68="","",IF(IFERROR(XLOOKUP(A68,tblAccounts[Account_ID],tblAccounts[Include],FALSE),FALSE),SUMIFS(tblAcctSummary[Net_Contrib_Base],tblAcctSummary[Account_ID],A68),0)) | G68: =IF(A68="","",IF(IFERROR(XLOOKUP(A68,tblAccounts[Account_ID],tblAccounts[Include],FALSE),FALSE),SUMIFS(tblAcctSummary[Income_Interest_Base],tblAcctSummary[Account_ID],A68),0)) | H68: =IF(A68="","",IF(IFERROR(XLOOKUP(A68,tblAccounts[Account_ID],tblAccounts[Include],FALSE),FALSE),SUMIFS(tblAcctSummary[Income_Dividends_Base],tblAcctSummary[Account_ID],A68),0)) | I68: =IF(A68="","",IF(IFERROR(XLOOKUP(A68,tblAccounts[Account_ID],tblAccounts[Include],FALSE),FALSE),SUMIFS(tblAcctSummary[Income_Other_Base],tblAcctSummary[Account_ID],A68),0)) | J68: =IF(A68="","",SUM(G68:I68)) | K68: =IF(A68="","",IF(IFERROR(XLOOKUP(A68,tblAccounts[Account_ID],tblAccounts[Include],FALSE),FALSE),SUMIFS(tblAcctSummary[Realized_GL_Base],tblAcctSummary[Account_ID],A68),0)) | L68: =IF(A68="","",IF(IFERROR(XLOOKUP(A68,tblAccounts[Account_ID],tblAccounts[Include],FALSE),FALSE),SUMIFS(tblAcctSummary[Fees_Base],tblAcctSummary[Account_ID],A68),0)) | M68: =IF(A68="","",IF(IFERROR(XLOOKUP(A68,tblAccounts[Account_ID],tblAccounts[Include],FALSE),FALSE),SUMIFS(tblAcctSummary[Taxes_Base],tblAcctSummary[Account_ID],A68),0)) | N68: =IF(A68="","",IF(IFERROR(XLOOKUP(A68,tblAccounts[Account_ID],tblAccounts[Include],FALSE),FALSE),IFERROR(SUMPRODUCT(tblAcctSummary[Return_Period],tblAcctSummary[Begin_Balance_Base],--(tblAcctSummary[Account_ID]=A68))/IF(SUMIFS(tblAcctSummary[Begin_Balance_Base],tblAcctSummary[Account_ID],A68)=0,NA(),SUMIFS(tblAcctSummary[Begin_Balance_Base],tblAcctSummary[Account_ID],A68)),0),0))
A69: =IFERROR(INDEX(tblAccounts[Account_ID],66),"") | B69: =IF(A69="","",IFERROR(XLOOKUP(A69,tblAccounts[Account_ID],tblAccounts[Account_Name],""),"")) | C69: =IF(A69="","",IFERROR(XLOOKUP(A69,tblAccounts[Account_ID],tblAccounts[Household_ID],""),"")) | D69: =IF(A69="","",IF(IFERROR(XLOOKUP(A69,tblAccounts[Account_ID],tblAccounts[Include],FALSE),FALSE),SUMIFS(tblAcctSummary[Begin_Balance_Base],tblAcctSummary[Account_ID],A69),0)) | E69: =IF(A69="","",IF(IFERROR(XLOOKUP(A69,tblAccounts[Account_ID],tblAccounts[Include],FALSE),FALSE),SUMIFS(tblAcctSummary[End_Balance_Base],tblAcctSummary[Account_ID],A69),0)) | F69: =IF(A69="","",IF(IFERROR(XLOOKUP(A69,tblAccounts[Account_ID],tblAccounts[Include],FALSE),FALSE),SUMIFS(tblAcctSummary[Net_Contrib_Base],tblAcctSummary[Account_ID],A69),0)) | G69: =IF(A69="","",IF(IFERROR(XLOOKUP(A69,tblAccounts[Account_ID],tblAccounts[Include],FALSE),FALSE),SUMIFS(tblAcctSummary[Income_Interest_Base],tblAcctSummary[Account_ID],A69),0)) | H69: =IF(A69="","",IF(IFERROR(XLOOKUP(A69,tblAccounts[Account_ID],tblAccounts[Include],FALSE),FALSE),SUMIFS(tblAcctSummary[Income_Dividends_Base],tblAcctSummary[Account_ID],A69),0)) | I69: =IF(A69="","",IF(IFERROR(XLOOKUP(A69,tblAccounts[Account_ID],tblAccounts[Include],FALSE),FALSE),SUMIFS(tblAcctSummary[Income_Other_Base],tblAcctSummary[Account_ID],A69),0)) | J69: =IF(A69="","",SUM(G69:I69)) | K69: =IF(A69="","",IF(IFERROR(XLOOKUP(A69,tblAccounts[Account_ID],tblAccounts[Include],FALSE),FALSE),SUMIFS(tblAcctSummary[Realized_GL_Base],tblAcctSummary[Account_ID],A69),0)) | L69: =IF(A69="","",IF(IFERROR(XLOOKUP(A69,tblAccounts[Account_ID],tblAccounts[Include],FALSE),FALSE),SUMIFS(tblAcctSummary[Fees_Base],tblAcctSummary[Account_ID],A69),0)) | M69: =IF(A69="","",IF(IFERROR(XLOOKUP(A69,tblAccounts[Account_ID],tblAccounts[Include],FALSE),FALSE),SUMIFS(tblAcctSummary[Taxes_Base],tblAcctSummary[Account_ID],A69),0)) | N69: =IF(A69="","",IF(IFERROR(XLOOKUP(A69,tblAccounts[Account_ID],tblAccounts[Include],FALSE),FALSE),IFERROR(SUMPRODUCT(tblAcctSummary[Return_Period],tblAcctSummary[Begin_Balance_Base],--(tblAcctSummary[Account_ID]=A69))/IF(SUMIFS(tblAcctSummary[Begin_Balance_Base],tblAcctSummary[Account_ID],A69)=0,NA(),SUMIFS(tblAcctSummary[Begin_Balance_Base],tblAcctSummary[Account_ID],A69)),0),0))
A70: =IFERROR(INDEX(tblAccounts[Account_ID],67),"") | B70: =IF(A70="","",IFERROR(XLOOKUP(A70,tblAccounts[Account_ID],tblAccounts[Account_Name],""),"")) | C70: =IF(A70="","",IFERROR(XLOOKUP(A70,tblAccounts[Account_ID],tblAccounts[Household_ID],""),"")) | D70: =IF(A70="","",IF(IFERROR(XLOOKUP(A70,tblAccounts[Account_ID],tblAccounts[Include],FALSE),FALSE),SUMIFS(tblAcctSummary[Begin_Balance_Base],tblAcctSummary[Account_ID],A70),0)) | E70: =IF(A70="","",IF(IFERROR(XLOOKUP(A70,tblAccounts[Account_ID],tblAccounts[Include],FALSE),FALSE),SUMIFS(tblAcctSummary[End_Balance_Base],tblAcctSummary[Account_ID],A70),0)) | F70: =IF(A70="","",IF(IFERROR(XLOOKUP(A70,tblAccounts[Account_ID],tblAccounts[Include],FALSE),FALSE),SUMIFS(tblAcctSummary[Net_Contrib_Base],tblAcctSummary[Account_ID],A70),0)) | G70: =IF(A70="","",IF(IFERROR(XLOOKUP(A70,tblAccounts[Account_ID],tblAccounts[Include],FALSE),FALSE),SUMIFS(tblAcctSummary[Income_Interest_Base],tblAcctSummary[Account_ID],A70),0)) | H70: =IF(A70="","",IF(IFERROR(XLOOKUP(A70,tblAccounts[Account_ID],tblAccounts[Include],FALSE),FALSE),SUMIFS(tblAcctSummary[Income_Dividends_Base],tblAcctSummary[Account_ID],A70),0)) | I70: =IF(A70="","",IF(IFERROR(XLOOKUP(A70,tblAccounts[Account_ID],tblAccounts[Include],FALSE),FALSE),SUMIFS(tblAcctSummary[Income_Other_Base],tblAcctSummary[Account_ID],A70),0)) | J70: =IF(A70="","",SUM(G70:I70)) | K70: =IF(A70="","",IF(IFERROR(XLOOKUP(A70,tblAccounts[Account_ID],tblAccounts[Include],FALSE),FALSE),SUMIFS(tblAcctSummary[Realized_GL_Base],tblAcctSummary[Account_ID],A70),0)) | L70: =IF(A70="","",IF(IFERROR(XLOOKUP(A70,tblAccounts[Account_ID],tblAccounts[Include],FALSE),FALSE),SUMIFS(tblAcctSummary[Fees_Base],tblAcctSummary[Account_ID],A70),0)) | M70: =IF(A70="","",IF(IFERROR(XLOOKUP(A70,tblAccounts[Account_ID],tblAccounts[Include],FALSE),FALSE),SUMIFS(tblAcctSummary[Taxes_Base],tblAcctSummary[Account_ID],A70),0)) | N70: =IF(A70="","",IF(IFERROR(XLOOKUP(A70,tblAccounts[Account_ID],tblAccounts[Include],FALSE),FALSE),IFERROR(SUMPRODUCT(tblAcctSummary[Return_Period],tblAcctSummary[Begin_Balance_Base],--(tblAcctSummary[Account_ID]=A70))/IF(SUMIFS(tblAcctSummary[Begin_Balance_Base],tblAcctSummary[Account_ID],A70)=0,NA(),SUMIFS(tblAcctSummary[Begin_Balance_Base],tblAcctSummary[Account_ID],A70)),0),0))
A71: =IFERROR(INDEX(tblAccounts[Account_ID],68),"") | B71: =IF(A71="","",IFERROR(XLOOKUP(A71,tblAccounts[Account_ID],tblAccounts[Account_Name],""),"")) | C71: =IF(A71="","",IFERROR(XLOOKUP(A71,tblAccounts[Account_ID],tblAccounts[Household_ID],""),"")) | D71: =IF(A71="","",IF(IFERROR(XLOOKUP(A71,tblAccounts[Account_ID],tblAccounts[Include],FALSE),FALSE),SUMIFS(tblAcctSummary[Begin_Balance_Base],tblAcctSummary[Account_ID],A71),0)) | E71: =IF(A71="","",IF(IFERROR(XLOOKUP(A71,tblAccounts[Account_ID],tblAccounts[Include],FALSE),FALSE),SUMIFS(tblAcctSummary[End_Balance_Base],tblAcctSummary[Account_ID],A71),0)) | F71: =IF(A71="","",IF(IFERROR(XLOOKUP(A71,tblAccounts[Account_ID],tblAccounts[Include],FALSE),FALSE),SUMIFS(tblAcctSummary[Net_Contrib_Base],tblAcctSummary[Account_ID],A71),0)) | G71: =IF(A71="","",IF(IFERROR(XLOOKUP(A71,tblAccounts[Account_ID],tblAccounts[Include],FALSE),FALSE),SUMIFS(tblAcctSummary[Income_Interest_Base],tblAcctSummary[Account_ID],A71),0)) | H71: =IF(A71="","",IF(IFERROR(XLOOKUP(A71,tblAccounts[Account_ID],tblAccounts[Include],FALSE),FALSE),SUMIFS(tblAcctSummary[Income_Dividends_Base],tblAcctSummary[Account_ID],A71),0)) | I71: =IF(A71="","",IF(IFERROR(XLOOKUP(A71,tblAccounts[Account_ID],tblAccounts[Include],FALSE),FALSE),SUMIFS(tblAcctSummary[Income_Other_Base],tblAcctSummary[Account_ID],A71),0)) | J71: =IF(A71="","",SUM(G71:I71)) | K71: =IF(A71="","",IF(IFERROR(XLOOKUP(A71,tblAccounts[Account_ID],tblAccounts[Include],FALSE),FALSE),SUMIFS(tblAcctSummary[Realized_GL_Base],tblAcctSummary[Account_ID],A71),0)) | L71: =IF(A71="","",IF(IFERROR(XLOOKUP(A71,tblAccounts[Account_ID],tblAccounts[Include],FALSE),FALSE),SUMIFS(tblAcctSummary[Fees_Base],tblAcctSummary[Account_ID],A71),0)) | M71: =IF(A71="","",IF(IFERROR(XLOOKUP(A71,tblAccounts[Account_ID],tblAccounts[Include],FALSE),FALSE),SUMIFS(tblAcctSummary[Taxes_Base],tblAcctSummary[Account_ID],A71),0)) | N71: =IF(A71="","",IF(IFERROR(XLOOKUP(A71,tblAccounts[Account_ID],tblAccounts[Include],FALSE),FALSE),IFERROR(SUMPRODUCT(tblAcctSummary[Return_Period],tblAcctSummary[Begin_Balance_Base],--(tblAcctSummary[Account_ID]=A71))/IF(SUMIFS(tblAcctSummary[Begin_Balance_Base],tblAcctSummary[Account_ID],A71)=0,NA(),SUMIFS(tblAcctSummary[Begin_Balance_Base],tblAcctSummary[Account_ID],A71)),0),0))
A72: =IFERROR(INDEX(tblAccounts[Account_ID],69),"") | B72: =IF(A72="","",IFERROR(XLOOKUP(A72,tblAccounts[Account_ID],tblAccounts[Account_Name],""),"")) | C72: =IF(A72="","",IFERROR(XLOOKUP(A72,tblAccounts[Account_ID],tblAccounts[Household_ID],""),"")) | D72: =IF(A72="","",IF(IFERROR(XLOOKUP(A72,tblAccounts[Account_ID],tblAccounts[Include],FALSE),FALSE),SUMIFS(tblAcctSummary[Begin_Balance_Base],tblAcctSummary[Account_ID],A72),0)) | E72: =IF(A72="","",IF(IFERROR(XLOOKUP(A72,tblAccounts[Account_ID],tblAccounts[Include],FALSE),FALSE),SUMIFS(tblAcctSummary[End_Balance_Base],tblAcctSummary[Account_ID],A72),0)) | F72: =IF(A72="","",IF(IFERROR(XLOOKUP(A72,tblAccounts[Account_ID],tblAccounts[Include],FALSE),FALSE),SUMIFS(tblAcctSummary[Net_Contrib_Base],tblAcctSummary[Account_ID],A72),0)) | G72: =IF(A72="","",IF(IFERROR(XLOOKUP(A72,tblAccounts[Account_ID],tblAccounts[Include],FALSE),FALSE),SUMIFS(tblAcctSummary[Income_Interest_Base],tblAcctSummary[Account_ID],A72),0)) | H72: =IF(A72="","",IF(IFERROR(XLOOKUP(A72,tblAccounts[Account_ID],tblAccounts[Include],FALSE),FALSE),SUMIFS(tblAcctSummary[Income_Dividends_Base],tblAcctSummary[Account_ID],A72),0)) | I72: =IF(A72="","",IF(IFERROR(XLOOKUP(A72,tblAccounts[Account_ID],tblAccounts[Include],FALSE),FALSE),SUMIFS(tblAcctSummary[Income_Other_Base],tblAcctSummary[Account_ID],A72),0)) | J72: =IF(A72="","",SUM(G72:I72)) | K72: =IF(A72="","",IF(IFERROR(XLOOKUP(A72,tblAccounts[Account_ID],tblAccounts[Include],FALSE),FALSE),SUMIFS(tblAcctSummary[Realized_GL_Base],tblAcctSummary[Account_ID],A72),0)) | L72: =IF(A72="","",IF(IFERROR(XLOOKUP(A72,tblAccounts[Account_ID],tblAccounts[Include],FALSE),FALSE),SUMIFS(tblAcctSummary[Fees_Base],tblAcctSummary[Account_ID],A72),0)) | M72: =IF(A72="","",IF(IFERROR(XLOOKUP(A72,tblAccounts[Account_ID],tblAccounts[Include],FALSE),FALSE),SUMIFS(tblAcctSummary[Taxes_Base],tblAcctSummary[Account_ID],A72),0)) | N72: =IF(A72="","",IF(IFERROR(XLOOKUP(A72,tblAccounts[Account_ID],tblAccounts[Include],FALSE),FALSE),IFERROR(SUMPRODUCT(tblAcctSummary[Return_Period],tblAcctSummary[Begin_Balance_Base],--(tblAcctSummary[Account_ID]=A72))/IF(SUMIFS(tblAcctSummary[Begin_Balance_Base],tblAcctSummary[Account_ID],A72)=0,NA(),SUMIFS(tblAcctSummary[Begin_Balance_Base],tblAcctSummary[Account_ID],A72)),0),0))
A73: =IFERROR(INDEX(tblAccounts[Account_ID],70),"") | B73: =IF(A73="","",IFERROR(XLOOKUP(A73,tblAccounts[Account_ID],tblAccounts[Account_Name],""),"")) | C73: =IF(A73="","",IFERROR(XLOOKUP(A73,tblAccounts[Account_ID],tblAccounts[Household_ID],""),"")) | D73: =IF(A73="","",IF(IFERROR(XLOOKUP(A73,tblAccounts[Account_ID],tblAccounts[Include],FALSE),FALSE),SUMIFS(tblAcctSummary[Begin_Balance_Base],tblAcctSummary[Account_ID],A73),0)) | E73: =IF(A73="","",IF(IFERROR(XLOOKUP(A73,tblAccounts[Account_ID],tblAccounts[Include],FALSE),FALSE),SUMIFS(tblAcctSummary[End_Balance_Base],tblAcctSummary[Account_ID],A73),0)) | F73: =IF(A73="","",IF(IFERROR(XLOOKUP(A73,tblAccounts[Account_ID],tblAccounts[Include],FALSE),FALSE),SUMIFS(tblAcctSummary[Net_Contrib_Base],tblAcctSummary[Account_ID],A73),0)) | G73: =IF(A73="","",IF(IFERROR(XLOOKUP(A73,tblAccounts[Account_ID],tblAccounts[Include],FALSE),FALSE),SUMIFS(tblAcctSummary[Income_Interest_Base],tblAcctSummary[Account_ID],A73),0)) | H73: =IF(A73="","",IF(IFERROR(XLOOKUP(A73,tblAccounts[Account_ID],tblAccounts[Include],FALSE),FALSE),SUMIFS(tblAcctSummary[Income_Dividends_Base],tblAcctSummary[Account_ID],A73),0)) | I73: =IF(A73="","",IF(IFERROR(XLOOKUP(A73,tblAccounts[Account_ID],tblAccounts[Include],FALSE),FALSE),SUMIFS(tblAcctSummary[Income_Other_Base],tblAcctSummary[Account_ID],A73),0)) | J73: =IF(A73="","",SUM(G73:I73)) | K73: =IF(A73="","",IF(IFERROR(XLOOKUP(A73,tblAccounts[Account_ID],tblAccounts[Include],FALSE),FALSE),SUMIFS(tblAcctSummary[Realized_GL_Base],tblAcctSummary[Account_ID],A73),0)) | L73: =IF(A73="","",IF(IFERROR(XLOOKUP(A73,tblAccounts[Account_ID],tblAccounts[Include],FALSE),FALSE),SUMIFS(tblAcctSummary[Fees_Base],tblAcctSummary[Account_ID],A73),0)) | M73: =IF(A73="","",IF(IFERROR(XLOOKUP(A73,tblAccounts[Account_ID],tblAccounts[Include],FALSE),FALSE),SUMIFS(tblAcctSummary[Taxes_Base],tblAcctSummary[Account_ID],A73),0)) | N73: =IF(A73="","",IF(IFERROR(XLOOKUP(A73,tblAccounts[Account_ID],tblAccounts[Include],FALSE),FALSE),IFERROR(SUMPRODUCT(tblAcctSummary[Return_Period],tblAcctSummary[Begin_Balance_Base],--(tblAcctSummary[Account_ID]=A73))/IF(SUMIFS(tblAcctSummary[Begin_Balance_Base],tblAcctSummary[Account_ID],A73)=0,NA(),SUMIFS(tblAcctSummary[Begin_Balance_Base],tblAcctSummary[Account_ID],A73)),0),0))
A74: =IFERROR(INDEX(tblAccounts[Account_ID],71),"") | B74: =IF(A74="","",IFERROR(XLOOKUP(A74,tblAccounts[Account_ID],tblAccounts[Account_Name],""),"")) | C74: =IF(A74="","",IFERROR(XLOOKUP(A74,tblAccounts[Account_ID],tblAccounts[Household_ID],""),"")) | D74: =IF(A74="","",IF(IFERROR(XLOOKUP(A74,tblAccounts[Account_ID],tblAccounts[Include],FALSE),FALSE),SUMIFS(tblAcctSummary[Begin_Balance_Base],tblAcctSummary[Account_ID],A74),0)) | E74: =IF(A74="","",IF(IFERROR(XLOOKUP(A74,tblAccounts[Account_ID],tblAccounts[Include],FALSE),FALSE),SUMIFS(tblAcctSummary[End_Balance_Base],tblAcctSummary[Account_ID],A74),0)) | F74: =IF(A74="","",IF(IFERROR(XLOOKUP(A74,tblAccounts[Account_ID],tblAccounts[Include],FALSE),FALSE),SUMIFS(tblAcctSummary[Net_Contrib_Base],tblAcctSummary[Account_ID],A74),0)) | G74: =IF(A74="","",IF(IFERROR(XLOOKUP(A74,tblAccounts[Account_ID],tblAccounts[Include],FALSE),FALSE),SUMIFS(tblAcctSummary[Income_Interest_Base],tblAcctSummary[Account_ID],A74),0)) | H74: =IF(A74="","",IF(IFERROR(XLOOKUP(A74,tblAccounts[Account_ID],tblAccounts[Include],FALSE),FALSE),SUMIFS(tblAcctSummary[Income_Dividends_Base],tblAcctSummary[Account_ID],A74),0)) | I74: =IF(A74="","",IF(IFERROR(XLOOKUP(A74,tblAccounts[Account_ID],tblAccounts[Include],FALSE),FALSE),SUMIFS(tblAcctSummary[Income_Other_Base],tblAcctSummary[Account_ID],A74),0)) | J74: =IF(A74="","",SUM(G74:I74)) | K74: =IF(A74="","",IF(IFERROR(XLOOKUP(A74,tblAccounts[Account_ID],tblAccounts[Include],FALSE),FALSE),SUMIFS(tblAcctSummary[Realized_GL_Base],tblAcctSummary[Account_ID],A74),0)) | L74: =IF(A74="","",IF(IFERROR(XLOOKUP(A74,tblAccounts[Account_ID],tblAccounts[Include],FALSE),FALSE),SUMIFS(tblAcctSummary[Fees_Base],tblAcctSummary[Account_ID],A74),0)) | M74: =IF(A74="","",IF(IFERROR(XLOOKUP(A74,tblAccounts[Account_ID],tblAccounts[Include],FALSE),FALSE),SUMIFS(tblAcctSummary[Taxes_Base],tblAcctSummary[Account_ID],A74),0)) | N74: =IF(A74="","",IF(IFERROR(XLOOKUP(A74,tblAccounts[Account_ID],tblAccounts[Include],FALSE),FALSE),IFERROR(SUMPRODUCT(tblAcctSummary[Return_Period],tblAcctSummary[Begin_Balance_Base],--(tblAcctSummary[Account_ID]=A74))/IF(SUMIFS(tblAcctSummary[Begin_Balance_Base],tblAcctSummary[Account_ID],A74)=0,NA(),SUMIFS(tblAcctSummary[Begin_Balance_Base],tblAcctSummary[Account_ID],A74)),0),0))
A75: =IFERROR(INDEX(tblAccounts[Account_ID],72),"") | B75: =IF(A75="","",IFERROR(XLOOKUP(A75,tblAccounts[Account_ID],tblAccounts[Account_Name],""),"")) | C75: =IF(A75="","",IFERROR(XLOOKUP(A75,tblAccounts[Account_ID],tblAccounts[Household_ID],""),"")) | D75: =IF(A75="","",IF(IFERROR(XLOOKUP(A75,tblAccounts[Account_ID],tblAccounts[Include],FALSE),FALSE),SUMIFS(tblAcctSummary[Begin_Balance_Base],tblAcctSummary[Account_ID],A75),0)) | E75: =IF(A75="","",IF(IFERROR(XLOOKUP(A75,tblAccounts[Account_ID],tblAccounts[Include],FALSE),FALSE),SUMIFS(tblAcctSummary[End_Balance_Base],tblAcctSummary[Account_ID],A75),0)) | F75: =IF(A75="","",IF(IFERROR(XLOOKUP(A75,tblAccounts[Account_ID],tblAccounts[Include],FALSE),FALSE),SUMIFS(tblAcctSummary[Net_Contrib_Base],tblAcctSummary[Account_ID],A75),0)) | G75: =IF(A75="","",IF(IFERROR(XLOOKUP(A75,tblAccounts[Account_ID],tblAccounts[Include],FALSE),FALSE),SUMIFS(tblAcctSummary[Income_Interest_Base],tblAcctSummary[Account_ID],A75),0)) | H75: =IF(A75="","",IF(IFERROR(XLOOKUP(A75,tblAccounts[Account_ID],tblAccounts[Include],FALSE),FALSE),SUMIFS(tblAcctSummary[Income_Dividends_Base],tblAcctSummary[Account_ID],A75),0)) | I75: =IF(A75="","",IF(IFERROR(XLOOKUP(A75,tblAccounts[Account_ID],tblAccounts[Include],FALSE),FALSE),SUMIFS(tblAcctSummary[Income_Other_Base],tblAcctSummary[Account_ID],A75),0)) | J75: =IF(A75="","",SUM(G75:I75)) | K75: =IF(A75="","",IF(IFERROR(XLOOKUP(A75,tblAccounts[Account_ID],tblAccounts[Include],FALSE),FALSE),SUMIFS(tblAcctSummary[Realized_GL_Base],tblAcctSummary[Account_ID],A75),0)) | L75: =IF(A75="","",IF(IFERROR(XLOOKUP(A75,tblAccounts[Account_ID],tblAccounts[Include],FALSE),FALSE),SUMIFS(tblAcctSummary[Fees_Base],tblAcctSummary[Account_ID],A75),0)) | M75: =IF(A75="","",IF(IFERROR(XLOOKUP(A75,tblAccounts[Account_ID],tblAccounts[Include],FALSE),FALSE),SUMIFS(tblAcctSummary[Taxes_Base],tblAcctSummary[Account_ID],A75),0)) | N75: =IF(A75="","",IF(IFERROR(XLOOKUP(A75,tblAccounts[Account_ID],tblAccounts[Include],FALSE),FALSE),IFERROR(SUMPRODUCT(tblAcctSummary[Return_Period],tblAcctSummary[Begin_Balance_Base],--(tblAcctSummary[Account_ID]=A75))/IF(SUMIFS(tblAcctSummary[Begin_Balance_Base],tblAcctSummary[Account_ID],A75)=0,NA(),SUMIFS(tblAcctSummary[Begin_Balance_Base],tblAcctSummary[Account_ID],A75)),0),0))
A76: =IFERROR(INDEX(tblAccounts[Account_ID],73),"") | B76: =IF(A76="","",IFERROR(XLOOKUP(A76,tblAccounts[Account_ID],tblAccounts[Account_Name],""),"")) | C76: =IF(A76="","",IFERROR(XLOOKUP(A76,tblAccounts[Account_ID],tblAccounts[Household_ID],""),"")) | D76: =IF(A76="","",IF(IFERROR(XLOOKUP(A76,tblAccounts[Account_ID],tblAccounts[Include],FALSE),FALSE),SUMIFS(tblAcctSummary[Begin_Balance_Base],tblAcctSummary[Account_ID],A76),0)) | E76: =IF(A76="","",IF(IFERROR(XLOOKUP(A76,tblAccounts[Account_ID],tblAccounts[Include],FALSE),FALSE),SUMIFS(tblAcctSummary[End_Balance_Base],tblAcctSummary[Account_ID],A76),0)) | F76: =IF(A76="","",IF(IFERROR(XLOOKUP(A76,tblAccounts[Account_ID],tblAccounts[Include],FALSE),FALSE),SUMIFS(tblAcctSummary[Net_Contrib_Base],tblAcctSummary[Account_ID],A76),0)) | G76: =IF(A76="","",IF(IFERROR(XLOOKUP(A76,tblAccounts[Account_ID],tblAccounts[Include],FALSE),FALSE),SUMIFS(tblAcctSummary[Income_Interest_Base],tblAcctSummary[Account_ID],A76),0)) | H76: =IF(A76="","",IF(IFERROR(XLOOKUP(A76,tblAccounts[Account_ID],tblAccounts[Include],FALSE),FALSE),SUMIFS(tblAcctSummary[Income_Dividends_Base],tblAcctSummary[Account_ID],A76),0)) | I76: =IF(A76="","",IF(IFERROR(XLOOKUP(A76,tblAccounts[Account_ID],tblAccounts[Include],FALSE),FALSE),SUMIFS(tblAcctSummary[Income_Other_Base],tblAcctSummary[Account_ID],A76),0)) | J76: =IF(A76="","",SUM(G76:I76)) | K76: =IF(A76="","",IF(IFERROR(XLOOKUP(A76,tblAccounts[Account_ID],tblAccounts[Include],FALSE),FALSE),SUMIFS(tblAcctSummary[Realized_GL_Base],tblAcctSummary[Account_ID],A76),0)) | L76: =IF(A76="","",IF(IFERROR(XLOOKUP(A76,tblAccounts[Account_ID],tblAccounts[Include],FALSE),FALSE),SUMIFS(tblAcctSummary[Fees_Base],tblAcctSummary[Account_ID],A76),0)) | M76: =IF(A76="","",IF(IFERROR(XLOOKUP(A76,tblAccounts[Account_ID],tblAccounts[Include],FALSE),FALSE),SUMIFS(tblAcctSummary[Taxes_Base],tblAcctSummary[Account_ID],A76),0)) | N76: =IF(A76="","",IF(IFERROR(XLOOKUP(A76,tblAccounts[Account_ID],tblAccounts[Include],FALSE),FALSE),IFERROR(SUMPRODUCT(tblAcctSummary[Return_Period],tblAcctSummary[Begin_Balance_Base],--(tblAcctSummary[Account_ID]=A76))/IF(SUMIFS(tblAcctSummary[Begin_Balance_Base],tblAcctSummary[Account_ID],A76)=0,NA(),SUMIFS(tblAcctSummary[Begin_Balance_Base],tblAcctSummary[Account_ID],A76)),0),0))
A77: =IFERROR(INDEX(tblAccounts[Account_ID],74),"") | B77: =IF(A77="","",IFERROR(XLOOKUP(A77,tblAccounts[Account_ID],tblAccounts[Account_Name],""),"")) | C77: =IF(A77="","",IFERROR(XLOOKUP(A77,tblAccounts[Account_ID],tblAccounts[Household_ID],""),"")) | D77: =IF(A77="","",IF(IFERROR(XLOOKUP(A77,tblAccounts[Account_ID],tblAccounts[Include],FALSE),FALSE),SUMIFS(tblAcctSummary[Begin_Balance_Base],tblAcctSummary[Account_ID],A77),0)) | E77: =IF(A77="","",IF(IFERROR(XLOOKUP(A77,tblAccounts[Account_ID],tblAccounts[Include],FALSE),FALSE),SUMIFS(tblAcctSummary[End_Balance_Base],tblAcctSummary[Account_ID],A77),0)) | F77: =IF(A77="","",IF(IFERROR(XLOOKUP(A77,tblAccounts[Account_ID],tblAccounts[Include],FALSE),FALSE),SUMIFS(tblAcctSummary[Net_Contrib_Base],tblAcctSummary[Account_ID],A77),0)) | G77: =IF(A77="","",IF(IFERROR(XLOOKUP(A77,tblAccounts[Account_ID],tblAccounts[Include],FALSE),FALSE),SUMIFS(tblAcctSummary[Income_Interest_Base],tblAcctSummary[Account_ID],A77),0)) | H77: =IF(A77="","",IF(IFERROR(XLOOKUP(A77,tblAccounts[Account_ID],tblAccounts[Include],FALSE),FALSE),SUMIFS(tblAcctSummary[Income_Dividends_Base],tblAcctSummary[Account_ID],A77),0)) | I77: =IF(A77="","",IF(IFERROR(XLOOKUP(A77,tblAccounts[Account_ID],tblAccounts[Include],FALSE),FALSE),SUMIFS(tblAcctSummary[Income_Other_Base],tblAcctSummary[Account_ID],A77),0)) | J77: =IF(A77="","",SUM(G77:I77)) | K77: =IF(A77="","",IF(IFERROR(XLOOKUP(A77,tblAccounts[Account_ID],tblAccounts[Include],FALSE),FALSE),SUMIFS(tblAcctSummary[Realized_GL_Base],tblAcctSummary[Account_ID],A77),0)) | L77: =IF(A77="","",IF(IFERROR(XLOOKUP(A77,tblAccounts[Account_ID],tblAccounts[Include],FALSE),FALSE),SUMIFS(tblAcctSummary[Fees_Base],tblAcctSummary[Account_ID],A77),0)) | M77: =IF(A77="","",IF(IFERROR(XLOOKUP(A77,tblAccounts[Account_ID],tblAccounts[Include],FALSE),FALSE),SUMIFS(tblAcctSummary[Taxes_Base],tblAcctSummary[Account_ID],A77),0)) | N77: =IF(A77="","",IF(IFERROR(XLOOKUP(A77,tblAccounts[Account_ID],tblAccounts[Include],FALSE),FALSE),IFERROR(SUMPRODUCT(tblAcctSummary[Return_Period],tblAcctSummary[Begin_Balance_Base],--(tblAcctSummary[Account_ID]=A77))/IF(SUMIFS(tblAcctSummary[Begin_Balance_Base],tblAcctSummary[Account_ID],A77)=0,NA(),SUMIFS(tblAcctSummary[Begin_Balance_Base],tblAcctSummary[Account_ID],A77)),0),0))
A78: =IFERROR(INDEX(tblAccounts[Account_ID],75),"") | B78: =IF(A78="","",IFERROR(XLOOKUP(A78,tblAccounts[Account_ID],tblAccounts[Account_Name],""),"")) | C78: =IF(A78="","",IFERROR(XLOOKUP(A78,tblAccounts[Account_ID],tblAccounts[Household_ID],""),"")) | D78: =IF(A78="","",IF(IFERROR(XLOOKUP(A78,tblAccounts[Account_ID],tblAccounts[Include],FALSE),FALSE),SUMIFS(tblAcctSummary[Begin_Balance_Base],tblAcctSummary[Account_ID],A78),0)) | E78: =IF(A78="","",IF(IFERROR(XLOOKUP(A78,tblAccounts[Account_ID],tblAccounts[Include],FALSE),FALSE),SUMIFS(tblAcctSummary[End_Balance_Base],tblAcctSummary[Account_ID],A78),0)) | F78: =IF(A78="","",IF(IFERROR(XLOOKUP(A78,tblAccounts[Account_ID],tblAccounts[Include],FALSE),FALSE),SUMIFS(tblAcctSummary[Net_Contrib_Base],tblAcctSummary[Account_ID],A78),0)) | G78: =IF(A78="","",IF(IFERROR(XLOOKUP(A78,tblAccounts[Account_ID],tblAccounts[Include],FALSE),FALSE),SUMIFS(tblAcctSummary[Income_Interest_Base],tblAcctSummary[Account_ID],A78),0)) | H78: =IF(A78="","",IF(IFERROR(XLOOKUP(A78,tblAccounts[Account_ID],tblAccounts[Include],FALSE),FALSE),SUMIFS(tblAcctSummary[Income_Dividends_Base],tblAcctSummary[Account_ID],A78),0)) | I78: =IF(A78="","",IF(IFERROR(XLOOKUP(A78,tblAccounts[Account_ID],tblAccounts[Include],FALSE),FALSE),SUMIFS(tblAcctSummary[Income_Other_Base],tblAcctSummary[Account_ID],A78),0)) | J78: =IF(A78="","",SUM(G78:I78)) | K78: =IF(A78="","",IF(IFERROR(XLOOKUP(A78,tblAccounts[Account_ID],tblAccounts[Include],FALSE),FALSE),SUMIFS(tblAcctSummary[Realized_GL_Base],tblAcctSummary[Account_ID],A78),0)) | L78: =IF(A78="","",IF(IFERROR(XLOOKUP(A78,tblAccounts[Account_ID],tblAccounts[Include],FALSE),FALSE),SUMIFS(tblAcctSummary[Fees_Base],tblAcctSummary[Account_ID],A78),0)) | M78: =IF(A78="","",IF(IFERROR(XLOOKUP(A78,tblAccounts[Account_ID],tblAccounts[Include],FALSE),FALSE),SUMIFS(tblAcctSummary[Taxes_Base],tblAcctSummary[Account_ID],A78),0)) | N78: =IF(A78="","",IF(IFERROR(XLOOKUP(A78,tblAccounts[Account_ID],tblAccounts[Include],FALSE),FALSE),IFERROR(SUMPRODUCT(tblAcctSummary[Return_Period],tblAcctSummary[Begin_Balance_Base],--(tblAcctSummary[Account_ID]=A78))/IF(SUMIFS(tblAcctSummary[Begin_Balance_Base],tblAcctSummary[Account_ID],A78)=0,NA(),SUMIFS(tblAcctSummary[Begin_Balance_Base],tblAcctSummary[Account_ID],A78)),0),0))
A79: =IFERROR(INDEX(tblAccounts[Account_ID],76),"") | B79: =IF(A79="","",IFERROR(XLOOKUP(A79,tblAccounts[Account_ID],tblAccounts[Account_Name],""),"")) | C79: =IF(A79="","",IFERROR(XLOOKUP(A79,tblAccounts[Account_ID],tblAccounts[Household_ID],""),"")) | D79: =IF(A79="","",IF(IFERROR(XLOOKUP(A79,tblAccounts[Account_ID],tblAccounts[Include],FALSE),FALSE),SUMIFS(tblAcctSummary[Begin_Balance_Base],tblAcctSummary[Account_ID],A79),0)) | E79: =IF(A79="","",IF(IFERROR(XLOOKUP(A79,tblAccounts[Account_ID],tblAccounts[Include],FALSE),FALSE),SUMIFS(tblAcctSummary[End_Balance_Base],tblAcctSummary[Account_ID],A79),0)) | F79: =IF(A79="","",IF(IFERROR(XLOOKUP(A79,tblAccounts[Account_ID],tblAccounts[Include],FALSE),FALSE),SUMIFS(tblAcctSummary[Net_Contrib_Base],tblAcctSummary[Account_ID],A79),0)) | G79: =IF(A79="","",IF(IFERROR(XLOOKUP(A79,tblAccounts[Account_ID],tblAccounts[Include],FALSE),FALSE),SUMIFS(tblAcctSummary[Income_Interest_Base],tblAcctSummary[Account_ID],A79),0)) | H79: =IF(A79="","",IF(IFERROR(XLOOKUP(A79,tblAccounts[Account_ID],tblAccounts[Include],FALSE),FALSE),SUMIFS(tblAcctSummary[Income_Dividends_Base],tblAcctSummary[Account_ID],A79),0)) | I79: =IF(A79="","",IF(IFERROR(XLOOKUP(A79,tblAccounts[Account_ID],tblAccounts[Include],FALSE),FALSE),SUMIFS(tblAcctSummary[Income_Other_Base],tblAcctSummary[Account_ID],A79),0)) | J79: =IF(A79="","",SUM(G79:I79)) | K79: =IF(A79="","",IF(IFERROR(XLOOKUP(A79,tblAccounts[Account_ID],tblAccounts[Include],FALSE),FALSE),SUMIFS(tblAcctSummary[Realized_GL_Base],tblAcctSummary[Account_ID],A79),0)) | L79: =IF(A79="","",IF(IFERROR(XLOOKUP(A79,tblAccounts[Account_ID],tblAccounts[Include],FALSE),FALSE),SUMIFS(tblAcctSummary[Fees_Base],tblAcctSummary[Account_ID],A79),0)) | M79: =IF(A79="","",IF(IFERROR(XLOOKUP(A79,tblAccounts[Account_ID],tblAccounts[Include],FALSE),FALSE),SUMIFS(tblAcctSummary[Taxes_Base],tblAcctSummary[Account_ID],A79),0)) | N79: =IF(A79="","",IF(IFERROR(XLOOKUP(A79,tblAccounts[Account_ID],tblAccounts[Include],FALSE),FALSE),IFERROR(SUMPRODUCT(tblAcctSummary[Return_Period],tblAcctSummary[Begin_Balance_Base],--(tblAcctSummary[Account_ID]=A79))/IF(SUMIFS(tblAcctSummary[Begin_Balance_Base],tblAcctSummary[Account_ID],A79)=0,NA(),SUMIFS(tblAcctSummary[Begin_Balance_Base],tblAcctSummary[Account_ID],A79)),0),0))
A80: =IFERROR(INDEX(tblAccounts[Account_ID],77),"") | B80: =IF(A80="","",IFERROR(XLOOKUP(A80,tblAccounts[Account_ID],tblAccounts[Account_Name],""),"")) | C80: =IF(A80="","",IFERROR(XLOOKUP(A80,tblAccounts[Account_ID],tblAccounts[Household_ID],""),"")) | D80: =IF(A80="","",IF(IFERROR(XLOOKUP(A80,tblAccounts[Account_ID],tblAccounts[Include],FALSE),FALSE),SUMIFS(tblAcctSummary[Begin_Balance_Base],tblAcctSummary[Account_ID],A80),0)) | E80: =IF(A80="","",IF(IFERROR(XLOOKUP(A80,tblAccounts[Account_ID],tblAccounts[Include],FALSE),FALSE),SUMIFS(tblAcctSummary[End_Balance_Base],tblAcctSummary[Account_ID],A80),0)) | F80: =IF(A80="","",IF(IFERROR(XLOOKUP(A80,tblAccounts[Account_ID],tblAccounts[Include],FALSE),FALSE),SUMIFS(tblAcctSummary[Net_Contrib_Base],tblAcctSummary[Account_ID],A80),0)) | G80: =IF(A80="","",IF(IFERROR(XLOOKUP(A80,tblAccounts[Account_ID],tblAccounts[Include],FALSE),FALSE),SUMIFS(tblAcctSummary[Income_Interest_Base],tblAcctSummary[Account_ID],A80),0)) | H80: =IF(A80="","",IF(IFERROR(XLOOKUP(A80,tblAccounts[Account_ID],tblAccounts[Include],FALSE),FALSE),SUMIFS(tblAcctSummary[Income_Dividends_Base],tblAcctSummary[Account_ID],A80),0)) | I80: =IF(A80="","",IF(IFERROR(XLOOKUP(A80,tblAccounts[Account_ID],tblAccounts[Include],FALSE),FALSE),SUMIFS(tblAcctSummary[Income_Other_Base],tblAcctSummary[Account_ID],A80),0)) | J80: =IF(A80="","",SUM(G80:I80)) | K80: =IF(A80="","",IF(IFERROR(XLOOKUP(A80,tblAccounts[Account_ID],tblAccounts[Include],FALSE),FALSE),SUMIFS(tblAcctSummary[Realized_GL_Base],tblAcctSummary[Account_ID],A80),0)) | L80: =IF(A80="","",IF(IFERROR(XLOOKUP(A80,tblAccounts[Account_ID],tblAccounts[Include],FALSE),FALSE),SUMIFS(tblAcctSummary[Fees_Base],tblAcctSummary[Account_ID],A80),0)) | M80: =IF(A80="","",IF(IFERROR(XLOOKUP(A80,tblAccounts[Account_ID],tblAccounts[Include],FALSE),FALSE),SUMIFS(tblAcctSummary[Taxes_Base],tblAcctSummary[Account_ID],A80),0)) | N80: =IF(A80="","",IF(IFERROR(XLOOKUP(A80,tblAccounts[Account_ID],tblAccounts[Include],FALSE),FALSE),IFERROR(SUMPRODUCT(tblAcctSummary[Return_Period],tblAcctSummary[Begin_Balance_Base],--(tblAcctSummary[Account_ID]=A80))/IF(SUMIFS(tblAcctSummary[Begin_Balance_Base],tblAcctSummary[Account_ID],A80)=0,NA(),SUMIFS(tblAcctSummary[Begin_Balance_Base],tblAcctSummary[Account_ID],A80)),0),0))
A81: =IFERROR(INDEX(tblAccounts[Account_ID],78),"") | B81: =IF(A81="","",IFERROR(XLOOKUP(A81,tblAccounts[Account_ID],tblAccounts[Account_Name],""),"")) | C81: =IF(A81="","",IFERROR(XLOOKUP(A81,tblAccounts[Account_ID],tblAccounts[Household_ID],""),"")) | D81: =IF(A81="","",IF(IFERROR(XLOOKUP(A81,tblAccounts[Account_ID],tblAccounts[Include],FALSE),FALSE),SUMIFS(tblAcctSummary[Begin_Balance_Base],tblAcctSummary[Account_ID],A81),0)) | E81: =IF(A81="","",IF(IFERROR(XLOOKUP(A81,tblAccounts[Account_ID],tblAccounts[Include],FALSE),FALSE),SUMIFS(tblAcctSummary[End_Balance_Base],tblAcctSummary[Account_ID],A81),0)) | F81: =IF(A81="","",IF(IFERROR(XLOOKUP(A81,tblAccounts[Account_ID],tblAccounts[Include],FALSE),FALSE),SUMIFS(tblAcctSummary[Net_Contrib_Base],tblAcctSummary[Account_ID],A81),0)) | G81: =IF(A81="","",IF(IFERROR(XLOOKUP(A81,tblAccounts[Account_ID],tblAccounts[Include],FALSE),FALSE),SUMIFS(tblAcctSummary[Income_Interest_Base],tblAcctSummary[Account_ID],A81),0)) | H81: =IF(A81="","",IF(IFERROR(XLOOKUP(A81,tblAccounts[Account_ID],tblAccounts[Include],FALSE),FALSE),SUMIFS(tblAcctSummary[Income_Dividends_Base],tblAcctSummary[Account_ID],A81),0)) | I81: =IF(A81="","",IF(IFERROR(XLOOKUP(A81,tblAccounts[Account_ID],tblAccounts[Include],FALSE),FALSE),SUMIFS(tblAcctSummary[Income_Other_Base],tblAcctSummary[Account_ID],A81),0)) | J81: =IF(A81="","",SUM(G81:I81)) | K81: =IF(A81="","",IF(IFERROR(XLOOKUP(A81,tblAccounts[Account_ID],tblAccounts[Include],FALSE),FALSE),SUMIFS(tblAcctSummary[Realized_GL_Base],tblAcctSummary[Account_ID],A81),0)) | L81: =IF(A81="","",IF(IFERROR(XLOOKUP(A81,tblAccounts[Account_ID],tblAccounts[Include],FALSE),FALSE),SUMIFS(tblAcctSummary[Fees_Base],tblAcctSummary[Account_ID],A81),0)) | M81: =IF(A81="","",IF(IFERROR(XLOOKUP(A81,tblAccounts[Account_ID],tblAccounts[Include],FALSE),FALSE),SUMIFS(tblAcctSummary[Taxes_Base],tblAcctSummary[Account_ID],A81),0)) | N81: =IF(A81="","",IF(IFERROR(XLOOKUP(A81,tblAccounts[Account_ID],tblAccounts[Include],FALSE),FALSE),IFERROR(SUMPRODUCT(tblAcctSummary[Return_Period],tblAcctSummary[Begin_Balance_Base],--(tblAcctSummary[Account_ID]=A81))/IF(SUMIFS(tblAcctSummary[Begin_Balance_Base],tblAcctSummary[Account_ID],A81)=0,NA(),SUMIFS(tblAcctSummary[Begin_Balance_Base],tblAcctSummary[Account_ID],A81)),0),0))
A82: =IFERROR(INDEX(tblAccounts[Account_ID],79),"") | B82: =IF(A82="","",IFERROR(XLOOKUP(A82,tblAccounts[Account_ID],tblAccounts[Account_Name],""),"")) | C82: =IF(A82="","",IFERROR(XLOOKUP(A82,tblAccounts[Account_ID],tblAccounts[Household_ID],""),"")) | D82: =IF(A82="","",IF(IFERROR(XLOOKUP(A82,tblAccounts[Account_ID],tblAccounts[Include],FALSE),FALSE),SUMIFS(tblAcctSummary[Begin_Balance_Base],tblAcctSummary[Account_ID],A82),0)) | E82: =IF(A82="","",IF(IFERROR(XLOOKUP(A82,tblAccounts[Account_ID],tblAccounts[Include],FALSE),FALSE),SUMIFS(tblAcctSummary[End_Balance_Base],tblAcctSummary[Account_ID],A82),0)) | F82: =IF(A82="","",IF(IFERROR(XLOOKUP(A82,tblAccounts[Account_ID],tblAccounts[Include],FALSE),FALSE),SUMIFS(tblAcctSummary[Net_Contrib_Base],tblAcctSummary[Account_ID],A82),0)) | G82: =IF(A82="","",IF(IFERROR(XLOOKUP(A82,tblAccounts[Account_ID],tblAccounts[Include],FALSE),FALSE),SUMIFS(tblAcctSummary[Income_Interest_Base],tblAcctSummary[Account_ID],A82),0)) | H82: =IF(A82="","",IF(IFERROR(XLOOKUP(A82,tblAccounts[Account_ID],tblAccounts[Include],FALSE),FALSE),SUMIFS(tblAcctSummary[Income_Dividends_Base],tblAcctSummary[Account_ID],A82),0)) | I82: =IF(A82="","",IF(IFERROR(XLOOKUP(A82,tblAccounts[Account_ID],tblAccounts[Include],FALSE),FALSE),SUMIFS(tblAcctSummary[Income_Other_Base],tblAcctSummary[Account_ID],A82),0)) | J82: =IF(A82="","",SUM(G82:I82)) | K82: =IF(A82="","",IF(IFERROR(XLOOKUP(A82,tblAccounts[Account_ID],tblAccounts[Include],FALSE),FALSE),SUMIFS(tblAcctSummary[Realized_GL_Base],tblAcctSummary[Account_ID],A82),0)) | L82: =IF(A82="","",IF(IFERROR(XLOOKUP(A82,tblAccounts[Account_ID],tblAccounts[Include],FALSE),FALSE),SUMIFS(tblAcctSummary[Fees_Base],tblAcctSummary[Account_ID],A82),0)) | M82: =IF(A82="","",IF(IFERROR(XLOOKUP(A82,tblAccounts[Account_ID],tblAccounts[Include],FALSE),FALSE),SUMIFS(tblAcctSummary[Taxes_Base],tblAcctSummary[Account_ID],A82),0)) | N82: =IF(A82="","",IF(IFERROR(XLOOKUP(A82,tblAccounts[Account_ID],tblAccounts[Include],FALSE),FALSE),IFERROR(SUMPRODUCT(tblAcctSummary[Return_Period],tblAcctSummary[Begin_Balance_Base],--(tblAcctSummary[Account_ID]=A82))/IF(SUMIFS(tblAcctSummary[Begin_Balance_Base],tblAcctSummary[Account_ID],A82)=0,NA(),SUMIFS(tblAcctSummary[Begin_Balance_Base],tblAcctSummary[Account_ID],A82)),0),0))
A83: =IFERROR(INDEX(tblAccounts[Account_ID],80),"") | B83: =IF(A83="","",IFERROR(XLOOKUP(A83,tblAccounts[Account_ID],tblAccounts[Account_Name],""),"")) | C83: =IF(A83="","",IFERROR(XLOOKUP(A83,tblAccounts[Account_ID],tblAccounts[Household_ID],""),"")) | D83: =IF(A83="","",IF(IFERROR(XLOOKUP(A83,tblAccounts[Account_ID],tblAccounts[Include],FALSE),FALSE),SUMIFS(tblAcctSummary[Begin_Balance_Base],tblAcctSummary[Account_ID],A83),0)) | E83: =IF(A83="","",IF(IFERROR(XLOOKUP(A83,tblAccounts[Account_ID],tblAccounts[Include],FALSE),FALSE),SUMIFS(tblAcctSummary[End_Balance_Base],tblAcctSummary[Account_ID],A83),0)) | F83: =IF(A83="","",IF(IFERROR(XLOOKUP(A83,tblAccounts[Account_ID],tblAccounts[Include],FALSE),FALSE),SUMIFS(tblAcctSummary[Net_Contrib_Base],tblAcctSummary[Account_ID],A83),0)) | G83: =IF(A83="","",IF(IFERROR(XLOOKUP(A83,tblAccounts[Account_ID],tblAccounts[Include],FALSE),FALSE),SUMIFS(tblAcctSummary[Income_Interest_Base],tblAcctSummary[Account_ID],A83),0)) | H83: =IF(A83="","",IF(IFERROR(XLOOKUP(A83,tblAccounts[Account_ID],tblAccounts[Include],FALSE),FALSE),SUMIFS(tblAcctSummary[Income_Dividends_Base],tblAcctSummary[Account_ID],A83),0)) | I83: =IF(A83="","",IF(IFERROR(XLOOKUP(A83,tblAccounts[Account_ID],tblAccounts[Include],FALSE),FALSE),SUMIFS(tblAcctSummary[Income_Other_Base],tblAcctSummary[Account_ID],A83),0)) | J83: =IF(A83="","",SUM(G83:I83)) | K83: =IF(A83="","",IF(IFERROR(XLOOKUP(A83,tblAccounts[Account_ID],tblAccounts[Include],FALSE),FALSE),SUMIFS(tblAcctSummary[Realized_GL_Base],tblAcctSummary[Account_ID],A83),0)) | L83: =IF(A83="","",IF(IFERROR(XLOOKUP(A83,tblAccounts[Account_ID],tblAccounts[Include],FALSE),FALSE),SUMIFS(tblAcctSummary[Fees_Base],tblAcctSummary[Account_ID],A83),0)) | M83: =IF(A83="","",IF(IFERROR(XLOOKUP(A83,tblAccounts[Account_ID],tblAccounts[Include],FALSE),FALSE),SUMIFS(tblAcctSummary[Taxes_Base],tblAcctSummary[Account_ID],A83),0)) | N83: =IF(A83="","",IF(IFERROR(XLOOKUP(A83,tblAccounts[Account_ID],tblAccounts[Include],FALSE),FALSE),IFERROR(SUMPRODUCT(tblAcctSummary[Return_Period],tblAcctSummary[Begin_Balance_Base],--(tblAcctSummary[Account_ID]=A83))/IF(SUMIFS(tblAcctSummary[Begin_Balance_Base],tblAcctSummary[Account_ID],A83)=0,NA(),SUMIFS(tblAcctSummary[Begin_Balance_Base],tblAcctSummary[Account_ID],A83)),0),0))
A84: =IFERROR(INDEX(tblAccounts[Account_ID],81),"") | B84: =IF(A84="","",IFERROR(XLOOKUP(A84,tblAccounts[Account_ID],tblAccounts[Account_Name],""),"")) | C84: =IF(A84="","",IFERROR(XLOOKUP(A84,tblAccounts[Account_ID],tblAccounts[Household_ID],""),"")) | D84: =IF(A84="","",IF(IFERROR(XLOOKUP(A84,tblAccounts[Account_ID],tblAccounts[Include],FALSE),FALSE),SUMIFS(tblAcctSummary[Begin_Balance_Base],tblAcctSummary[Account_ID],A84),0)) | E84: =IF(A84="","",IF(IFERROR(XLOOKUP(A84,tblAccounts[Account_ID],tblAccounts[Include],FALSE),FALSE),SUMIFS(tblAcctSummary[End_Balance_Base],tblAcctSummary[Account_ID],A84),0)) | F84: =IF(A84="","",IF(IFERROR(XLOOKUP(A84,tblAccounts[Account_ID],tblAccounts[Include],FALSE),FALSE),SUMIFS(tblAcctSummary[Net_Contrib_Base],tblAcctSummary[Account_ID],A84),0)) | G84: =IF(A84="","",IF(IFERROR(XLOOKUP(A84,tblAccounts[Account_ID],tblAccounts[Include],FALSE),FALSE),SUMIFS(tblAcctSummary[Income_Interest_Base],tblAcctSummary[Account_ID],A84),0)) | H84: =IF(A84="","",IF(IFERROR(XLOOKUP(A84,tblAccounts[Account_ID],tblAccounts[Include],FALSE),FALSE),SUMIFS(tblAcctSummary[Income_Dividends_Base],tblAcctSummary[Account_ID],A84),0)) | I84: =IF(A84="","",IF(IFERROR(XLOOKUP(A84,tblAccounts[Account_ID],tblAccounts[Include],FALSE),FALSE),SUMIFS(tblAcctSummary[Income_Other_Base],tblAcctSummary[Account_ID],A84),0)) | J84: =IF(A84="","",SUM(G84:I84)) | K84: =IF(A84="","",IF(IFERROR(XLOOKUP(A84,tblAccounts[Account_ID],tblAccounts[Include],FALSE),FALSE),SUMIFS(tblAcctSummary[Realized_GL_Base],tblAcctSummary[Account_ID],A84),0)) | L84: =IF(A84="","",IF(IFERROR(XLOOKUP(A84,tblAccounts[Account_ID],tblAccounts[Include],FALSE),FALSE),SUMIFS(tblAcctSummary[Fees_Base],tblAcctSummary[Account_ID],A84),0)) | M84: =IF(A84="","",IF(IFERROR(XLOOKUP(A84,tblAccounts[Account_ID],tblAccounts[Include],FALSE),FALSE),SUMIFS(tblAcctSummary[Taxes_Base],tblAcctSummary[Account_ID],A84),0)) | N84: =IF(A84="","",IF(IFERROR(XLOOKUP(A84,tblAccounts[Account_ID],tblAccounts[Include],FALSE),FALSE),IFERROR(SUMPRODUCT(tblAcctSummary[Return_Period],tblAcctSummary[Begin_Balance_Base],--(tblAcctSummary[Account_ID]=A84))/IF(SUMIFS(tblAcctSummary[Begin_Balance_Base],tblAcctSummary[Account_ID],A84)=0,NA(),SUMIFS(tblAcctSummary[Begin_Balance_Base],tblAcctSummary[Account_ID],A84)),0),0))
A85: =IFERROR(INDEX(tblAccounts[Account_ID],82),"") | B85: =IF(A85="","",IFERROR(XLOOKUP(A85,tblAccounts[Account_ID],tblAccounts[Account_Name],""),"")) | C85: =IF(A85="","",IFERROR(XLOOKUP(A85,tblAccounts[Account_ID],tblAccounts[Household_ID],""),"")) | D85: =IF(A85="","",IF(IFERROR(XLOOKUP(A85,tblAccounts[Account_ID],tblAccounts[Include],FALSE),FALSE),SUMIFS(tblAcctSummary[Begin_Balance_Base],tblAcctSummary[Account_ID],A85),0)) | E85: =IF(A85="","",IF(IFERROR(XLOOKUP(A85,tblAccounts[Account_ID],tblAccounts[Include],FALSE),FALSE),SUMIFS(tblAcctSummary[End_Balance_Base],tblAcctSummary[Account_ID],A85),0)) | F85: =IF(A85="","",IF(IFERROR(XLOOKUP(A85,tblAccounts[Account_ID],tblAccounts[Include],FALSE),FALSE),SUMIFS(tblAcctSummary[Net_Contrib_Base],tblAcctSummary[Account_ID],A85),0)) | G85: =IF(A85="","",IF(IFERROR(XLOOKUP(A85,tblAccounts[Account_ID],tblAccounts[Include],FALSE),FALSE),SUMIFS(tblAcctSummary[Income_Interest_Base],tblAcctSummary[Account_ID],A85),0)) | H85: =IF(A85="","",IF(IFERROR(XLOOKUP(A85,tblAccounts[Account_ID],tblAccounts[Include],FALSE),FALSE),SUMIFS(tblAcctSummary[Income_Dividends_Base],tblAcctSummary[Account_ID],A85),0)) | I85: =IF(A85="","",IF(IFERROR(XLOOKUP(A85,tblAccounts[Account_ID],tblAccounts[Include],FALSE),FALSE),SUMIFS(tblAcctSummary[Income_Other_Base],tblAcctSummary[Account_ID],A85),0)) | J85: =IF(A85="","",SUM(G85:I85)) | K85: =IF(A85="","",IF(IFERROR(XLOOKUP(A85,tblAccounts[Account_ID],tblAccounts[Include],FALSE),FALSE),SUMIFS(tblAcctSummary[Realized_GL_Base],tblAcctSummary[Account_ID],A85),0)) | L85: =IF(A85="","",IF(IFERROR(XLOOKUP(A85,tblAccounts[Account_ID],tblAccounts[Include],FALSE),FALSE),SUMIFS(tblAcctSummary[Fees_Base],tblAcctSummary[Account_ID],A85),0)) | M85: =IF(A85="","",IF(IFERROR(XLOOKUP(A85,tblAccounts[Account_ID],tblAccounts[Include],FALSE),FALSE),SUMIFS(tblAcctSummary[Taxes_Base],tblAcctSummary[Account_ID],A85),0)) | N85: =IF(A85="","",IF(IFERROR(XLOOKUP(A85,tblAccounts[Account_ID],tblAccounts[Include],FALSE),FALSE),IFERROR(SUMPRODUCT(tblAcctSummary[Return_Period],tblAcctSummary[Begin_Balance_Base],--(tblAcctSummary[Account_ID]=A85))/IF(SUMIFS(tblAcctSummary[Begin_Balance_Base],tblAcctSummary[Account_ID],A85)=0,NA(),SUMIFS(tblAcctSummary[Begin_Balance_Base],tblAcctSummary[Account_ID],A85)),0),0))
A86: =IFERROR(INDEX(tblAccounts[Account_ID],83),"") | B86: =IF(A86="","",IFERROR(XLOOKUP(A86,tblAccounts[Account_ID],tblAccounts[Account_Name],""),"")) | C86: =IF(A86="","",IFERROR(XLOOKUP(A86,tblAccounts[Account_ID],tblAccounts[Household_ID],""),"")) | D86: =IF(A86="","",IF(IFERROR(XLOOKUP(A86,tblAccounts[Account_ID],tblAccounts[Include],FALSE),FALSE),SUMIFS(tblAcctSummary[Begin_Balance_Base],tblAcctSummary[Account_ID],A86),0)) | E86: =IF(A86="","",IF(IFERROR(XLOOKUP(A86,tblAccounts[Account_ID],tblAccounts[Include],FALSE),FALSE),SUMIFS(tblAcctSummary[End_Balance_Base],tblAcctSummary[Account_ID],A86),0)) | F86: =IF(A86="","",IF(IFERROR(XLOOKUP(A86,tblAccounts[Account_ID],tblAccounts[Include],FALSE),FALSE),SUMIFS(tblAcctSummary[Net_Contrib_Base],tblAcctSummary[Account_ID],A86),0)) | G86: =IF(A86="","",IF(IFERROR(XLOOKUP(A86,tblAccounts[Account_ID],tblAccounts[Include],FALSE),FALSE),SUMIFS(tblAcctSummary[Income_Interest_Base],tblAcctSummary[Account_ID],A86),0)) | H86: =IF(A86="","",IF(IFERROR(XLOOKUP(A86,tblAccounts[Account_ID],tblAccounts[Include],FALSE),FALSE),SUMIFS(tblAcctSummary[Income_Dividends_Base],tblAcctSummary[Account_ID],A86),0)) | I86: =IF(A86="","",IF(IFERROR(XLOOKUP(A86,tblAccounts[Account_ID],tblAccounts[Include],FALSE),FALSE),SUMIFS(tblAcctSummary[Income_Other_Base],tblAcctSummary[Account_ID],A86),0)) | J86: =IF(A86="","",SUM(G86:I86)) | K86: =IF(A86="","",IF(IFERROR(XLOOKUP(A86,tblAccounts[Account_ID],tblAccounts[Include],FALSE),FALSE),SUMIFS(tblAcctSummary[Realized_GL_Base],tblAcctSummary[Account_ID],A86),0)) | L86: =IF(A86="","",IF(IFERROR(XLOOKUP(A86,tblAccounts[Account_ID],tblAccounts[Include],FALSE),FALSE),SUMIFS(tblAcctSummary[Fees_Base],tblAcctSummary[Account_ID],A86),0)) | M86: =IF(A86="","",IF(IFERROR(XLOOKUP(A86,tblAccounts[Account_ID],tblAccounts[Include],FALSE),FALSE),SUMIFS(tblAcctSummary[Taxes_Base],tblAcctSummary[Account_ID],A86),0)) | N86: =IF(A86="","",IF(IFERROR(XLOOKUP(A86,tblAccounts[Account_ID],tblAccounts[Include],FALSE),FALSE),IFERROR(SUMPRODUCT(tblAcctSummary[Return_Period],tblAcctSummary[Begin_Balance_Base],--(tblAcctSummary[Account_ID]=A86))/IF(SUMIFS(tblAcctSummary[Begin_Balance_Base],tblAcctSummary[Account_ID],A86)=0,NA(),SUMIFS(tblAcctSummary[Begin_Balance_Base],tblAcctSummary[Account_ID],A86)),0),0))
A87: =IFERROR(INDEX(tblAccounts[Account_ID],84),"") | B87: =IF(A87="","",IFERROR(XLOOKUP(A87,tblAccounts[Account_ID],tblAccounts[Account_Name],""),"")) | C87: =IF(A87="","",IFERROR(XLOOKUP(A87,tblAccounts[Account_ID],tblAccounts[Household_ID],""),"")) | D87: =IF(A87="","",IF(IFERROR(XLOOKUP(A87,tblAccounts[Account_ID],tblAccounts[Include],FALSE),FALSE),SUMIFS(tblAcctSummary[Begin_Balance_Base],tblAcctSummary[Account_ID],A87),0)) | E87: =IF(A87="","",IF(IFERROR(XLOOKUP(A87,tblAccounts[Account_ID],tblAccounts[Include],FALSE),FALSE),SUMIFS(tblAcctSummary[End_Balance_Base],tblAcctSummary[Account_ID],A87),0)) | F87: =IF(A87="","",IF(IFERROR(XLOOKUP(A87,tblAccounts[Account_ID],tblAccounts[Include],FALSE),FALSE),SUMIFS(tblAcctSummary[Net_Contrib_Base],tblAcctSummary[Account_ID],A87),0)) | G87: =IF(A87="","",IF(IFERROR(XLOOKUP(A87,tblAccounts[Account_ID],tblAccounts[Include],FALSE),FALSE),SUMIFS(tblAcctSummary[Income_Interest_Base],tblAcctSummary[Account_ID],A87),0)) | H87: =IF(A87="","",IF(IFERROR(XLOOKUP(A87,tblAccounts[Account_ID],tblAccounts[Include],FALSE),FALSE),SUMIFS(tblAcctSummary[Income_Dividends_Base],tblAcctSummary[Account_ID],A87),0)) | I87: =IF(A87="","",IF(IFERROR(XLOOKUP(A87,tblAccounts[Account_ID],tblAccounts[Include],FALSE),FALSE),SUMIFS(tblAcctSummary[Income_Other_Base],tblAcctSummary[Account_ID],A87),0)) | J87: =IF(A87="","",SUM(G87:I87)) | K87: =IF(A87="","",IF(IFERROR(XLOOKUP(A87,tblAccounts[Account_ID],tblAccounts[Include],FALSE),FALSE),SUMIFS(tblAcctSummary[Realized_GL_Base],tblAcctSummary[Account_ID],A87),0)) | L87: =IF(A87="","",IF(IFERROR(XLOOKUP(A87,tblAccounts[Account_ID],tblAccounts[Include],FALSE),FALSE),SUMIFS(tblAcctSummary[Fees_Base],tblAcctSummary[Account_ID],A87),0)) | M87: =IF(A87="","",IF(IFERROR(XLOOKUP(A87,tblAccounts[Account_ID],tblAccounts[Include],FALSE),FALSE),SUMIFS(tblAcctSummary[Taxes_Base],tblAcctSummary[Account_ID],A87),0)) | N87: =IF(A87="","",IF(IFERROR(XLOOKUP(A87,tblAccounts[Account_ID],tblAccounts[Include],FALSE),FALSE),IFERROR(SUMPRODUCT(tblAcctSummary[Return_Period],tblAcctSummary[Begin_Balance_Base],--(tblAcctSummary[Account_ID]=A87))/IF(SUMIFS(tblAcctSummary[Begin_Balance_Base],tblAcctSummary[Account_ID],A87)=0,NA(),SUMIFS(tblAcctSummary[Begin_Balance_Base],tblAcctSummary[Account_ID],A87)),0),0))
A88: =IFERROR(INDEX(tblAccounts[Account_ID],85),"") | B88: =IF(A88="","",IFERROR(XLOOKUP(A88,tblAccounts[Account_ID],tblAccounts[Account_Name],""),"")) | C88: =IF(A88="","",IFERROR(XLOOKUP(A88,tblAccounts[Account_ID],tblAccounts[Household_ID],""),"")) | D88: =IF(A88="","",IF(IFERROR(XLOOKUP(A88,tblAccounts[Account_ID],tblAccounts[Include],FALSE),FALSE),SUMIFS(tblAcctSummary[Begin_Balance_Base],tblAcctSummary[Account_ID],A88),0)) | E88: =IF(A88="","",IF(IFERROR(XLOOKUP(A88,tblAccounts[Account_ID],tblAccounts[Include],FALSE),FALSE),SUMIFS(tblAcctSummary[End_Balance_Base],tblAcctSummary[Account_ID],A88),0)) | F88: =IF(A88="","",IF(IFERROR(XLOOKUP(A88,tblAccounts[Account_ID],tblAccounts[Include],FALSE),FALSE),SUMIFS(tblAcctSummary[Net_Contrib_Base],tblAcctSummary[Account_ID],A88),0)) | G88: =IF(A88="","",IF(IFERROR(XLOOKUP(A88,tblAccounts[Account_ID],tblAccounts[Include],FALSE),FALSE),SUMIFS(tblAcctSummary[Income_Interest_Base],tblAcctSummary[Account_ID],A88),0)) | H88: =IF(A88="","",IF(IFERROR(XLOOKUP(A88,tblAccounts[Account_ID],tblAccounts[Include],FALSE),FALSE),SUMIFS(tblAcctSummary[Income_Dividends_Base],tblAcctSummary[Account_ID],A88),0)) | I88: =IF(A88="","",IF(IFERROR(XLOOKUP(A88,tblAccounts[Account_ID],tblAccounts[Include],FALSE),FALSE),SUMIFS(tblAcctSummary[Income_Other_Base],tblAcctSummary[Account_ID],A88),0)) | J88: =IF(A88="","",SUM(G88:I88)) | K88: =IF(A88="","",IF(IFERROR(XLOOKUP(A88,tblAccounts[Account_ID],tblAccounts[Include],FALSE),FALSE),SUMIFS(tblAcctSummary[Realized_GL_Base],tblAcctSummary[Account_ID],A88),0)) | L88: =IF(A88="","",IF(IFERROR(XLOOKUP(A88,tblAccounts[Account_ID],tblAccounts[Include],FALSE),FALSE),SUMIFS(tblAcctSummary[Fees_Base],tblAcctSummary[Account_ID],A88),0)) | M88: =IF(A88="","",IF(IFERROR(XLOOKUP(A88,tblAccounts[Account_ID],tblAccounts[Include],FALSE),FALSE),SUMIFS(tblAcctSummary[Taxes_Base],tblAcctSummary[Account_ID],A88),0)) | N88: =IF(A88="","",IF(IFERROR(XLOOKUP(A88,tblAccounts[Account_ID],tblAccounts[Include],FALSE),FALSE),IFERROR(SUMPRODUCT(tblAcctSummary[Return_Period],tblAcctSummary[Begin_Balance_Base],--(tblAcctSummary[Account_ID]=A88))/IF(SUMIFS(tblAcctSummary[Begin_Balance_Base],tblAcctSummary[Account_ID],A88)=0,NA(),SUMIFS(tblAcctSummary[Begin_Balance_Base],tblAcctSummary[Account_ID],A88)),0),0))
A89: =IFERROR(INDEX(tblAccounts[Account_ID],86),"") | B89: =IF(A89="","",IFERROR(XLOOKUP(A89,tblAccounts[Account_ID],tblAccounts[Account_Name],""),"")) | C89: =IF(A89="","",IFERROR(XLOOKUP(A89,tblAccounts[Account_ID],tblAccounts[Household_ID],""),"")) | D89: =IF(A89="","",IF(IFERROR(XLOOKUP(A89,tblAccounts[Account_ID],tblAccounts[Include],FALSE),FALSE),SUMIFS(tblAcctSummary[Begin_Balance_Base],tblAcctSummary[Account_ID],A89),0)) | E89: =IF(A89="","",IF(IFERROR(XLOOKUP(A89,tblAccounts[Account_ID],tblAccounts[Include],FALSE),FALSE),SUMIFS(tblAcctSummary[End_Balance_Base],tblAcctSummary[Account_ID],A89),0)) | F89: =IF(A89="","",IF(IFERROR(XLOOKUP(A89,tblAccounts[Account_ID],tblAccounts[Include],FALSE),FALSE),SUMIFS(tblAcctSummary[Net_Contrib_Base],tblAcctSummary[Account_ID],A89),0)) | G89: =IF(A89="","",IF(IFERROR(XLOOKUP(A89,tblAccounts[Account_ID],tblAccounts[Include],FALSE),FALSE),SUMIFS(tblAcctSummary[Income_Interest_Base],tblAcctSummary[Account_ID],A89),0)) | H89: =IF(A89="","",IF(IFERROR(XLOOKUP(A89,tblAccounts[Account_ID],tblAccounts[Include],FALSE),FALSE),SUMIFS(tblAcctSummary[Income_Dividends_Base],tblAcctSummary[Account_ID],A89),0)) | I89: =IF(A89="","",IF(IFERROR(XLOOKUP(A89,tblAccounts[Account_ID],tblAccounts[Include],FALSE),FALSE),SUMIFS(tblAcctSummary[Income_Other_Base],tblAcctSummary[Account_ID],A89),0)) | J89: =IF(A89="","",SUM(G89:I89)) | K89: =IF(A89="","",IF(IFERROR(XLOOKUP(A89,tblAccounts[Account_ID],tblAccounts[Include],FALSE),FALSE),SUMIFS(tblAcctSummary[Realized_GL_Base],tblAcctSummary[Account_ID],A89),0)) | L89: =IF(A89="","",IF(IFERROR(XLOOKUP(A89,tblAccounts[Account_ID],tblAccounts[Include],FALSE),FALSE),SUMIFS(tblAcctSummary[Fees_Base],tblAcctSummary[Account_ID],A89),0)) | M89: =IF(A89="","",IF(IFERROR(XLOOKUP(A89,tblAccounts[Account_ID],tblAccounts[Include],FALSE),FALSE),SUMIFS(tblAcctSummary[Taxes_Base],tblAcctSummary[Account_ID],A89),0)) | N89: =IF(A89="","",IF(IFERROR(XLOOKUP(A89,tblAccounts[Account_ID],tblAccounts[Include],FALSE),FALSE),IFERROR(SUMPRODUCT(tblAcctSummary[Return_Period],tblAcctSummary[Begin_Balance_Base],--(tblAcctSummary[Account_ID]=A89))/IF(SUMIFS(tblAcctSummary[Begin_Balance_Base],tblAcctSummary[Account_ID],A89)=0,NA(),SUMIFS(tblAcctSummary[Begin_Balance_Base],tblAcctSummary[Account_ID],A89)),0),0))
